Workbook
Name Table1: #REF!
Name ___thinkcellf7gEwppKqUWVmG8WHzQ68g: #REF!
Name ___thinkcellGv_HMPayz0.PxVwiQe5IHg: #REF!
Name ___thinkcellsxsFZEKfu0KTlYCYIuITaA: #REF!
Name ___thinkcellUJcvPfgxy0Cqr_m8uCJCKA: #REF!
Name ___thinkcellY0P34UIewEePiRhx5hmEzA: #REF!
Name ___utc: #REF!
Name \_: #REF!
Name \a: #N/A
Name A: #REF!
Name A_Interface_IPoFEGE.EthREDPort: #REF!
Name A_Interface_IPoFEGE.IP_Path: #REF!
Name AA: #REF!
Name AAEspinos: #REF!
Name Abis_Interface_eGBTS.IP_Path: #REF!
Name Abis_Interface_IPoFEGE.IP_PATH: #REF!
Name adaFASFQAF: #REF!
Name afasfsgg: #REF!
Name Andra_pradesh: #REF!
Name ARBO001: #REF!
Name AREA: '[1]Fishbone Validation'!$D$3:$D$6
Name Area_Cat: #REF!
Name asas: #REF!
Name asd: #REF!
Name asdas: #REF!
Name asdasdasfvsaf: #REF!
Name asdasfafqf: #REF!
Name asdasfasfasf: #REF!
Name ASDASFASFQ: #REF!
Name asdfas: #REF!
Name asdfasf: #REF!
Name asdS: #REF!
Name asfasdf: #REF!
Name asfasfaf: #REF!
Name asfassd: #REF!
Name asfdsf: #REF!
Name asfsgdfhgjdh: #REF!
Name asfzxc: #REF!
Name asgthaththtth: #REF!
Name AUGPORTUTIL: #REF!
Name Availability: #REF!
Name BAND: #REF!
Name BATCH1TO5: #REF!
Name BATCH4TO5: #REF!
Name batch6: #REF!
Name batch7new: #REF!
Name BINONDO: #REF!
Name BLDG_TYPE: #REF!
Name BLOOD: #REF!
Name BoardList: #REF!
Name BOQ: #REF!
Name BOQA: #REF!
Name BRY: #REF!
Name BSC_Clock_Configuration.Configure_IP_Clock_Server: #REF!
Name BUDGET: #REF!
Name BUILD: #REF!
Name BY_NATURE_OF_BUS: #REF!
Name CABEX: #REF!
Name CABINET_SPACE: #REF!
Name cards: #REF!

Sheet IRUP SITELIST
A1: =SUBTOTAL(3,A4:A1047896) -> 6 | D1: =SUBTOTAL(3,D4:D1047896) -> 6 | N1: =SUBTOTAL(3,N4:N1010) -> 6 | Q1: =SUBTOTAL(9,Q4:Q1047896) -> 2326.6 | R1: =SUBTOTAL(9,R4:R1047896) -> 657.25 | AP1: PERMITTING | CB1: =SUBTOTAL(9,CB4:CB1009) -> 4.75 | CC1: =SUBTOTAL(9,CC4:CC1009) -> 19
A2: MIGRATION PLAN DATE2957 | B2: STATUS | D2: AREA | E2: LATITUDE | F2: LONGITUDE | G2: CITY | H2: PROVINCE | I2: CSZ | J2: APM ASSIGNED | K2: QTR | L2: WBS CODE | M2: SITE NO | N2: SITE NAME | O2: ARCHITYPE | P2: TONNES CLASSIFICATION | Q2: APPROX TONS | R2: DESIGN TONS | S2: OVERALL MILESTONE | T2: OVERALL PROGRESS | U2: DESIGN WEEK TARGET | V2: DESIGN ORIGINAL TARGET | W2: DESIGN REVISED TARGET COMPLETION | X2: DESIGN STATUS | Y2: SURVEY START | Z2: SURVEY DONE DATE | AA2: DESIGN COMPLETION | AB2: DESIGN SUBMISSION | AC2: DESIGN APPROVED | AD2: DESIGN REMARKS/ ISSUE | AE2: ISP/OSP | AF2: TOTAL WORKING DAYS | AG2: NO. OF MH ACTUAL | AH2: MH ACCESSIBLE | AI2: MH N/ ACCESSIBLE | AJ2: ASPHALTED | AK2: CEMENTED | AL2: BRICKS | AM2: MH INSIDE BLDG | AN2: DESIGN PROGRESS | AO2: PERMITTING WEEK TARGET | AP2: PERMITTING TARGET COMPLETION | AQ2: NEW PERMITTING TARGET | AR2: PERMITTING GENERAL STAUS | AS2: HOA SUBMITTED | AT2: HOA SECURED | AU2: HOA START | AV2: HOA END | AW2: DEVELOPER SUBMITTED | AX2: DEVELOPER secured | AY2: DEVELOPER START | AZ2: DEVELOPER END | BA2: BRGY SUBMITTED | BB2: BRGY PERMIT SECURED | BC2: BARANGAY START | BD2: BRGY END | BE2: LGU PERMIT SUBMITTED | BF2: LGU PERMIT SECURED | BG2: LGU START | BH2: LGU END | BI2: TRAFFIC submitted | BJ2: TRAFFIC PERMIT SECURED | BK2: TRAFFIC START | BL2: TRAFFIC END | BM2: DPWH submitted | BN2: DPWH SECURED | BO2: DPWH START | BP2: DPWH END | BQ2: PERMITTING ISSUE / REMARKS | BR2: PERMITTING PROGESS | BS2: EXTRACTION TARGET START WEEK | BT2: EXTRACTION TARGET START DATE | BU2: REVISED START WEEK | BV2: REVISED EXTRACTION START DATE | BW2: EXTRACTION DONE TARGET WEEK | BX2: EXTRACTION TARGET DONE DATE | BY2: REVISED EXTRACTION DONE DATE | BZ2: REVISION REMARKS | CA2: EXTRACTION START | CB2: EXCAVATION TEAM QUANTITY | CC2: EXTRACTION TEAM QUANTITY | CD2: EXTRACTION DONE DAYS | CE2: SUBCON | CF2: ISP/OSP | CG2: PS NAME | CH2: EXTRACTION STATUS | CI2: EXTRACTION PROGRESS | CJ2: EXTRACTION REMARKS | CK2: ISP EXTRACTION MONTH | CL2: OSP EXTRACTION MONTH | CM2: TOTAL MANHOLE | CN2: CIVIL WORKS MH | CO2: DEWATERING MH | CP2: NO DEWATERING MH | CQ2: TOTAL MANHOLE EXTRACTED | CR2: MANHOLE EXTRACTED GAP | CS2: ISP EXTRACTED | CT2: OSP EXTRACTED | CU2: TOTAL TONS EXTRACTED | CV2: EXTRACTION DONE
A3: Column1 | B3: STATUS | C3: Column2 | D3: AREA | E3: LATITUDE | F3: LONGITUDE | G3: CITY | H3: PROVINCE | I3: CSZ | J3: APM ASSIGNED | K3: QTR | L3: WBS CODE | M3: SITE NO | N3: SITE NAME | O3: ARCHITYPE | P3: TONNES CLASSIFICATION | Q3: APPROX TONS | R3: DESIGN TONS | S3: OVERALL MILESTONE | T3: OVERALL PROGRESS | U3: DESIGN WEEK TARGET | V3: DESIGN ORIGINAL TARGET | W3: DESIGN REVISED TARGET COMPLETION | X3: DESIGN STATUS | Y3: SURVEY START | Z3: SURVEY DONE DATE | AA3: DESIGN COMPLETION | AB3: DESIGN SUBMISSION | AC3: DESIGN APPROVED | AD3: DESIGN REMARKS/ ISSUE | AE3: ISP/OSP | AF3: TOTAL WORKING DAYS | AG3: NO. OF MH ACTUAL22 | AH3: MH ACCESSIBLE2 | AI3: MH N/ ACCESSIBLE2 | AJ3: ASPHALTED2 | AK3: CEMENTED2 | AL3: BRICKS | AM3: MH INSIDE BLDG | AN3: DESIGN PROGRESS | AO3: PERMITTING WEEK TARGET | AP3: PERMITTING TARGET COMPLETION | AQ3: NEW PERMITTING TARGET | AR3: PERMITTING GENERAL STAUS | AS3: HOA SUBMITTED | AT3: HOA SECURED | AU3: HOA START | AV3: HOA END | AW3: DEVELOPER SUBMITTED | AX3: DEVELOPER Secured | AY3: DEVELOPER START | AZ3: DEVELOPER END | BA3: BRGY SUBMITTED | BB3: BRGY PERMIT SECURED | BC3: BARANGAY START | BD3: BRGY END | BE3: LGU PERMIT SUBMITTED | BF3: LGU PERMIT SECURED | BG3: LGU START | BH3: LGU END | BI3: TRAFFIC submitted | BJ3: TRAFFIC PERMIT SECURED | BK3: TRAFFIC START | BL3: TRAFFIC END | BM3: DPWH submitted | BN3: DPWH SECURED | BO3: DPWH START | BP3: DPWH END | BQ3: PERMITTING ISSUE | BR3: PERMITTING PROGESS | BS3: EXTRACTION TARGET START WEEK | BT3: EXTRACTION TARGET START DATE | BU3: REVISED START WEEK | BV3: REVISED EXTRACTION START DATE | BW3: EXTRACTION DONE TARGET WEEK | BX3: EXTRACTION TARGET DONE DATE | BY3: REVISED EXTRACTION DONE DATE | BZ3: REVISION REMARKS | CA3: EXTRACTION START | CB3: EXCAVATION TEAM QUANTITY | CC3: TEAM QUANTITY | CD3: EXTRACTION DONE DAYS | CE3: SUBCON2 | CF3: ISP/OSP2 | CG3: PS NAME2 | CH3: EXTRACTION STATUS | CI3: EXTRACTION PROGRESS | CJ3: EXTRACTION REMARKS | CK3: Column6 | CL3: Column8 | CM3: TOTAL MANHOLE | CN3: CIVIL WORKS MH | CO3: DEWATERING MH | CP3: NO DEWATERING MH | CQ3: TOTAL MANHOLE OPENNED | CR3: MANHOLE OPENNED GAP | CS3: ISP EXTRACTED | CT3: OSP EXTRACTED | CU3: TOTAL TONS EXTRACTED | CV3: EXTRACTION DONE
A4: 46235 | B4: RFE | C4: PART OF 233 | D4: GMM | E4: 14.578856 | F4: 121.00113 | G4: Manila City | H4: Metropolitan Manila | I4: South Manila | J4: Jessa | K4: Q1 | L4: T-37262327I-1-GMM-00002 | M4: IRUP0001 | N4: Paco Exchange | O4: Exchange-L | P4: =IF(OR(NOT(ISNUMBER(Q4)),Q4=0),"NO DATA",IF(Q4<10,"<10 TONNES",">=10 TONNES")) -> >=10 TONNES | Q4: 454.2 | R4: 121.59 | S4: =IF(CH4="CANCELLED","CANCELLED",IF(CV4<>"","EXTRACTION DONE",IF(CH4="ON GOING EXTRACTION","ON GOING EXTRACTION",IF(AR4="RFE","READY FOR EXTRACTION",IF(AR4="ON GOING PERMITTING","ON GOING PERMITTING",IF(AC4<>"","DESIGN APPROVED",IF(AB4<>"","DESIGN SUBMITTED",IF(AA4<>"","DESIGN COMPLETED",IF(Z4<>"","ON GOING DESIGN",IF(Y4<>"","ON GOING SURVEY","NOT STARTED")))))))))) -> ON GOING EXTRACTION | T4: =IFERROR((AN4*33%)+(BR4*27%)+(CI4*40%),0) -> 0.68529412 | U4: =IF(V4>0,WEEKNUM(V4,1)&"-"&YEAR(V4),"") -> 38-2026 | V4: 46282 | W4: =V4 -> 46282 | X4: =IF(AD4>0,"DESIGN WITH CONCERN",IF(AC4>0,"DESIGN APPROVED",IF(AB4>0,"DESIGN FOR APPROVAL",IF(AA4>0,"DESIGN FOR SUBMISSION",IF(Z4>0,"ON GOING DESIGN",IF(Y4>0,"ON GOING SURVEY","FOR SURVEY")))))) -> DESIGN APPROVED | Y4: 46275 | Z4: 46281 | AA4: 46282 | AB4: 46282 | AC4: 46282 | AE4: Both | AF4: =IF(AA4-Y4<0,0,AA4-Y4) -> 7 | AG4: =AH4+AI4 -> 136 | AH4: 72 | AI4: 64 | AJ4: 31 | AK4: 33 | AL4: 0 | AN4: =COUNT(Y4:AC4)/5 -> 1 | AO4: =IF(AQ4>0,WEEKNUM(AQ4,1)&"-"&YEAR(AQ4),"") -> 42-2026 | AP4: 46307 | AQ4: 46307 | AR4: =IF(AA4="","WAITING FOR PLAN",IF(AU4="","PERMITTING NOT STARTED",IF(BR4>=100%,"RFE","ON GOING PERMITTING"))) -> RFE | AS4: NA | AT4: NA | AU4: 46316 | AV4: 46316 | AW4: NA | AX4: NA | AY4: 46316 | AZ4: 46316 | BA4: 68 | BB4: 68 | BC4: 46266 | BD4: 46283 | BE4: 1 | BF4: 1 | BG4: 46286 | BH4: 46307 | BI4: 2 | BJ4: 2 | BK4: 46294 | BL4: 46307 | BM4: 1 | BN4: 1 | BO4: 46289 | BP4: 46307 | BQ4: 13-Oct-26 - RFE Sites | BR4: =IFERROR((COUNT(BD4)*40%)+(COUNT(BL4)*20%)+(COUNT(BH4)*10%)+(COUNT(BP4)*10%)+(COUNT(AV4)*10%)+(COUNT(AZ4)*10%),0) -> 1 | BS4: =IF(BT4>0,WEEKNUM(BT4,1)&"-"&YEAR(BT4),"") -> 42-2026 | BT4: =AP4+3 -> 46310 | BU4: =IF(BV4>0,WEEKNUM(BV4,1)&"-"&YEAR(BV4),"") -> 42-2026 | BV4: 46311 | BW4: =IF(BX4>0,WEEKNUM(BX4,1)&"-"&YEAR(BX4),"") -> 47-2026 | BX4: =IF(CA4="",BV4+CD4,CA4+CD4) -> 46343.424 | BY4: 46340 | BZ4: 10/29/26: Partially Completed on Nov 14. Continuation on 2027 | CA4: 46311 | CB4: =IF(AI4<>0,CC4*0.25,0) -> 0.75 | CC4: 3 | CD4: =IF(R4=0,IFERROR(Q4/(CC4)/1.25,0),IFERROR(R4/(CC4)/1.25,0)) -> 32.424 | CE4: DIMARCO | CF4: BOTH | CG4: Jed, Mark, Ron, Adrian, Jerome, Naj, Alain | CH4: =IF(CA4="","NOT STARTED",IF(CA4<>"","ON GOING EXTRACTION",IF(CV4<>"","EXTRACTION COMPLETED"))) -> ON GOING EXTRACTION | CI4: =IFERROR(CQ4/CM4,0) -> 0.21323529 | CJ4: 10/27/26: 2,847.9 kg extracted: ~Cluster 3 (2pcs MH Open/Dewater) MH01 - MH04 • 300 pairs (48.52m) = 120.35 kg • 600 pairs (92.89m) = 199.6 kg • 1200 pairs (91.93m) = 388.9 kg • 2100 pairs (91.51m) = 642.3 kg • 2400 pairs (182.9m) = 1,496.75 kg ~ For continuation on Wednesday (October 28 shift) at Paco Site. 10/23/26: 4,566.20 kg extracted: ~Cluster 3 (4pcs MH Open/Dewater) MH92 - MH94 • 1500 pairs = 659.30 kg • 1800 pairs = 763.55 kg • 2400 pairs = 3,143.35 kg 10/24/26: 2,758.25 kg extracted: ~Cluster 3 (5pcs MH Open/Dewater) MH01 - MH92 • 1500 pairs (171.28m) = 875.75 kg • 1800 pairs (170m) = 1,055.95 kg MH01 - MH57 • 400 pairs (3.29m) = 5.05 kg • 600 pairs (35.32m) = 79.75 kg • 900 pairs (6.71m) = 21.9 kg • 1200 pairs (2m) = 8.70 kg • 1500 pairs (60.88m) = 346.1 kg • 1800 pairs (6.26m) = 32.85 kg • 2100 pairs (18.72m) = 132.20 kg • 2400 pairs (25.47m) = 200 kg 10/20/26: 1,272.75kg extracted: • >600 pairs = 1,233.45kg • <600 pairs = 39.3 kg ~ For Cluster 7: •Copper cable near EOL (Near 7-11; After MH 243), still cannot pull the cable. Used push rod to trace the cable route, it was stopped midway due to clogged duct. •MH38 still cannot open the manhole. Even used the Lever/Jack system, not able to access the MH ~For Cluster 6: •MH20 - Tried to open the Manhole again using various tools and method, still, cannot access the Manhole Cover. •MH23 - MH25, For verification the next day if the remaining copper was cut and extractable or not. 10/19/26: 1,157.85 kg extracted - For Cluster 7: •MH12054 - EOL, still cannot pull the cable even though the copepr at the other was cut. •MH2096 - MH2107, can't extract one span of copper cable •MH2117 - MH2106, MH can't open, need additional tools to open MH. 10/16/26: For Cluster 6: MH2172, MH2162, MH2151, visible but hard to open due to the manholes are not opened for a long time and was stuck. For Cluster 7: Copper lines from the following span are not removed due to cables are stuck (can't pull): MH12054 - End of Cable Line MH2186 - MH3068 Total of 2 Span and 4 MH opened | CK4: 46296 | CL4: 46296 | CM4: =AG4 -> 136 | CN4: =AI4 -> 64 | CO4: 15 | CQ4: 29 | CR4: =CM4-CQ4 -> 107 | CS4: 1.67 | CT4: 25.9 | CU4: =CS4+CT4 -> 27.57
A5: 46235 | B5: RFE | C5: PART OF 233 | D5: NLZ | E5: 14.957886 | F5: 120.90429 | G5: Baliuag | H5: Bulacan | I5: Bulacan | J5: Limwell | K5: Q1 | L5: T-37262327I-1-NLZ-00005 | M5: IRUP0002 | N5: Baliuag Sub-Exchange | O5: Sub-Exchange-S | P5: =IF(OR(NOT(ISNUMBER(Q5)),Q5=0),"NO DATA",IF(Q5<10,"<10 TONNES",">=10 TONNES")) -> >=10 TONNES | Q5: 60.2 | R5: 22.88 | S5: =IF(CH5="CANCELLED","CANCELLED",IF(CV5<>"","EXTRACTION DONE",IF(CH5="ON GOING EXTRACTION","ON GOING EXTRACTION",IF(AR5="RFE","READY FOR EXTRACTION",IF(AR5="ON GOING PERMITTING","ON GOING PERMITTING",IF(AC5<>"","DESIGN APPROVED",IF(AB5<>"","DESIGN SUBMITTED",IF(AA5<>"","DESIGN COMPLETED",IF(Z5<>"","ON GOING DESIGN",IF(Y5<>"","ON GOING SURVEY","NOT STARTED")))))))))) -> READY FOR EXTRACTION | T5: =IFERROR((AN5*33%)+(BR5*27%)+(CI5*40%),0) -> 0.6 | U5: =IF(V5>0,WEEKNUM(V5,1)&"-"&YEAR(V5),"") -> 38-2026 | V5: 46279 | W5: =V5 -> 46279 | X5: =IF(AD5>0,"DESIGN WITH CONCERN",IF(AC5>0,"DESIGN APPROVED",IF(AB5>0,"DESIGN FOR APPROVAL",IF(AA5>0,"DESIGN FOR SUBMISSION",IF(Z5>0,"ON GOING DESIGN",IF(Y5>0,"ON GOING SURVEY","FOR SURVEY")))))) -> DESIGN APPROVED | Y5: 46275 | Z5: 46276 | AA5: 46279 | AB5: 46279 | AC5: 46279 | AE5: Both | AF5: =IF(AA5-Y5<0,0,AA5-Y5) -> 4 | AG5: =AH5+AI5 -> 28 | AH5: 12 | AI5: 16 | AJ5: 13 | AK5: 3 | AL5: 0 | AN5: =COUNT(Y5:AC5)/5 -> 1 | AO5: =IF(AQ5>0,WEEKNUM(AQ5,1)&"-"&YEAR(AQ5),"") -> 44-2026 | AP5: 46325 | AQ5: 46325 | AR5: =IF(AA5="","WAITING FOR PLAN",IF(AU5="","PERMITTING NOT STARTED",IF(BR5>=100%,"RFE","ON GOING PERMITTING"))) -> RFE | AS5: NA | AT5: NA | AU5: 46316 | AV5: 46316 | AW5: NA | AX5: NA | AY5: 46316 | AZ5: 46316 | BA5: 5 | BB5: 5 | BC5: 46287 | BD5: 46295 | BE5: 1 | BF5: 1 | BG5: 46303 | BH5: 46321 | BI5: 1 | BJ5: 1 | BK5: 46301 | BL5: 46303 | BM5: 1 | BN5: 1 | BO5: 46301 | BP5: 46324 | BQ5: Oct 23 DPWH Bulacan 1st DEO Remarks: waiting to release receipt of Cash Bond and following up routing of the permit. Validity: 72 calendar days once secured. Contact name - Engr. Jose Federico Estigoy Contact number - 09260414377 Brgy: 5/5 LGU: 1/1 Traffic: 1/1 DPWH: 0/1 (Ongoing) DPWH Bulacan 1st DEO Remarks: waiting to release receipt of Cash Bond and following up routing of the permit. Validity: 72 calendar days once secured. Contact name - Engr. Jose Federico Estigoy Contact number - 09260414377 Brgy: 5/5 LGU: 1/1 Traffic: 1/1 DPWH: 0/1 (Ongoing) 19-Oct-26 Advanced Copy of the signed Baliuag LGU Permit. The hardcopy will be picked up by Engr. Billy here in Baliuag City Engr'g Office and will be released at the business center. As per City Engr., make sure to have a close coordination with BCTMO and Barangay. Contact Person: Engr. Billy James John C. Punzalan Contact #: 09057892343 Validity: 1yr Work hours: 6pm-6am Barangay: 5/5 LGU: 0/1 (ongoing) Traffic: 1/1 DPWH: 0/1 (Ongoing) 15-Oct-26 Baliuag City Hall MH #: MH001-MH016, MH018-MH029 Remarks: LGU Permit paid, 35,270.27. As per Engr. Billy, kindly wait for further instructions later if permit can possibly be released today. According to him, Baliuag City Business Center (one stop shop) is open even on Fridays but release of permit still depends if it will be signed immediately by the City Engineer. Since Baliuag City Hall is close during Fridays, they can only release permits which were signed the day prior. Contact Person: Engr. Billy James John C. Punzalan Contact #: 09057892343 Barangay: 5/5 LGU: 0/1 (ongoing) Traffic: 1/1 DPWH: 0/1 (Ongoing) Thank you! ROW Officer - Maria Ivory C. Suarez 14-Oct-26 Baliuag Sub Exchange Grantor: Baliuag City Hall MH #: MH001-MH016, MH018-MH029 Remarks: Advance copy of the OP amounting to 35,270.27. Official OP will possibly be released either later or tomorrow. As per advise, once paid, issuance of permit will be released the following day. Contact Person: Engr. Billy James John C. Punzalan Contact #: 09057892343 Barangay: 5/5 LGU: 0/1 (ongoing Traffic: 1/1 DPWH: 0/1 (Ongoing) Thank you! ROW Officer - Maria Ivory C. Suarez 12-Oct-26 DPWH Bulacan 1st DEO Remarks: Submitted Notarized Authorization Letter and Terms and Condition. Following up the status of the docs that are for routing. Waiting for the feedback of Engr. Joes and Engr. Charles. Brgy: 5/5 LGU: 0/1 (ongoing) Traffic: 1/1 DPWH: 0/1 (Ongoing) Thank you! ---- 8-Oct-26 ( Baliuag City Hall Remarks: Application has been received. As per Engr. Billy Punzalan, it will be endorsed to the Engr'g Office in 1-2 days for assessment. Once Engr'g Office received the documents, inspection will take place if there will be no dependecy. Informed them that I will follow up by Wednesday. Please see photo as proof of submission. Note: They required notarization for the BOM. Thank you!) --- (BTMO MH #: MH001-MH016, MH018-MH029 Remarks: Secured Traffic Clearance. No payment fee. As per Sir Ramil, remarks on the permit must be followed otherwise, cancellation may be applied. Contact Person: Ramil Ubungin Contact #: 09423162142 Barangay: 5/5 LGU: 0/1 Traffic: 1/1 DPWH: 0/1 (Ongoing) Thank you! ROW Officer - Maria Ivory C. Suarez) --- Baliuag Sub Exchange Grantor: DPWH Bulacan 1st DEO Remarks: Ongoing DPWH inspection with Sir Lincoln, Engr. Joes and Engr. Charles. Thank you! --- 1-Oct-26 Brgy. Sabang - Here at brgy Hall Sabang. Waiting for the budget and BC to be released. Thank you. Brgy. Treasurer Melchor Encarnacion - 09326338204 Brgy. Secretary Sarah Cruz - 09331538844 -- 30-Sep-26 (BTMO - Coordinated with Sir Ramil Ubungin, Admin Aide of BTMO. He provided the list of requirements for the traffic clearance. LOI BC Authorization Letter from PLDT ID of the Authorized Person List of Names of the people who will do the implementation. As per him, no fee for the traffic clearance. Ramil Ubungin - 09423162144 (8am-5pm/M-F only) ---- (Brgy. Bagong Nayon - As per Brgy. Sec., they are still waiting for the feedback of some of the councils. Also, brgy chairman has prior engagement. As per Sec., they will give feedback either tomorrow or latest is Friday.)Brgy. Poblacion - Secured BC. Free of charge. Was advised to do courtesy call prior mob. 28/09/2026 DPWH - inquire requirements in DPWH Bulacan 1st DEO for the Baliuag site. Coordinated with Engr. Joes. List of requirements were provided. Engr. Joes of the Maintenance Dept. - 09260414377 | BR5: =IFERROR((COUNT(BD5)*40%)+(COUNT(BL5)*20%)+(COUNT(BH5)*10%)+(COUNT(BP5)*10%)+(COUNT(AV5)*10%)+(COUNT(AZ5)*10%),0) -> 1 | BS5: =IF(BT5>0,WEEKNUM(BT5,1)&"-"&YEAR(BT5),"") -> 45-2026 | BT5: =AP5+3 -> 46328 | BU5: =IF(BV5>0,WEEKNUM(BV5,1)&"-"&YEAR(BV5),"") | BW5: =IF(BX5>0,WEEKNUM(BX5,1)&"-"&YEAR(BX5),"") | BZ5: 10/29/26: Sir Jayson's feedback today | CB5: =IF(AI5<>0,CC5*0.25,0) -> 0.5 | CC5: 2 | CD5: =IF(R5=0,IFERROR(Q5/(CC5)/1.25,0),IFERROR(R5/(CC5)/1.25,0)) -> 9.152 | CE5: ASSURE | CH5: =IF(CA5="","NOT STARTED",IF(CA5<>"","ON GOING EXTRACTION",IF(CV5<>"","EXTRACTION COMPLETED"))) -> NOT STARTED | CI5: =IFERROR(CQ5/CM5,0) -> 0 | CK5: 46296 | CL5: 46296 | CM5: =AG5 -> 28 | CN5: =AI5 -> 16 | CR5: =CM5-CQ5 -> 28 | CU5: =CS5+CT5 -> 0
A6: 46235 | B6: RFE | C6: PART OF 233 | D6: NLZ | E6: 14.797833 | F6: 120.87748 | G6: Bulacan | H6: Bulacan | I6: Bulacan | J6: Limwell | K6: Q1 | L6: T-37262327I-1-NLZ-00004 | M6: IRUP0003 | N6: Bulacan Sub-Exchange/RSU | O6: Sub-Exchange-S | P6: =IF(OR(NOT(ISNUMBER(Q6)),Q6=0),"NO DATA",IF(Q6<10,"<10 TONNES",">=10 TONNES")) -> >=10 TONNES | Q6: 26.8 | R6: 1.54 | S6: =IF(CH6="CANCELLED","CANCELLED",IF(CV6<>"","EXTRACTION DONE",IF(CH6="ON GOING EXTRACTION","ON GOING EXTRACTION",IF(AR6="RFE","READY FOR EXTRACTION",IF(AR6="ON GOING PERMITTING","ON GOING PERMITTING",IF(AC6<>"","DESIGN APPROVED",IF(AB6<>"","DESIGN SUBMITTED",IF(AA6<>"","DESIGN COMPLETED",IF(Z6<>"","ON GOING DESIGN",IF(Y6<>"","ON GOING SURVEY","NOT STARTED")))))))))) -> ON GOING EXTRACTION | T6: =IFERROR((AN6*33%)+(BR6*27%)+(CI6*40%),0) -> 0.6 | U6: =IF(V6>0,WEEKNUM(V6,1)&"-"&YEAR(V6),"") -> 38-2026 | V6: 46282 | W6: =V6 -> 46282 | X6: =IF(AD6>0,"DESIGN WITH CONCERN",IF(AC6>0,"DESIGN APPROVED",IF(AB6>0,"DESIGN FOR APPROVAL",IF(AA6>0,"DESIGN FOR SUBMISSION",IF(Z6>0,"ON GOING DESIGN",IF(Y6>0,"ON GOING SURVEY","FOR SURVEY")))))) -> DESIGN APPROVED | Y6: 46275 | Z6: 46275 | AA6: 46282 | AB6: 46282 | AC6: 46282 | AE6: Both | AF6: =IF(AA6-Y6<0,0,AA6-Y6) -> 7 | AG6: =AH6+AI6 -> 9 | AH6: 1 | AI6: 8 | AJ6: 8 | AK6: 0 | AL6: 0 | AN6: =COUNT(Y6:AC6)/5 -> 1 | AO6: =IF(AQ6>0,WEEKNUM(AQ6,1)&"-"&YEAR(AQ6),"") -> 43-2026 | AP6: 46318 | AQ6: 46318 | AR6: =IF(AA6="","WAITING FOR PLAN",IF(AU6="","PERMITTING NOT STARTED",IF(BR6>=100%,"RFE","ON GOING PERMITTING"))) -> RFE | AS6: NA | AT6: NA | AU6: 46316 | AV6: 46316 | AW6: NA | AX6: NA | AY6: 46316 | AZ6: 46316 | BA6: 2 | BB6: 2 | BC6: 46286 | BD6: 46301 | BE6: 1 | BF6: 1 | BG6: 46302 | BH6: 46303 | BI6: 1 | BJ6: 1 | BK6: 46303 | BL6: 46302 | BM6: 1 | BN6: 1 | BO6: 46302 | BP6: 46303 | BQ6: 8-Oct-26 - RFE Sites 6-Oct-26 Brgy Matungao Secured Permit Contact name: Brgy Sec contact number: 09205650575 Validity of Permit - 1 month Permit fee - 1k Remarks:/Report: Permit Secured Brgy - 1/2 LGU - 0/1 TRAFFIC - DPWH - ---- 29-Sep-26 Claster 1 Bulakan bulacan MH001, MH002 Grantor NAme - Brgy San Jose Contact name Gemma G. Mabanta (Brgy Secretary) Contact number - 09151046402 Validity of Permit - 6 months / 1 yr Permit fee: 2000 OR Remarks:/Report Submitted LOI for paynent tomorrow The brgy captain is in seminar for follow up tomorrow | BR6: =IFERROR((COUNT(BD6)*40%)+(COUNT(BL6)*20%)+(COUNT(BH6)*10%)+(COUNT(BP6)*10%)+(COUNT(AV6)*10%)+(COUNT(AZ6)*10%),0) -> 1 | BS6: =IF(BT6>0,WEEKNUM(BT6,1)&"-"&YEAR(BT6),"") -> 44-2026 | BT6: =AP6+3 -> 46321 | BU6: =IF(BV6>0,WEEKNUM(BV6,1)&"-"&YEAR(BV6),"") -> 44-2026 | BV6: 46324 | BW6: =IF(BX6>0,WEEKNUM(BX6,1)&"-"&YEAR(BX6),"") -> 44-2026 | BX6: =IF(CA6="",BV6+CD6,CA6+CD6) -> 46324.616 | BY6: 46330 | BZ6: 10/29/26: DD: 10/29 | CA6: 46324 | CB6: =IF(AI6<>0,CC6*0.25,0) -> 0.5 | CC6: 2 | CD6: =IF(R6=0,IFERROR(Q6/(CC6)/1.25,0),IFERROR(R6/(CC6)/1.25,0)) -> 0.616 | CE6: ASSURE | CF6: BOTH | CG6: lincoln, Jeff, Marvin, Darren | CH6: ON GOING EXTRACTION | CI6: =IFERROR(CQ6/CM6,0) -> 0 | CK6: 46296 | CL6: 46296 | CM6: =AG6 -> 9 | CN6: =AI6 -> 8 | CR6: =CM6-CQ6 -> 9 | CU6: =CS6+CT6 -> 0
A7: 46235 | B7: RFE | C7: PART OF 233 | D7: GMM | E7: 14.516502 | F7: 121.23834 | G7: Morong | H7: Rizal | I7: CTAABMT | K7: Q2 | L7: T-37262327I-1-GMM-00015 | M7: IRUP0004 | N7: Morong | O7: Exchange-S | P7: =IF(OR(NOT(ISNUMBER(Q7)),Q7=0),"NO DATA",IF(Q7<10,"<10 TONNES",">=10 TONNES")) -> <10 TONNES | Q7: 8.9 | R7: 2.71 | S7: =IF(CH7="CANCELLED","CANCELLED",IF(CV7<>"","EXTRACTION DONE",IF(CH7="ON GOING EXTRACTION","ON GOING EXTRACTION",IF(AR7="RFE","READY FOR EXTRACTION",IF(AR7="ON GOING PERMITTING","ON GOING PERMITTING",IF(AC7<>"","DESIGN APPROVED",IF(AB7<>"","DESIGN SUBMITTED",IF(AA7<>"","DESIGN COMPLETED",IF(Z7<>"","ON GOING DESIGN",IF(Y7<>"","ON GOING SURVEY","NOT STARTED")))))))))) -> DESIGN APPROVED | T7: =IFERROR((AN7*33%)+(BR7*27%)+(CI7*40%),0) -> 0.33 | U7: =IF(V7>0,WEEKNUM(V7,1)&"-"&YEAR(V7),"") -> 38-2026 | V7: 46282 | W7: =V7 -> 46282 | X7: =IF(AD7>0,"DESIGN WITH CONCERN",IF(AC7>0,"DESIGN APPROVED",IF(AB7>0,"DESIGN FOR APPROVAL",IF(AA7>0,"DESIGN FOR SUBMISSION",IF(Z7>0,"ON GOING DESIGN",IF(Y7>0,"ON GOING SURVEY","FOR SURVEY")))))) -> DESIGN APPROVED | Y7: 46282 | Z7: 46282 | AA7: 46284 | AB7: 46284 | AC7: 46284 | AE7: Both | AF7: =IF(AA7-Y7<0,0,AA7-Y7) -> 2 | AG7: =AH7+AI7 -> 20 | AH7: 1 | AI7: 19 | AJ7: 19 | AK7: 0 | AL7: 0 | AN7: =COUNT(Y7:AC7)/5 -> 1 | AO7: =IF(AQ7>0,WEEKNUM(AQ7,1)&"-"&YEAR(AQ7),"") -> 49-2026 | AP7: 46371 | AQ7: 46357 | AR7: =IF(AA7="","WAITING FOR PLAN",IF(AU7="","PERMITTING NOT STARTED",IF(BR7>=100%,"RFE","ON GOING PERMITTING"))) -> PERMITTING NOT STARTED | BQ7: PENDING | BR7: =IFERROR((COUNT(BD7)*40%)+(COUNT(BL7)*20%)+(COUNT(BH7)*10%)+(COUNT(BP7)*10%)+(COUNT(AV7)*10%)+(COUNT(AZ7)*10%),0) -> 0 | BS7: =IF(BT7>0,WEEKNUM(BT7,1)&"-"&YEAR(BT7),"") | BU7: =IF(BV7>0,WEEKNUM(BV7,1)&"-"&YEAR(BV7),"") | BW7: =IF(BX7>0,WEEKNUM(BX7,1)&"-"&YEAR(BX7),"") -> 1-1900 | BX7: =IF(CA7="",BV7+CD7,CA7+CD7) -> 1.084 | CB7: =IF(AI7<>0,CC7*0.25,0) -> 0.5 | CC7: 2 | CD7: =IF(R7=0,IFERROR(Q7/(CC7)/1.25,0),IFERROR(R7/(CC7)/1.25,0)) -> 1.084 | CH7: =IF(CA7="","NOT STARTED",IF(CA7<>"","ON GOING EXTRACTION",IF(CV7<>"","EXTRACTION COMPLETED"))) -> NOT STARTED | CI7: =IFERROR(CQ7/CM7,0) -> 0 | CM7: =AG7 -> 20 | CN7: =AI7 -> 19 | CR7: =CM7-CQ7 -> 20 | CU7: =CS7+CT7 -> 0
A8: 46235 | B8: RFE | C8: PART OF 233 | D8: GMM | E8: 14.494219 | F8: 121.29121 | G8: Tanay | H8: Rizal | I8: CTAABMT | J8: Jessa | K8: Q1 | L8: T-37262327I-1-GMM-00003 | M8: IRUP0005 | N8: Tanay CO | O8: Exchange-M | P8: =IF(OR(NOT(ISNUMBER(Q8)),Q8=0),"NO DATA",IF(Q8<10,"<10 TONNES",">=10 TONNES")) -> >=10 TONNES | Q8: 156.8 | R8: 17.44 | S8: =IF(CH8="CANCELLED","CANCELLED",IF(CV8<>"","EXTRACTION DONE",IF(CH8="ON GOING EXTRACTION","ON GOING EXTRACTION",IF(AR8="RFE","READY FOR EXTRACTION",IF(AR8="ON GOING PERMITTING","ON GOING PERMITTING",IF(AC8<>"","DESIGN APPROVED",IF(AB8<>"","DESIGN SUBMITTED",IF(AA8<>"","DESIGN COMPLETED",IF(Z8<>"","ON GOING DESIGN",IF(Y8<>"","ON GOING SURVEY","NOT STARTED")))))))))) -> ON GOING EXTRACTION | T8: =IFERROR((AN8*33%)+(BR8*27%)+(CI8*40%),0) -> 0.62857143 | U8: =IF(V8>0,WEEKNUM(V8,1)&"-"&YEAR(V8),"") -> 38-2026 | V8: 46282 | W8: =V8 -> 46282 | X8: =IF(AD8>0,"DESIGN WITH CONCERN",IF(AC8>0,"DESIGN APPROVED",IF(AB8>0,"DESIGN FOR APPROVAL",IF(AA8>0,"DESIGN FOR SUBMISSION",IF(Z8>0,"ON GOING DESIGN",IF(Y8>0,"ON GOING SURVEY","FOR SURVEY")))))) -> DESIGN APPROVED | Y8: 46275 | Z8: 46276 | AA8: 46282 | AB8: 46282 | AC8: 46282 | AE8: Both | AF8: =IF(AA8-Y8<0,0,AA8-Y8) -> 7 | AG8: =AH8+AI8 -> 14 | AH8: 4 | AI8: 10 | AJ8: 10 | AK8: 0 | AL8: 0 | AN8: =COUNT(Y8:AC8)/5 -> 1 | AO8: =IF(AQ8>0,WEEKNUM(AQ8,1)&"-"&YEAR(AQ8),"") -> 43-2026 | AP8: 46318 | AQ8: 46318 | AR8: =IF(AA8="","WAITING FOR PLAN",IF(AU8="","PERMITTING NOT STARTED",IF(BR8>=100%,"RFE","ON GOING PERMITTING"))) -> RFE | AS8: NA | AT8: NA | AU8: 46316 | AV8: 46316 | AW8: NA | AX8: NA | AY8: 46316 | AZ8: 46316 | BA8: 4 | BB8: 4 | BC8: 46287 | BD8: 46315 | BE8: 1 | BF8: 1 | BG8: 46290 | BH8: 46315 | BI8: 1 | BJ8: 1 | BK8: 46290 | BL8: 46290 | BM8: 1 | BN8: 1 | BO8: 46290 | BP8: 46315 | BQ8: Oct 23 DPWH Rizal 2nd DEO - For pick up Official permit with DPWH Dry seal. The first DPWH provided was Only an Advance copy for Lgu Tanay application. However Engr. Rick is not around Already RFE DPWH Rizal 2nd DEO - For pick up Official permit with DPWH Dry seal. The first DPWH provided was Only an Advance copy for Lgu Tanay application. However Engr. Rick is not around Already RFE 20-Oct-26 Tanay Lgu - Follow up the Order of payment to the assessment officer, Arch. Angela 19-Oct-26 Tanay Lgu, Waiting for Engr. Vitas to submit DPWH permit and Acquire Order of Payment 15-Oct-26 DPWH Engr. Rick is currently on sick leave and is in the hospital. However, I have already requested an advance copy of the permit, even without the official DPWH dry seal, just so we can present it to the LGU of Tanay as proof that our permit has already been approved by DPWH. This way, the LGU of Tanay can at least consider our request and allow us to proceed with the payment process. and Engr. Rick agreed to speak to the Office of the Building Official of Tanay as proof that we have DPWH Approval ( If Necessary.) and Received call from Tanay Water District Asking for additional requirements such as: ID's of Personnel and Exact Working Date. 14-Oct-26 With Engr. Johnrich Head Officer of the Office of the Building Official Tanay Rizal. Done Discussion/Negotiation With Engr. John, And Agreed to Accept and Have an Advance assessment of our Lgu Permit Application while waiting for the DPWH Permit. However the person Incharge for The Assessment of our Documents Submitted is on Seminar. 13-Oct-26 Tanay Exchange Grantor: Ongoing Sign and Seal Plan and Civil/Electronincs Permit. 7-Oct-26 DPWH Rizal 2nd DEO -Waiting for Engr. Rick's availability to submit His Requested Edited LOI. Removing Repair and Restoration Words. 6-Oct-26 Ongoing Site inspection with DPWH RIZAL 2ND DEO --- 2-Oct-26 Tanay Exchange C1 DPWH Tanay 2nd Rizal District .- Already spoke to Engr.Nick Regarding 10 overlayed Manholes Along Jurisdiction of DPWH, Which are Requested for Manholes raising.. As per him We will meet on Monday Next week to talk what remedy or Help they could offer us to Expedite the Permit acquisition. 30-Sep-26 -DPWH Rizal 2nd DEO. - Pick DPWH Request Letter to PLDT Manhole Raising. With District Engr. Signatory. --- 29-Sep-26 (Tanay Exchange C1 Grantor: Tanay LGU . @Office of the Municipal Mayor, Follow up Plan Proposal Evaluation.) As per the Mayor's office Staff, Plan Proposal Already Done Evaluation of the mayor and Endorsed to Municipal Engineering office. 28-Sep-26 Tanay Exchange Gantors: DPWH/Tanay Lgu (Tanay Exchange Grantor: DPWH Rizal 2nd DEO- They need PLDT’s details so they can properly address the letter regarding the manhole raising. As per Engr. Rick, the letter should be addressed directly to the principal client and not to the contractor. LOI must be Notarized following/Attached all Requirements prior for receiving of LOI. @⁨FH Mam Nena Feliciano⁩ ma'am) 25-Sep-26 For Submission of LOI address to District Engr. and follow up Engr . Rick for The additional requirements, However Engr. rick is on Site. as per his Subordinate follow up on Monday, possibly at DWPH Pasig. Acquired Engr.'s Contact Number. 25/09/2026 Tanay Exchange Grantor: DPWH Tanay 2nd District Rizal Remarks: They will no longer allow excavation and restoration only. They want the missing manholes to be installed flush with the road surface because they said that excavating and restoring the road would compromise its durability and could eventually cause potholes. 10 missing manholes out of 14 manholes. Engr. Rick advised me to visit his office at DWPH PASIG for further Explanation. | BR8: =IFERROR((COUNT(BD8)*40%)+(COUNT(BL8)*20%)+(COUNT(BH8)*10%)+(COUNT(BP8)*10%)+(COUNT(AV8)*10%)+(COUNT(AZ8)*10%),0) -> 1 | BS8: =IF(BT8>0,WEEKNUM(BT8,1)&"-"&YEAR(BT8),"") -> 44-2026 | BT8: =AP8+3 -> 46321 | BU8: =IF(BV8>0,WEEKNUM(BV8,1)&"-"&YEAR(BV8),"") -> 44-2026 | BV8: 46323 | BW8: =IF(BX8>0,WEEKNUM(BX8,1)&"-"&YEAR(BX8),"") -> 46-2026 | BX8: =IF(CA8="",BV8+CD8,CA8+CD8) -> 46336.952 | BY8: 46333 | BZ8: 10/29/26: Partially Completed on Nov 7. Continuation on 2027 | CA8: 46323 | CB8: =IF(AI8<>0,CC8*0.25,0) -> 0.25 | CC8: 1 | CD8: =IF(R8=0,IFERROR(Q8/(CC8)/1.25,0),IFERROR(R8/(CC8)/1.25,0)) -> 13.952 | CE8: DIMARCO | CF8: BOTH | CG8: Jed, Mark, Ron, Adrian, Jerome, Naj, Alain | CH8: =IF(CA8="","NOT STARTED",IF(CA8<>"","ON GOING EXTRACTION",IF(CV8<>"","EXTRACTION COMPLETED"))) -> ON GOING EXTRACTION | CI8: =IFERROR(CQ8/CM8,0) -> 0.071428571 | CK8: 46296 | CL8: 46296 | CM8: =AG8 -> 14 | CN8: =AI8 -> 10 | CQ8: 1 | CR8: =CM8-CQ8 -> 13 | CS8: 2.5778 | CU8: =CS8+CT8 -> 2.5778
A9: 46235 | B9: RFE | C9: PART OF 233 | D9: GMM | E9: 14.67066 | F9: 120.94582 | G9: Malabon City | H9: Metropolitan Manila | I9: CaMaNaVa | J9: Dan | K9: Q1 | L9: T-37262327I-1-GMM-00012 | M9: IRUP0006 | N9: Malabon Exchange | O9: Exchange-M | P9: =IF(OR(NOT(ISNUMBER(Q9)),Q9=0),"NO DATA",IF(Q9<10,"<10 TONNES",">=10 TONNES")) -> >=10 TONNES | Q9: 127.4 | R9: 34.73 | S9: =IF(CH9="CANCELLED","CANCELLED",IF(CV9<>"","EXTRACTION DONE",IF(CH9="ON GOING EXTRACTION","ON GOING EXTRACTION",IF(AR9="RFE","READY FOR EXTRACTION",IF(AR9="ON GOING PERMITTING","ON GOING PERMITTING",IF(AC9<>"","DESIGN APPROVED",IF(AB9<>"","DESIGN SUBMITTED",IF(AA9<>"","DESIGN COMPLETED",IF(Z9<>"","ON GOING DESIGN",IF(Y9<>"","ON GOING SURVEY","NOT STARTED")))))))))) -> ON GOING PERMITTING | T9: =IFERROR((AN9*33%)+(BR9*27%)+(CI9*40%),0) -> 0.492 | U9: =IF(V9>0,WEEKNUM(V9,1)&"-"&YEAR(V9),"") -> 39-2026 | V9: 46289 | W9: =V9 -> 46289 | X9: =IF(AD9>0,"DESIGN WITH CONCERN",IF(AC9>0,"DESIGN APPROVED",IF(AB9>0,"DESIGN FOR APPROVAL",IF(AA9>0,"DESIGN FOR SUBMISSION",IF(Z9>0,"ON GOING DESIGN",IF(Y9>0,"ON GOING SURVEY","FOR SURVEY")))))) -> DESIGN APPROVED | Y9: 46279 | Z9: 46283 | AA9: 46289 | AB9: 46289 | AC9: 46295 | AE9: Both | AF9: =IF(AA9-Y9<0,0,AA9-Y9) -> 10 | AG9: =AH9+AI9 -> 50 | AH9: 31 | AI9: 19 | AJ9: 1 | AK9: 18 | AL9: 0 | AN9: =COUNT(Y9:AC9)/5 -> 1 | AO9: =IF(AQ9>0,WEEKNUM(AQ9,1)&"-"&YEAR(AQ9),"") -> 45-2026 | AP9: 46333 | AQ9: 46333 | AR9: =IF(AA9="","WAITING FOR PLAN",IF(AU9="","PERMITTING NOT STARTED",IF(BR9>=100%,"RFE","ON GOING PERMITTING"))) -> ON GOING PERMITTING | AS9: NA | AT9: NA | AU9: 46316 | AV9: 46316 | AW9: NA | AX9: NA | AY9: 46316 | AZ9: 46316 | BA9: 9 | BB9: 9 | BC9: 46293 | BD9: 46307 | BE9: 1 | BG9: 46293 | BI9: 1 | BK9: 46293 | BQ9: Cluster 2 – Malabon Cluster 2 – Caloocan Exchange Co. Cluster 1 – Caloocan Cluster 1 – Grace Park Remarks: Submitted the signed and sealed plans, BOM, and Gantt Chart to the LGU. Engnr Kweenie advised that she will inform me once the Order of Payment is available, as she still needs to review the excavation permit application. I also submitted the documents to Engr. Carlo for the LGU’s No Objection approval. OCT 22 Cluster 2 – Malabon Cluster 2 – Caloocan Exchange Co. Cluster 1 – Caloocan Cluster 1 – Grace Park Remarks: Submitted the signed and sealed plans, BOM, and Gantt Chart to the LGU. Engnr Kweenie advised that she will inform me once the Order of Payment is available, as she still needs to review the excavation permit application. I also submitted the documents to Engr. Carlo for the LGU’s No Objection approval. 12-Oct-26 Brgy Flores Remarks : Here at brgy Flores done payment for brgy permit STATUS : Permit Secured Permit Validity : Until finish Amount : 300 Permit fee (OR) 3000 cash Bond Note : the barangay will provide excavation cashbond form Total Amount : 3,300 BRGY - 7/7 LGU - 0/1 DPWH - 0/1 TRAFFIC - 0/1 --- 8-Oct-26 (Brgy Concepcion @brgy concepcion waiting for brgy secretary for payment of brgy permit) LGU Malabon Remarks: @ LGU Malabon Engineering Department and spoke with Ms. Divina Ramos to ask about the requirements needed for the LGU permit. She advised that we need to submit an LOI addressed to the City Mayor, indicating the barangays where we will be conducting the project. We also need to secure the Contractor’s Tax for excavation and the DPWH Permit. Contact person : divina b. Ramos Contact no: 09225217854 Designation : administrative officer 2 ----- 5-Oct-26 -Brgy baritan Remarks : done payment for brgy permit - Permit secured Permit fee : 2000 (AR) OR/AR Permit Validity : 3 months Contact person : zander Contact no: 0943640308 Brgy - 4/7 Lgu - 0/1 Dpwh - 0-1 Traffice 0-1 --- 1-Oct-26 -Brgy san Agustin Contact Name: Benilda S. Legarda Designation - brgy secretary Contact no: 09063474254 Validity permit - 4 months Permit Fee - 1500 (OR) Cashbond - 10,000 (SOA) NOTE: We can get the cash bond back once we’re done and everything is properly completed. They still need to inspect the work, so they’ll also need to see the before-and-after photos of the site. Remarks : done payment for brgy permit of San Agustin - permit Secured Brgy - 2/6 LGU - 0/1 TRAFFIC - 0/1 DPWH - 0/1 30-Sep-26 Brgy. Baritan Following up on the barangay application. I’m just waiting for the Barangay Secretary to confirm the amount fee for the barangay permit. They asked me to come back at 2:00 PM so I can speak with him directly. ---- 29/09/2026 (Chief Officer Saint James T. Lopez of CTPMO stated that a permit will not be issued without the DPWH Permit, which must be applied for with the DPWH and followed by an inspection. He recommends conducting implementation once the permit is granted, preferably between 8pm to 5am on weekdays, and at any time during weekends. Meanwhile, during the work, the manhole should be covered with a 1-inch-thick steel plate to ensure safety.) (Malabon C2 Grantor: Barangay Hulong Duhat MH Nos.: MH 057, MH 058, MH 044, MH 045, MH 045 Submitted the LOI and plans for Barangay Hulong Duhat. as per Barangay Secretary, Ms. Desiree O. Bersales, there is a cash bond of ₱5,000 that needs to be paid. The cash bond will be refundable after six (6) months, as the barangay will conduct another inspection once the work has been completed to ensure that the excavation and restoration work has been properly done. The permit fee is ₱300, which covers all the manholes that will be constructed. Permit Validity: 6 months Refundable Cash Bond: ₱5,000 Permit Fee: ₱300 Contact Person: Desiree O. Bersales, Barangay Secretary Contact No.: 0924 571 3655) --- (DPWH–Malabon–Navotas District Engineering Office. Ms. Honey Tejadilla (0908 370 7858) advised that the manholes (MH) located along E. Rodriguez St., with MH Nos. SB051, SB050, SB049, and SB048, were just restored this year. They cannot guarantee that excavation will be permitted because the road works are still under a surety bond with the subcontractor who completed the restoration. She suggested submitting a Request Letter regarding our activity at the said location. The request will then be reviewed, and they will provide a response based on the discussion with their District Engineer. She also suggested submitting the following documents: 1.Program of Works and Detailed Unit Price Analysis 2.Geotagged Pictures 3.Utility Layout Plan 4.Cross-Sectional Plan and Specifications showing the proposed utility to be embedded in the existing road 5.Precedence Diagram Method 6.Notarized Authorization Letter from the Agency/Company) ----- -Claster 1 Bulakan bulacan MH001, MH002 Grantor NAme - Brgy San Jose Contact name Gemma G. Mabanta (Brgy Secretary) Contact number - 09151046402 Validity of Permit - 6 months / 1 yr Permit fee: 2000 OR Remarks:/Report Submitted LOI for paynent tomorrow The brgy captain is in seminar for follow up tomorrow 28/09/2026 San Agustin I already submitted the LOI and plan for the Barangay Permit, as advised by Ma’am Benilda, the Barangay Secretary, regarding the manhole opening She mentioned that they require a ₱10,000 cash bond, which is refundable once the work is completed and the site is properly restored. We just need to provide before-and-after photos of the site when we process the refund. The Barangay Permit fee is ₱1,500, and the permit is valid for 3 months. Contact person: Ma’am Benilda S. Legarda Barangay Secretary 0906 347 4254 | BR9: =IFERROR((COUNT(BD9)*40%)+(COUNT(BL9)*20%)+(COUNT(BH9)*10%)+(COUNT(BP9)*10%)+(COUNT(AV9)*10%)+(COUNT(AZ9)*10%),0) -> 0.6 | BS9: =IF(BT9>0,WEEKNUM(BT9,1)&"-"&YEAR(BT9),"") -> 46-2026 | BT9: =AP9+3 -> 46336 | BU9: =IF(BV9>0,WEEKNUM(BV9,1)&"-"&YEAR(BV9),"") -> 46-2026 | BV9: 46337 | BW9: =IF(BX9>0,WEEKNUM(BX9,1)&"-"&YEAR(BX9),"") -> 48-2026 | BX9: =IF(CA9="",BV9+CD9,CA9+CD9) -> 46350.892 | BY9: =IF(CA9="",BV9+CD9,CA9+CD9) -> 46350.892 | CB9: =IF(AI9<>0,CC9*0.25,0) -> 0.5 | CC9: 2 | CD9: =IF(R9=0,IFERROR(Q9/(CC9)/1.25,0),IFERROR(R9/(CC9)/1.25,0)) -> 13.892 | CG9: Frederick, Randy, Mjay, Loyd, Rafael, Winston, Mathew | CH9: =IF(CA9="","NOT STARTED",IF(CA9<>"","ON GOING EXTRACTION",IF(CV9<>"","EXTRACTION COMPLETED"))) -> NOT STARTED | CI9: =IFERROR(CQ9/CM9,0) -> 0 | CM9: =AG9 -> 50 | CN9: =AI9 -> 19 | CR9: =CM9-CQ9 -> 50 | CU9: =CS9+CT9 -> 0
A10: 46235 | B10: RFE | C10: PART OF 233 | D10: GMM | E10: 14.756092 | F10: 121.04702 | G10: Caloocan City | H10: Metropolitan Manila | I10: CaMaNaVa | J10: Dan | K10: Q1 | L10: T-37262327I-1-GMM-00001 | M10: IRUP0007 | N10: Kalookan Exchange CO | O10: Exchange-M | P10: =IF(OR(NOT(ISNUMBER(Q10)),Q10=0),"NO DATA",IF(Q10<10,"<10 TONNES",">=10 TONNES")) -> >=10 TONNES | Q10: 156.8 | R10: 93.1 | S10: =IF(CH10="CANCELLED","CANCELLED",IF(CV10<>"","EXTRACTION DONE",IF(CH10="ON GOING EXTRACTION","ON GOING EXTRACTION",IF(AR10="RFE","READY FOR EXTRACTION",IF(AR10="ON GOING PERMITTING","ON GOING PERMITTING",IF(AC10<>"","DESIGN APPROVED",IF(AB10<>"","DESIGN SUBMITTED",IF(AA10<>"","DESIGN COMPLETED",IF(Z10<>"","ON GOING DESIGN",IF(Y10<>"","ON GOING SURVEY","NOT STARTED")))))))))) -> ON GOING PERMITTING | T10: =IFERROR((AN10*33%)+(BR10*27%)+(CI10*40%),0) -> 0.438 | U10: =IF(V10>0,WEEKNUM(V10,1)&"-"&YEAR(V10),"") -> 39-2026 | V10: 46291 | W10: =V10 -> 46291 | X10: =IF(AD10>0,"DESIGN WITH CONCERN",IF(AC10>0,"DESIGN APPROVED",IF(AB10>0,"DESIGN FOR APPROVAL",IF(AA10>0,"DESIGN FOR SUBMISSION",IF(Z10>0,"ON GOING DESIGN",IF(Y10>0,"ON GOING SURVEY","FOR SURVEY")))))) -> DESIGN APPROVED | Y10: 46288 | Z10: 46288 | AA10: 46291 | AB10: 46291 | AC10: 46300 | AE10: OSP only | AF10: =IF(AA10-Y10<0,0,AA10-Y10) -> 3 | AG10: =AH10+AI10 -> 61 | AH10: 58 | AI10: 3 | AJ10: 2 | AK10: 0 | AL10: 1 | AN10: =COUNT(Y10:AC10)/5 -> 1 | AO10: =IF(AQ10>0,WEEKNUM(AQ10,1)&"-"&YEAR(AQ10),"") -> 45-2026 | AP10: 46329 | AQ10: 46329 | AR10: =IF(AA10="","WAITING FOR PLAN",IF(AU10="","PERMITTING NOT STARTED",IF(BR10>=100%,"RFE","ON GOING PERMITTING"))) -> ON GOING PERMITTING | AS10: NA | AT10: NA | AU10: 46316 | AV10: 46316 | AW10: NA | AX10: NA | AY10: 46316 | AZ10: 46316 | BA10: 1 | BB10: 13 | BC10: 46294 | BE10: 2 | BF10: 1 | BG10: 46294 | BI10: 1 | BJ10: 1 | BK10: 46294 | BL10: 46307 | BM10: 1 | BO10: 46297 | BQ10: 14-Oct-26 BRGY LONGOS Remarks : done payment for brgy longos PERMIT FEE: 500 (OR) VALIDITY PERMIT : 5 MONTHS STATUS : BRGY PERMIT SECURED BRGY - 2/3 LGU - 0/1 DPWH - 0/1 TRAFFIC - 0/1 13-Oct-26 Brgy longos REMARKS: As per the Barangay Secretary, only the three (3) manholes listed above are under their jurisdiction, based on their site inspection. The other manholes are reportedly under the jurisdiction of Barangay 14, Kalookan. I was advised to verify the remaining manholes with Barangay 14 first before they can release the permit. ---- 12-Oct-26 DPSTM South Caloocan Activity: Permit Secured until October 31, 2026 ( Renewable free) --- 8-Oct-26 Brgy 9 Contact Details: Sec Micah Contact Number: 09672906364 Permit Fee: 2k AR with 5k Cashbond (Refundable) Validity Permit: 3 months Remarks: PERMIT ACQUIRED - PLEASE SUBMIT JOB ORDER AND ID’s OF PERSONNEL TO BRGY ONCE DEPLOYED (STRICTLY COMPLIANCE FOR SAFETY PURPOSE). MAKE SURE TO ALWAYS BRING COPY OF PERMIT. Brgy - 4/4 LGU - 0/1 Traffic - 0/1 Dpwh - 0/1 7-Oct-26 (Brgy. Longos -- Follow up application, Sec Eugene is in the meeting.) (Brgy. Tonsuya Remarks: As per Ma’am Tin, Clerk Officer, we need to comply first with the required documents/requirements being requested by the barangay. These include the following: Plan List of personnel No Objection from the Malabon LGU According to the barangay, they have an existing barangay ordinance requiring these documents before they can proceed with the manhole inspection and release. ) --- (DPSTM Done submitting and discussing our Traffic Management Plan with Architect Nitz. As per him, our application is currently being routed for signature. Once the permit is signed, we will need to pay ₱50.00 for the Documentary Stamp at the New Caloocan City Hall. The permit is expected to be released by Monday or Tuesday, once the signing and payment are completed.) ---- Brgy. 3 Contact Name: Chairman Manuel Estolano Contact Number: 09164387475 Designation: Brgy Chairman Permit Validity: 3 months Permit Fee: 5k AR Remarks: STRICTLY NO WORK OR WORK-RELATED ACTIVITIES SHALL BE CONDUCTED FROM OCTOBER 30, 2026 UNTIL NOVEMBER 4, 2026. ACTIVITIES WILL RESUME ON NOVEMBER 5. OPENING OF MANHOLES CAN ACCESS FROM OCT.7 to OCT 29, 2026 IF UNDONE, WILL RESUME ON NOVEMBER 5. Brgy - 4/4 LGU - 0/1 Traffic - 0/1 Dpwh - 0/1 --- 5-Oct-26 - (Brgy 14 Contact Name: Jeus Marco Galvez Contact Number: 09426061406 Designation: Brgy Secretary Permit Validity: 6 months Permit Fee: 2k AR to follow OR by Friday Validity 6 months Remarks: Permit Acquired. Please inform Brgy ahead of time before deployment. And the team must log in first. Brgy - 2/5 LGU - 0/1 Traffic - 0/1 Dpwh - 0/1) --- (Brgy. Tinajeros MH # : MH2347 MH2346 MH2345 MH2344 MH2348 MH2349 Remarks : done payment of brgy tinajeros permit - secured Permit Permit fee - 500 (OR) Permit Validity : 1 month Contact Person: roselle Vibar Designation : brgy clerk Contact no: 09325377664 BRGY - 2/3 LGU - 0/1 TRAFFIC - 0/1 DPWH - 0/1) ---- Brgy 12 Contact Name: Earl Gene Cruz Contact Number: 09941646819 Designation: Brgy Admin Permit Validity: 6 months for Opening manhole, 2-3weeks for Excavtion Permit Permit Fee: 4k AR with Cash Bond 5k (Refundable) Total of 9,000 Remarks: -permit acquired, negotiated the fee from ₱12,000 down to ₱4,000 for 2 overlayed manhole plus ₱5k cash bond refundable after the excavated areas are fully restored. - Excavation Permit will be issued once the team is deployed just present the receipt. The activity must be completed within a maximum of 2-3 weeks, including the full restoration of the affected areas. - Can proceed on accessible manholes. Team must inform and log in at the barangay office before starting any work. - Prioritize Pusit Street for the excavation and complete the restoration, as delivery trucks use the road to access the public market. --- 2-Oct-26 (Submitted the revised plan for the visible manhole only. Since I was unable to catch Engr. William today as he is currently conducting a site inspection, he requested that we leave our application with their Admin Office. Engr. William will retrieve the application on Monday and provide me with an update regarding its status. For the manhole with civil works, we will apply online once we have the pending requirements from the Design Team, particularly the cross-sectional section and Precedence Diagram Method (PDM). For the Legal Team requirements, the Secretary’s Certificate/Authorization is expected to be released earlier on Monday, as advised by the Legal Team.) --- (Brgy. 4 Contact Details: Sec. Priscila Tolentino Contact Number: 09150731787 Designation: Brgy Chairman Permit Validity: 6 months Permit Fee: 2k OR Remarks: Need to inform and log in first at the Barangay before proceeding with the implementation. Brgy - 0/4 LGU - 0/1 Traffic - 0/1 Dpwh - 0/1) --- (Brgy. Longos Remarks: LOI Submitted, For inspection of Brgy. Officials. Once inspection is done they will inform me for Payment Process. Need to apply LGU, PSTMO & DPWH under National Road. Barangay: 0/3 LGU: 0/1 PSTMO: 0/1 DPWH: 0/1) ---- Brgy Acacia remarks : for payment of brgy permit ----- 1-Oct-26 (Brgy.5 for MH 1025 Brgy.Sec.Imelda De Guzman 0936-7992309 donation of Php500 for their cleaning materials with AR. Validity one year during mob.their Brgy.Tanod will have to assist us and provide them their compensation for the services rendered. ) --- (Brgy.9 for MH 6947 LOI submitted as per Brgy. Capt.Edwin Galvez Brgy.9 tel# 878-4467 needed the following as attachments with our LOI 1).PLDT job order 2).PLDT authorization to Fiberhome to undertake said scope of works 3).duration of works 4)traffic management plan Permit fee-to be determine once above are complied.) -- Brgy. 1 Contact Name: Cherrie Ann (Secretary) Contact Number: 09056564324 Designation: Brgy Chairman Permit Validity: 6 months Permit Fee: 2k AR -- 30-Sep-26 (PUBLIC SAFETY AND TRAFFIC MANAGEMENT DEPARTMENT • Documents received by PSTMD. To follow: Submission of the following requirements: ◦ Barangay Permit ◦ MMDA Permit ◦ DPWH Permit ◦ NTP • As per Ma’am Dolly, we need to confirm with Arch. Nitz first if he will allow us to attend his meeting on Monday at 10:00 AM. • During meeting we need discuss the traffic flow and traffic management plan for our project. Engr assigned is required to attend the meeting. • PSTMD requires traffic personnel for the project, and their salary will be shouldered by us. • We also need to comply with the remaining requirements first to avoid any hold or delay in the application process. Contact Details: Architect Nitz Contact Number: 09988466746 ) ---- Brgy. Longos Remarks: As per Sec. Eugene, requested revisions to the LOI, indicating streets with manholes and their count under their jurisdiction. Advised to apply for a permit with CTPMO since it's under National Road. ---- 29-Sep-26 (Caloocan City Cluster 4 Brgy.14 for MH 6947 LOI submitted 09/29/26. Brgy.Sec.Jeus Marco Galvez 0942-6061406 permit fee Php2,000 per MH excavation with Brgy.ordinance.Permit tentative release date on Thurs.Oct.01/26. Remarks : MH 6947 is not accessible.) ----- (kalookan exchange City Cluster 1 Brgy. Acacia for MH6913 6910 6912 6905 LOI submitted 09/29/26. Brgy.staff. Ms. Sharmaine permit fee Php1,000 Remarks : permit will be release upon payment valid for 6 mos.) ----- (kalookan exchange City Cluster 1 Brgy. Tugatog for MH2339 2336 6905 2342 2343 2341 2337 2338 2340 LOI submitted 09/29/26. Brgy.staff. Ms. Juvy Barrios contact no:09493528341 permit fee and cash bond to be determine as soon as we give them the timeline of the implementation, working hours and implementation target completion Remarks: MH6909 not accssible Remarks :AR will be given up on payment ) Caloocan City Cluster 4 at Brgy.12 for MH 6945,6942,6944 & 6946 accessible MH and MH 6943 & 6941 not accessible MH along Dagat dagatan Ave.but unfortunately our LOI was not receive by the B.Sec.for the reason that once received they acknowledged said letter.Permit fee P2K per MH. Brgy.Sec.Melanie Forte Brgy.Ofc.# 0994-1646811 Remarks : Permit once paid for release. | BR10: =IFERROR((COUNT(BD10)*40%)+(COUNT(BL10)*20%)+(COUNT(BH10)*10%)+(COUNT(BP10)*10%)+(COUNT(AV10)*10%)+(COUNT(AZ10)*10%),0) -> 0.4 | BS10: =IF(BT10>0,WEEKNUM(BT10,1)&"-"&YEAR(BT10),"") -> 45-2026 | BT10: =AP10+3 -> 46332 | BU10: =IF(BV10>0,WEEKNUM(BV10,1)&"-"&YEAR(BV10),"") -> 46-2026 | BV10: 46335 | BW10: =IF(BX10>0,WEEKNUM(BX10,1)&"-"&YEAR(BX10),"") -> 49-2026 | BX10: =IF(CA10="",BV10+CD10,CA10+CD10) -> 46359.827 | BY10: =IF(CA10="",BV10+CD10,CA10+CD10) -> 46359.827 | CB10: =IF(AI10<>0,CC10*0.25,0) -> 0.75 | CC10: 3 | CD10: =IF(R10=0,IFERROR(Q10/(CC10)/1.25,0),IFERROR(R10/(CC10)/1.25,0)) -> 24.826667 | CG10: Frederick, Randy, Mjay, Loyd, Rafael, Winston, Mathew | CH10: =IF(CA10="","NOT STARTED",IF(CA10<>"","ON GOING EXTRACTION",IF(CV10<>"","EXTRACTION COMPLETED"))) -> NOT STARTED | CI10: =IFERROR(CQ10/CM10,0) -> 0 | CM10: =AG10 -> 61 | CN10: =AI10 -> 3 | CR10: =CM10-CQ10 -> 61 | CU10: =CS10+CT10 -> 0
A11: 46235 | B11: RFE | C11: PART OF 233 | D11: GMM | E11: 14.566452 | F11: 121.0771 | G11: Pasig City | H11: Metropolitan Manila | I11: Pasig-Pateros-Taguig | J11: Jessa | K11: Q1 | L11: T-37262327I-1-GMM-00014 | M11: IRUP0008 | N11: New Pasig Exchange | O11: Exchange-L | P11: =IF(OR(NOT(ISNUMBER(Q11)),Q11=0),"NO DATA",IF(Q11<10,"<10 TONNES",">=10 TONNES")) -> >=10 TONNES | Q11: 517.9 | R11: 162.37 | S11: =IF(CH11="CANCELLED","CANCELLED",IF(CV11<>"","EXTRACTION DONE",IF(CH11="ON GOING EXTRACTION","ON GOING EXTRACTION",IF(AR11="RFE","READY FOR EXTRACTION",IF(AR11="ON GOING PERMITTING","ON GOING PERMITTING",IF(AC11<>"","DESIGN APPROVED",IF(AB11<>"","DESIGN SUBMITTED",IF(AA11<>"","DESIGN COMPLETED",IF(Z11<>"","ON GOING DESIGN",IF(Y11<>"","ON GOING SURVEY","NOT STARTED")))))))))) -> ON GOING PERMITTING | T11: =IFERROR((AN11*33%)+(BR11*27%)+(CI11*40%),0) -> 0.384 | U11: =IF(V11>0,WEEKNUM(V11,1)&"-"&YEAR(V11),"") -> 39-2026 | V11: 46291 | W11: =V11 -> 46291 | X11: =IF(AD11>0,"DESIGN WITH CONCERN",IF(AC11>0,"DESIGN APPROVED",IF(AB11>0,"DESIGN FOR APPROVAL",IF(AA11>0,"DESIGN FOR SUBMISSION",IF(Z11>0,"ON GOING DESIGN",IF(Y11>0,"ON GOING SURVEY","FOR SURVEY")))))) -> DESIGN APPROVED | Y11: 46275 | Z11: 46282 | AA11: 46291 | AB11: 46291 | AC11: 46295 | AE11: Both | AF11: =IF(AA11-Y11<0,0,AA11-Y11) -> 16 | AG11: =AH11+AI11 -> 249 | AH11: 121 | AI11: 128 | AJ11: 110 | AK11: 18 | AL11: 0 | AN11: =COUNT(Y11:AC11)/5 -> 1 | AO11: =IF(AQ11>0,WEEKNUM(AQ11,1)&"-"&YEAR(AQ11),"") -> 45-2026 | AP11: 46333 | AQ11: 46333 | AR11: =IF(AA11="","WAITING FOR PLAN",IF(AU11="","PERMITTING NOT STARTED",IF(BR11>=100%,"RFE","ON GOING PERMITTING"))) -> ON GOING PERMITTING | AS11: NA | AT11: NA | AU11: 46316 | AV11: 46316 | AW11: NA | AX11: NA | AY11: 46316 | AZ11: 46316 | BA11: 28 | BB11: 28 | BC11: 46294 | BE11: 4 | BF11: 1 | BG11: 46309 | BI11: 1 | BJ11: 1 | BK11: 46305 | BQ11: Oct 22 New Pasig Exchange Cluster 1 of Pateros Remarks LGU Pateros (Engineering department) - According to Sir Aldren, our application is currently undergoing assessment. He advised me to return on Monday to obtain the results of the assessment. Upon completion and approval of the assessment, the Order of Payment will be issued. 20-Oct-26 City Engineering Office mam @⁨FH Mam Nena Feliciano⁩ sir @⁨carry cheng⁩ as per City engineering office thru sir Digs he requested to submit a revised loi per barangay indicating street with specific date . as for the schedule of joint inspection he will advised me about the date. 15-Oct-26 (Brgy. Ligid Tipas - Brgy. clearance secured with 200 pesos fees, the brgy working permit will be secured once the CTF and LUO permit release. ) (Brgy. Napindan Contact Name: Brgy. Chairman Engr. Gerome Michael R. San Pedro Contact No. : (02)82535606 Designation: Brgy. Chairman Permit fee: 1,500 OR Validity: 1week Remarks - As per the Barangay Chairman, a cash bond of ₱10,000 will be required for the activity. According to the Chairman, the roads in their area are newly constructed, and he wants to ensure that the road restoration is properly and durably completed, considering that trucks frequently pass through the project location. Additionally, the work permit fee is ₱1,500, valid for seven (7) days. Brgy. 3/6 CTF 0/1 LUO 0/1 TMO 0/1 ) Brgy. Ibayo Tipas - They have a barangay ordinance stating that the excavation fee is ₱2,000 per manhole.payable with an Official Receipt (OR). I requested a discount from the barangay admin. Initially, the admin offered a discount equivalent to one manhole only. I further negotiated and requested a discount for two manholes, but the admin advised that the request would need to be discussed with the Barangay Captain for approval. For the meantime, the barangay requested that we submit our Schedule of Activity and Restoration Plan while waiting for confirmation of the discount. Brgy. 3/6 CTF 0/1 LUO 0/1 14-Oct-26 (3-1 to 3-3 of Pasig Grantor:City Engineering Office. Loi received but as instructed it should be revised or application must be by barangay indicating streets. Amount to be paid per street is 625 for manhole opening and 268 for overlayed. valid for 7 days only.) Brgy. Sta. Ana - Permit secured, 1 day Validity. but we can renew the permit. As per the Barangay Secretary, the fee has been reduced to ₱250 since our work is only for restoration. Brgy. 2/6 CTF 0/1 LUO 0/1 13-Oct-26 Brgy. Santa Ana - Received the Letter of Intent (LOI). Unfortunately, the Barangay Secretary was not available at the time of my visit. However, I was able to inform him about our project through a phone call. - According to the Barangay Secretary, he will issue the Order of Payment once he arrives at the barangay office. - The payment fee is ₱1,000.00 for two (2) manholes, with an Official Receipt (OR) to be issued. Status Update: - Brgy.: 0/6 - CTF: 0/1 - LUO: 0/1 9-Oct-26 Brgy Kalawaan Permit Secured with OR Validity: Oct. 8-Nov.8, 2026, can be renewed if not yet used. BRGY 9/14 LGU 0/1 TPMO 0/1 8-Oct-26 (Brgy. Kalawaan Permit is ready but chairman unable to sign the permit he's already out.Advised to comeback tomorrow at 9 am.) Brgy. San Andres Cainta Contact name: Kenneth Temblor contact number: 09065848494 designtion : Personal Assistant Validity of Permit: 1yr Woking hours/days: Permit fee: 3,500 OR Remarks: For payment: The rate is ₱300 per manhole for 17 manholes, with a total amount of ₱5,100. I negotiated with the Barangay Chairman, and the final agreed amount was reduced to ₱3,500. I also verified if there is an HOA since the Barangay Chairman advised that the work area will enter Greenwoods Executive Village. The village has its own Homeowners Association (GEVHAI), so I will also verify with the HOA/administration if a separate permit or clearance is required. Brgy - 0/1 LGU - 0/1 DPWH - 0/1 HOA - 0/1 --- 6-Oct-26 Brgy. San Jose To submit loi. As per Ms. Luisa Cruz barangay Admin-Head MH 152 is not their jurisdiction. Need to verify with other barangay. ----- 5-Oct-26 Brgy. Sta. Ana - Waiting to release the work permit Brgy. Santa Ana Contact name: Jocelyn Mondejar contact number: 640-0229 designtion- Brgy. Secretary Validity of Permit: 1day Woking hours/days: 24hrs/Mon-sun Permit fee: 500 (OR) Remarks: Working Permit Secured Brgy - 6/6 LGU - 0/1 DPWH - 0/1 ---- 2-Oct-26 (Brgy Bambang Contact Name: Kagawad Darwin Contact number: 09751626172 Permit validity: Validity for 1 month advice to inform the Brgy once Mob . We can renew the BC permit anytime no additional fees collected. Working hrs: 10pm to 4am Permit fee: 2,000.00 / OR Remarks : done payment -BC secured.) ---- (Brgy. Sto.Tomas Working Permit - 2,000 Excavation Permit-2,000 Total payment 4,000 MH 251-253, MH276 Permit will be valid for 1 month only. Brgy. suggest to secure permits from LGU and Tpmo first so the permit won't expire.) --- Brgy. Palatiw waiting for Mr. Edwin Capores. Barangay Administrator. He is requiring to submit ID of the personnel to have joint inspection on the location of the 4 overlayed manhole located at MH del Pilar street (MH254-257). 1-Oct-26 (Brgy. Martirez Del 96 - Work Permit secured with 300 pesos fee (OR) valid for 3months) ---- -- (Brgy Malinao - as per talk to admin Vel Garcia #0994-840-1996. resubmit of loi including the exact location of MH, exact Date duration of works . - MH estimated fee is PHP 500.) --- ( Brgy. Sagad Barangay permit for payment. mam @⁨FH Mam Nena Feliciano⁩ sir @⁨carry cheng⁩ permit will be valid only for 1 month. Since they are requiring us to give exact date of activity and we cannot yet determine the exact date is it safe to say to start the permit validity from nov. 1-30?Payment fee is only 2,000. Brgy. Sagad Permit secured. We may request to change the Date of validity depending on the release of permit from LGU and Tpmo. As long as it's for a month only.) ---- (Brgy. Aguho - Permit Secured with 1000 pesos fee OR, 2months validation. )Brgy Bambang -- - follow up BC amount fee .php 2,000.00 with OR. --- 30-Sep-26 (Taguig City Hall - Mobility Office Remarks: Follow-up with Ms. Glenda: According to Ms. Glenda, the presentation may be scheduled next week or the following week since they already have several big projects lined up. However, she said she will try to include our presentation in their schedule. She advised us to prepare the Geographic Map with the specific locations of all manholes, including the inaccessible manholes. She will message me in advance once the specific presentation date is confirmed.) ---- ( hall bambang pasig. - submit the plan and loi as per sec. Rona as per her brgy kagawad eng. ed will be the one inspecting the MH and computation per MH. advice to be back tomorrow .with contact number : 09635414957.) -- (cluster 3- 2 of pasig Grantor: Barangay kapasigan brgy permit secured. valid until dec. 31, 2026) ---- (LGU Pateros Municipal Engineering - Need to submit the following requirements. LOI add. to Engr. Eldar G. Jimenez Brgy. Clearance Detail Plan DPWH Clearance (For National Road) BOM Engineering Office 0998-985-4658 Thanks) --- (Brgy. San Miguel MH258 Loi received but need To submit ID of personnel prior issuance of permit. Assessment fee to follow contact person :Mr. Jaime Cruz-09997525019) (BRGY LIGID-TIPAS -They will not give any request details for working permit unless we can provide the required requirements they needed same with brgy. ususan. Letter indicating the scheduled date of the activity and the exact location Project Plan Photocopy of the CTF Permit Photocopy of the LUO Permit )Brgy.Sto. Tomas (MH 251-253, MH276) Loi received. Barangay Secretary ms. Danilyn Guimba thru contact person jester aguilar-09542630448) need to review and will give feedback until tomorrow afternoon. --- 29-Sep-26 (Cainta Engineering. - as per talk to ms. lyka attached the Brgy permit to the plan first . each MH they will be charge php2,500 and has the excavation Bond to be computed to their end. contact number -09756153617) --- (Barangay Sagad (Pasig) Loi received. For follow up tomorrow. To inform the barangay on the target date of activity to assess the payment fee.) --- (NEW PASIG EXCHANGE Cluster 1 @Brgy. Santa Ana MH169,MH170,MH171,MH172,MH173,MH221,MH222,MH223 - Submitted Loi to Brgy. Sec. Jocelyn A. Mondejar as per brgy secretary. the fee is 500 per manhole. she also give me the ORDER OF PAYMENT. Contact Person Jocelyn Mondejar Bgry. Sectary 640-0229) ---- ( Cluster 2 Taguig City MH No.: MH1033, MH1032, MH1031, MH1030 Grantor Name: Brgy. Tuktukan Contact Person: Rea Bañal Contact No.: 8275-0957 Designtion: Barangay Staff Validity of Permit; 1Month Woking hours/days: based on the activity indicated in the submitted letter Permit fee: To be computed Type of Receipt: OR Remarks: - As per Ma’am Rea Bañal, Barangay Staff, there is no fixed amount for the Telecom project. The permit fee will be computed depending on the project activity. We need to submit the required documents first before they can provide the corresponding permit fee/amount. Requirements: Letter indicating the scheduled date of the activity Project Plan Photocopy of the CTF Permit Photocopy of the LUO Permit) ---- (Pasig cluster 5 Grantor: Brgy sto. tomas Barangay secretary went out to attend seminar. loi can only be received by her. Advised to come back tomorrow to talk to barangay secretary.)(NEW PASIG EXCHANGE Cluster 1 @Brgy. MAGTANGGOL MH120,MH121,MH216,MH122,MH217 Submitted LOI. as per Bgry. Sec. MARIBETH BUENAVENTURA the fee for Bgry. Clearance is 1000 with OR. validity of permit was 6 months. CONTACT PERSON : MARIBETH BUENAVENTURA Brgy. Secretary 09952484038) ---- (PASIG CITY -SN: New Pasig Cluster 5 Grantor: Barangay Palatiw loi received. Since we cannot provide actual photo or location of manhole along MH Del Pilar street.MH255-257 we are requested to attend barangay joint inspection prior issuance of permit. Assessment fee to follow right after inspection. contact person: Edwin Capores- 09070218886 Brgy hall Maybunga - as per talk to Ms.Rhea brgy secretary with contact number : 09268156617 - Excavation fee with OR is php1,000.00. duration of permits is 1month negotiate if we they can extend of 6months . as per her be back tomorrow to talk to brgy Captain he will be the one approved the duration of permits . (TAGUIG -Cluster 2 Taguig City MH No.: MH1034 and MH1036 Grantor Name: Brgy. Sta. Ana Contact Person: Rustin Remillo Contact No.: 0947-613-9068 Designtion: Barangay Secretary Validity of Permit; 1Month Woking hours/days: based on the activity indicated in the submitted letter Permit fee: 500 per manhole Type of Receipt: OR Remarks: - As per Sir Rustin need to submit the following requirements. They will provide the order of payment upon request the work permit after we submit their require requirements. Letter indicating the scheduled date of the activity Project Plan Photocopy of the CTF Permit Photocopy of the LUO Permit | BR11: =IFERROR((COUNT(BD11)*40%)+(COUNT(BL11)*20%)+(COUNT(BH11)*10%)+(COUNT(BP11)*10%)+(COUNT(AV11)*10%)+(COUNT(AZ11)*10%),0) -> 0.2 | BS11: =IF(BT11>0,WEEKNUM(BT11,1)&"-"&YEAR(BT11),"") -> 46-2026 | BT11: =AP11+3 -> 46336 | BU11: =IF(BV11>0,WEEKNUM(BV11,1)&"-"&YEAR(BV11),"") -> 45-2026 | BV11: 46330 | BW11: =IF(BX11>0,WEEKNUM(BX11,1)&"-"&YEAR(BX11),"") -> 50-2026 | BX11: =IF(CA11="",BV11+CD11,CA11+CD11) -> 46362.474 | BY11: 46330 | BZ11: 10/29/26: ISP only; OSP will continue based on the Permit Secured; Taguig will be first inExtraction | CB11: =IF(AI11<>0,CC11*0.25,0) -> 1 | CC11: 4 | CD11: =IF(R11=0,IFERROR(Q11/(CC11)/1.25,0),IFERROR(R11/(CC11)/1.25,0)) -> 32.474 | CF11: ISP ONLY | CG11: Jed, Mark, Ron, Adrian, Jerome, Naj, Alain | CH11: =IF(CA11="","NOT STARTED",IF(CA11<>"","ON GOING EXTRACTION",IF(CV11<>"","EXTRACTION COMPLETED"))) -> NOT STARTED | CI11: =IFERROR(CQ11/CM11,0) -> 0 | CM11: =AG11 -> 249 | CN11: =AI11 -> 128 | CR11: =CM11-CQ11 -> 249 | CU11: =CS11+CT11 -> 0
A12: 46235 | B12: RFE | C12: PART OF 233 | D12: GMM | E12: 14.694408 | F12: 120.96861 | G12: Valenzuela City | H12: Metropolitan Manila | I12: CaMaNaVa | J12: Dan | K12: Q1 | L12: T-37262327I-1-GMM-00013 | M12: IRUP0009 | N12: Valenzuela Exchange | O12: Exchange-L | P12: =IF(OR(NOT(ISNUMBER(Q12)),Q12=0),"NO DATA",IF(Q12<10,"<10 TONNES",">=10 TONNES")) -> >=10 TONNES | Q12: 505.6 | R12: 188.31 | S12: =IF(CH12="CANCELLED","CANCELLED",IF(CV12<>"","EXTRACTION DONE",IF(CH12="ON GOING EXTRACTION","ON GOING EXTRACTION",IF(AR12="RFE","READY FOR EXTRACTION",IF(AR12="ON GOING PERMITTING","ON GOING PERMITTING",IF(AC12<>"","DESIGN APPROVED",IF(AB12<>"","DESIGN SUBMITTED",IF(AA12<>"","DESIGN COMPLETED",IF(Z12<>"","ON GOING DESIGN",IF(Y12<>"","ON GOING SURVEY","NOT STARTED")))))))))) -> ON GOING EXTRACTION | T12: =IFERROR((AN12*33%)+(BR12*27%)+(CI12*40%),0) -> 0.38526582 | U12: =IF(V12>0,WEEKNUM(V12,1)&"-"&YEAR(V12),"") -> 40-2026 | V12: 46295 | W12: =V12 -> 46295 | X12: =IF(AD12>0,"DESIGN WITH CONCERN",IF(AC12>0,"DESIGN APPROVED",IF(AB12>0,"DESIGN FOR APPROVAL",IF(AA12>0,"DESIGN FOR SUBMISSION",IF(Z12>0,"ON GOING DESIGN",IF(Y12>0,"ON GOING SURVEY","FOR SURVEY")))))) -> DESIGN APPROVED | Y12: 46279 | Z12: 46288 | AA12: 46295 | AB12: 46296 | AC12: 46302 | AE12: Both | AF12: =IF(AA12-Y12<0,0,AA12-Y12) -> 16 | AG12: =AH12+AI12 -> 316 | AH12: 162 | AI12: 154 | AJ12: 4 | AK12: 150 | AL12: 0 | AN12: =COUNT(Y12:AC12)/5 -> 1 | AO12: =IF(AQ12>0,WEEKNUM(AQ12,1)&"-"&YEAR(AQ12),"") -> 47-2026 | AP12: 46345 | AQ12: 46346 | AR12: =IF(AA12="","WAITING FOR PLAN",IF(AU12="","PERMITTING NOT STARTED",IF(BR12>=100%,"RFE","ON GOING PERMITTING"))) -> ON GOING PERMITTING | AS12: NA | AT12: NA | AU12: 46316 | AV12: 46316 | AW12: NA | AX12: NA | AY12: 46316 | AZ12: 46316 | BA12: 3 | BB12: 18 | BC12: 46296 | BE12: 3 | BG12: 46323 | BI12: 1 | BK12: 46302 | BQ12: Oct 23 Bgry:masambong REMARKS: brgy captain have ongoing interview waiting for renego BRGY 0/5 LGU: 0/0 TRAFFIC 0/0 DPWH: 0/0 masambong REMARKS: brgy captain have ongoing interview waiting for renego BRGY 0/5 LGU: 0/0 TRAFFIC 0/0 DPWH: 0/0 masambong REMARKS: brgy captain have ongoing interview waiting for renego BRGY 0/5 LGU: 0/0 TRAFFIC 0/0 DPWH: 0/0 masambong REMARKS: brgy captain have ongoing interview waiting for renego BRGY 0/5 LGU: 0/0 TRAFFIC 0/0 DPWH: 0/0 OCT 22 Brgy. Veinte Reales 21mh permit fee 500/ MH validity:1 month AR / OR :OR Remarks: for Payment OCT 22 2026 Barangay: Canumay West No. of Manholes: 11 MH Remarks: As per Barangay Secretary Rico Balono, we are required to attend a meeting with the Kapitan on Monday at 3:00 PM to explain our mobilization plan. Hon. Kapitan Mario San Andres is currently unavailable due to a scheduled SOBA tomorrow. 20-Oct-26 Brgy. dalandann Grantor : 28mh For payment Remarks: waiting permit to be release 15-Oct-26 Brgy. Malanday Permit fee: 1,000 OR Validity: 1month 14-Oct-26 Brgy. Mabolo Remarks: They are requesting additional photos to complete their requirements. 13-Oct-26 BRGY. DALANDANAN REMARKS: According to the Barangay staff, the Barangay Captain does not agree to lowering the fee because they have an ordinance to follow. Therefore, the permit fee will amount to ₱28,000 for the 28 manholes. Excavation/ Industrial: 1,000 x 28= Total of 28,000 OR. 18 manholes for Cluster 4.1 and 10 manholes for Cluster 4.2 Validity: 3months ---- 8-Oct-26 brgy. panghulo,malabon mh7776 LOI SUBMITTED contact person: Brgy Clerk: Venus Cobar contact no. 09279891566 remarks: As per Ms. Venus Cobar, the barangay will not issue the work permit and clearance at this time due to an ongoing road construction project in the area near our manhole location. The barangay is concerned that the additional work may worsen traffic congestion in the area, even though the proposed mobilization schedule and planned night work were properly explained thank you EdMinay --- 7-Oct-26 VALENZUELA TRAFFIC Currently at Valenzuela Traffic Office, awaiting for someone who can assist us and provide the requirements for the Traffic Clearance 5-Oct-26 (Brgy. Malinta- 25 Manholes under Brgy.Malinta, with 13 overlayed. Permit fee 1,860.00 O.R . Just see to it Restoration eill be Done after Excavation. NOTE: will edit report later Indicating Particular Manholes of Each Brgy. Will visit first other Brgy. For Manholes Verification. @⁨FH Mam Nena Feliciano⁩ ma'am) ---- Brgy. Karuhatan LOI SUBMITTED 33Mh Permit fee: 200 per MH +18 CEDULA IF the job order is opening of manhole only 500 per MH if there's Excavation 1k per MH Cashbond- Refundable OR /AR : OR Contact person Brgy. Clerk Anna Taccad 09966739761 REMARKS: For payment to secure permit 1-Oct-26 (Barangay Santulan for MH291 MH292 MH293 MH294 MH295 MH296 MH297 MH298 MH 290 LOI : SUBMITTED WITH BRGY SANTULAN SEC: Fernando Fernandez CONTACT # 09075052138 REMARKS : Per Barangay Secretary, a meeting will be arranged with Brgy. Chairman Jerome Jasper P. Manalastas to finalize the barangay permits, clearances, and plans. Since the manhole location at MH Del Pilar St. is a heavy-traffic area, the Implementation Engineer will also be requested to attend to further discuss the project scope and implementation. The Barangay Secretary will advise me once the) ---- Barangay Panghulo, Obando, Bulacan Manholes: VAL_MH006, MH303, MH304, MH305, MH306, MH307 Status: LOI submitted to Barangay Treasurer Maria Celina Sto. Tomas. As per the Barangay Treasurer, they will provide an update tomorrow regarding the barangay permit, clearance, and cash bond, as the Barangay Secretary and Chairman are currently attending a seminar. | BR12: =IFERROR((COUNT(BD12)*40%)+(COUNT(BL12)*20%)+(COUNT(BH12)*10%)+(COUNT(BP12)*10%)+(COUNT(AV12)*10%)+(COUNT(AZ12)*10%),0) -> 0.2 | BS12: =IF(BT12>0,WEEKNUM(BT12,1)&"-"&YEAR(BT12),"") -> 48-2026 | BT12: =AP12+3 -> 46348 | BU12: =IF(BV12>0,WEEKNUM(BV12,1)&"-"&YEAR(BV12),"") -> 44-2026 | BV12: 46323 | BW12: =IF(BX12>0,WEEKNUM(BX12,1)&"-"&YEAR(BX12),"") -> 49-2026 | BX12: =IF(CA12="",BV12+CD12,CA12+CD12) -> 46360.662 | BY12: 46325 | BZ12: 10/29/26: Started ISP only; Continuation of OSP is based on Permit Secured - Permitting Target: 11/20; OSP Extraction Target Start: 11/21 | CA12: 46323 | CB12: =IF(AI12<>0,CC12*0.25,0) -> 1 | CC12: 4 | CD12: =IF(R12=0,IFERROR(Q12/(CC12)/1.25,0),IFERROR(R12/(CC12)/1.25,0)) -> 37.662 | CE12: DIMARCO | CF12: ISP ONLY | CG12: Frederick, Randy, Mjay, Loyd, Rafael, Winston, Mathew | CH12: =IF(CA12="","NOT STARTED",IF(CA12<>"","ON GOING EXTRACTION",IF(CV12<>"","EXTRACTION COMPLETED"))) -> ON GOING EXTRACTION | CI12: =IFERROR(CQ12/CM12,0) -> 0.003164557 | CJ12: ‎10/28/26: ‎1,859.30 kgs extracted ‎ ‎26 pcs closures ‎ ‎2400 / 422.8 kgs / 49.83 meters ‎2000 / 68.3 kgs / 10 meters ‎1800 / 124.9 kgs / 23.45 meters ‎1200 / 598.6 kgs / 104.24 meters ‎900 / 87.5 kgs / 25.27 meters ‎600 / 114.3 kgs / 29.82 meters ‎100 / 442.9 kgs / 529.92 meters | CM12: =AG12 -> 316 | CN12: =AI12 -> 154 | CQ12: 1 | CR12: =CM12-CQ12 -> 315 | CS12: 1.8593 | CU12: =CS12+CT12 -> 1.8593
A13: 46235 | B13: RFE | C13: PART OF 233 | D13: NLZ | E13: 15.063876 | F13: 120.72241 | G13: Mexico City | H13: Pampanga | I13: PamBatZam | K13: Q2 | M13: IRUP0010 | N13: Mexico Sub-Exchange | O13: Sub-Exchange-S | P13: =IF(OR(NOT(ISNUMBER(Q13)),Q13=0),"NO DATA",IF(Q13<10,"<10 TONNES",">=10 TONNES")) -> >=10 TONNES | Q13: 15.5 | S13: =IF(CH13="CANCELLED","CANCELLED",IF(CV13<>"","EXTRACTION DONE",IF(CH13="ON GOING EXTRACTION","ON GOING EXTRACTION",IF(AR13="RFE","READY FOR EXTRACTION",IF(AR13="ON GOING PERMITTING","ON GOING PERMITTING",IF(AC13<>"","DESIGN APPROVED",IF(AB13<>"","DESIGN SUBMITTED",IF(AA13<>"","DESIGN COMPLETED",IF(Z13<>"","ON GOING DESIGN",IF(Y13<>"","ON GOING SURVEY","NOT STARTED")))))))))) -> DESIGN COMPLETED | T13: =IFERROR((AN13*33%)+(BR13*27%)+(CI13*40%),0) -> 0.198 | U13: =IF(V13>0,WEEKNUM(V13,1)&"-"&YEAR(V13),"") -> 42-2026 | V13: 46308 | W13: =V13 -> 46308 | X13: =IF(AD13>0,"DESIGN WITH CONCERN",IF(AC13>0,"DESIGN APPROVED",IF(AB13>0,"DESIGN FOR APPROVAL",IF(AA13>0,"DESIGN FOR SUBMISSION",IF(Z13>0,"ON GOING DESIGN",IF(Y13>0,"ON GOING SURVEY","FOR SURVEY")))))) -> DESIGN FOR SUBMISSION | Y13: 46287 | Z13: 46287 | AA13: 46308 | AE13: Both | AF13: =IF(AA13-Y13<0,0,AA13-Y13) -> 21 | AG13: =AH13+AI13 -> 17 | AH13: 1 | AI13: 16 | AJ13: 0 | AK13: 0 | AL13: 0 | AN13: =COUNT(Y13:AC13)/5 -> 0.6 | AO13: =IF(AQ13>0,WEEKNUM(AQ13,1)&"-"&YEAR(AQ13),"") | AP13: 46371 | AQ13: 0 | AR13: =IF(AA13="","WAITING FOR PLAN",IF(AU13="","PERMITTING NOT STARTED",IF(BR13>=100%,"RFE","ON GOING PERMITTING"))) -> PERMITTING NOT STARTED | BR13: =IFERROR((COUNT(BD13)*40%)+(COUNT(BL13)*20%)+(COUNT(BH13)*10%)+(COUNT(BP13)*10%)+(COUNT(AV13)*10%)+(COUNT(AZ13)*10%),0) -> 0 | BS13: =IF(BT13>0,WEEKNUM(BT13,1)&"-"&YEAR(BT13),"") | BU13: =IF(BV13>0,WEEKNUM(BV13,1)&"-"&YEAR(BV13),"") | BW13: =IF(BX13>0,WEEKNUM(BX13,1)&"-"&YEAR(BX13),"") -> 1-1900 | BX13: =IF(CA13="",BV13+CD13,CA13+CD13) -> 6.2 | CB13: =IF(AI13<>0,CC13*0.25,0) -> 0.5 | CC13: 2 | CD13: =IF(R13=0,IFERROR(Q13/(CC13)/1.25,0),IFERROR(R13/(CC13)/1.25,0)) -> 6.2 | CH13: =IF(CA13="","NOT STARTED",IF(CA13<>"","ON GOING EXTRACTION",IF(CV13<>"","EXTRACTION COMPLETED"))) -> NOT STARTED | CI13: =IFERROR(CQ13/CM13,0) -> 0 | CM13: =AG13 -> 17 | CN13: =AI13 -> 16 | CR13: =CM13-CQ13 -> 17 | CU13: =CS13+CT13 -> 0
A14: 46235 | B14: RFE | C14: PART OF 233 | D14: NLZ | E14: 15.310246 | F14: 120.9472 | G14: Gapan City | H14: Nueva Ecija | I14: Tarlac-NE | J14: Rowlan | K14: Q1 | L14: T-37262327I-1-NLZ-00008 | M14: IRUP0011 | N14: Gapan Sub-Exchange | O14: Sub-Exchange-S | P14: =IF(OR(NOT(ISNUMBER(Q14)),Q14=0),"NO DATA",IF(Q14<10,"<10 TONNES",">=10 TONNES")) -> >=10 TONNES | Q14: 31.5 | R14: 10.1 | S14: =IF(CH14="CANCELLED","CANCELLED",IF(CV14<>"","EXTRACTION DONE",IF(CH14="ON GOING EXTRACTION","ON GOING EXTRACTION",IF(AR14="RFE","READY FOR EXTRACTION",IF(AR14="ON GOING PERMITTING","ON GOING PERMITTING",IF(AC14<>"","DESIGN APPROVED",IF(AB14<>"","DESIGN SUBMITTED",IF(AA14<>"","DESIGN COMPLETED",IF(Z14<>"","ON GOING DESIGN",IF(Y14<>"","ON GOING SURVEY","NOT STARTED")))))))))) -> ON GOING PERMITTING | T14: =IFERROR((AN14*33%)+(BR14*27%)+(CI14*40%),0) -> 0.546 | U14: =IF(V14>0,WEEKNUM(V14,1)&"-"&YEAR(V14),"") -> 41-2026 | V14: 46302 | W14: =V14 -> 46302 | X14: =IF(AD14>0,"DESIGN WITH CONCERN",IF(AC14>0,"DESIGN APPROVED",IF(AB14>0,"DESIGN FOR APPROVAL",IF(AA14>0,"DESIGN FOR SUBMISSION",IF(Z14>0,"ON GOING DESIGN",IF(Y14>0,"ON GOING SURVEY","FOR SURVEY")))))) -> DESIGN APPROVED | Y14: 46291 | Z14: 46292 | AA14: 46295 | AB14: 46296 | AC14: 46300 | AE14: Both | AF14: =IF(AA14-Y14<0,0,AA14-Y14) -> 4 | AG14: =AH14+AI14 -> 19 | AH14: 6 | AI14: 13 | AJ14: 12 | AK14: 1 | AL14: 0 | AN14: =COUNT(Y14:AC14)/5 -> 1 | AO14: =IF(AQ14>0,WEEKNUM(AQ14,1)&"-"&YEAR(AQ14),"") -> 45-2026 | AP14: 46338 | AQ14: 46332 | AR14: =IF(AA14="","WAITING FOR PLAN",IF(AU14="","PERMITTING NOT STARTED",IF(BR14>=100%,"RFE","ON GOING PERMITTING"))) -> ON GOING PERMITTING | AS14: NA | AT14: NA | AU14: 46316 | AV14: 46316 | AW14: NA | AX14: NA | AY14: 46316 | AZ14: 46316 | BA14: 8 | BB14: 8 | BC14: 46301 | BD14: 46311 | BE14: 1 | BG14: 46314 | BI14: 1 | BJ14: 1 | BK14: 46324 | BL14: 46324 | BQ14: 19-Oct-26 GAPAN LGU REMARKS: According to Sir Richard (OIC Building Officer), we must submit the complete set of requirements before proceeding with the inspection. - We are also required to provide a written Construction Safety and Health Program (CSHP), signed by the PLDT Safety Officer, which outlines the safe procedures for working on and maintaining the manholes. - Additionally, we must provide documentation confirming that PLDT has secured permission from Necco and PrimeWater, ensuring that the opening of our manholes will not interfere with any existing lines belonging to these two entities. - We are also required to provide a tarpaulin regarding the excavation permit. They have provided a sample for a building-related tarpaulin, which simply needs to be updated for the excavation permit. for futher questions and concerns here's the contact # of sir Richard. Contact Person: RICHARD BLANCO Designation: OIC B.O contact # : 09156494099 Brgy - 8/8 LGU - 0/1 DPWH - 0/1 TRAFFIC 15-Oct-26 BRGY. SAN NICOLAS - still waiting for brgy captain for the donation fee of BC. 14-Oct-26 (BRGY. SAN NICOLAS MH : ADDITONAL 9 MH ( ALL ACCESSIBLE) REMARKS: I submitted another LOI because the previous one hadn't been brought to the barangay captain's attention. Secretary Lory said she would text me with an update later today. CONTACT PERSON: SEC. LORY BRGY. SECRETARY 09051652535) ( BRGY. STO CRISTO NORTE MH: GPNHH007 - NOT ACCESSIBLE GPNHH006 GPNHH005 REMARKS: SECURED PERMIT VALIDITY: until end of this year AMOUNT : 500 (AR) BRGY - 3/6 ADDITIONAL BRGY - 1/2 LGU- 0/1 DPWH-0/1 TRAFFIC- 0/1)Brgy. Sto Cristo Norte - waiting for the budget to transfer to secured BC. ---- 13-Oct-26 BRGY BAYANIHAN MH: SB_001 - not accessible GPNHH004 - ACCESSIBLE GPNHH003 GPNHH002 REMARKS: SECURED PERMIT VALIDITY: until end of this year AMOUNT : 2000 (AR) BRGY - 2/6 ADDITIONAL BRGY - 1/2 LGU- 0/1 DPWH-0/1 TRAFFIC- 0/1 ----- 5-Oct-26 BRGY. SAN VICENTE POB Contact Name: JESSIE A. ISON Designation - BGRY.CAPTAIN Validity permit - 1 YEAR Permit Fee - 500 Remarks : PERMIT SECURED | BR14: =IFERROR((COUNT(BD14)*40%)+(COUNT(BL14)*20%)+(COUNT(BH14)*10%)+(COUNT(BP14)*10%)+(COUNT(AV14)*10%)+(COUNT(AZ14)*10%),0) -> 0.8 | BS14: =IF(BT14>0,WEEKNUM(BT14,1)&"-"&YEAR(BT14),"") -> 47-2026 | BT14: =AP14+3 -> 46341 | BU14: =IF(BV14>0,WEEKNUM(BV14,1)&"-"&YEAR(BV14),"") -> 46-2026 | BV14: 46335 | BW14: =IF(BX14>0,WEEKNUM(BX14,1)&"-"&YEAR(BX14),"") -> 46-2026 | BX14: =IF(CA14="",BV14+CD14,CA14+CD14) -> 46339.04 | BY14: =IF(CA14="",BV14+CD14,CA14+CD14) -> 46339.04 | BZ14: 10/29/26: | CB14: =IF(AI14<>0,CC14*0.25,0) -> 0.5 | CC14: 2 | CD14: =IF(R14=0,IFERROR(Q14/(CC14)/1.25,0),IFERROR(R14/(CC14)/1.25,0)) -> 4.04 | CG14: Jed, Mark, Ron, Adrian, Jerome, Naj, Alain | CH14: =IF(CA14="","NOT STARTED",IF(CA14<>"","ON GOING EXTRACTION",IF(CV14<>"","EXTRACTION COMPLETED"))) -> NOT STARTED | CI14: =IFERROR(CQ14/CM14,0) -> 0 | CM14: =AG14 -> 19 | CN14: =AI14 -> 13 | CR14: =CM14-CQ14 -> 19 | CU14: =CS14+CT14 -> 0
A15: 46235 | B15: RFE | C15: PART OF 233 | D15: NLZ | E15: 15.716322 | F15: 120.90366 | G15: Munoz City | H15: Nueva Ecija | I15: Tarlac-NE | J15: Rowlan | K15: Q1 | L15: T-37262327I-1-NLZ-00003 | M15: IRUP0012 | N15: Munoz Sub-Exchange | O15: Sub-Exchange-S | P15: =IF(OR(NOT(ISNUMBER(Q15)),Q15=0),"NO DATA",IF(Q15<10,"<10 TONNES",">=10 TONNES")) -> >=10 TONNES | Q15: 20.6 | R15: 6.05 | S15: =IF(CH15="CANCELLED","CANCELLED",IF(CV15<>"","EXTRACTION DONE",IF(CH15="ON GOING EXTRACTION","ON GOING EXTRACTION",IF(AR15="RFE","READY FOR EXTRACTION",IF(AR15="ON GOING PERMITTING","ON GOING PERMITTING",IF(AC15<>"","DESIGN APPROVED",IF(AB15<>"","DESIGN SUBMITTED",IF(AA15<>"","DESIGN COMPLETED",IF(Z15<>"","ON GOING DESIGN",IF(Y15<>"","ON GOING SURVEY","NOT STARTED")))))))))) -> READY FOR EXTRACTION | T15: =IFERROR((AN15*33%)+(BR15*27%)+(CI15*40%),0) -> 0.6 | U15: =IF(V15>0,WEEKNUM(V15,1)&"-"&YEAR(V15),"") -> 41-2026 | V15: 46303 | W15: =V15 -> 46303 | X15: =IF(AD15>0,"DESIGN WITH CONCERN",IF(AC15>0,"DESIGN APPROVED",IF(AB15>0,"DESIGN FOR APPROVAL",IF(AA15>0,"DESIGN FOR SUBMISSION",IF(Z15>0,"ON GOING DESIGN",IF(Y15>0,"ON GOING SURVEY","FOR SURVEY")))))) -> DESIGN APPROVED | Y15: 46291 | Z15: 46293 | AA15: 46296 | AB15: 46296 | AC15: 46300 | AE15: ISP only | AF15: =IF(AA15-Y15<0,0,AA15-Y15) -> 5 | AG15: =AH15+AI15 -> 5 | AH15: 5 | AI15: 0 | AJ15: 0 | AK15: 0 | AL15: 0 | AN15: =COUNT(Y15:AC15)/5 -> 1 | AO15: =IF(AQ15>0,WEEKNUM(AQ15,1)&"-"&YEAR(AQ15),"") -> 46-2026 | AP15: 46339 | AQ15: 46339 | AR15: =IF(AA15="","WAITING FOR PLAN",IF(AU15="","PERMITTING NOT STARTED",IF(BR15>=100%,"RFE","ON GOING PERMITTING"))) -> RFE | AS15: NA | AT15: NA | AU15: 46316 | AV15: 46316 | AW15: NA | AX15: NA | AY15: 46316 | AZ15: 46316 | BA15: 2 | BB15: 2 | BC15: 46303 | BD15: 46303 | BE15: 1 | BF15: 1 | BG15: 46303 | BH15: 46303 | BI15: 1 | BJ15: 1 | BK15: 46303 | BL15: 46303 | BM15: 1 | BN15: 1 | BO15: 46303 | BP15: 46303 | BQ15: 9-Oct-26 -RFE Sites Secured Permit | BR15: =IFERROR((COUNT(BD15)*40%)+(COUNT(BL15)*20%)+(COUNT(BH15)*10%)+(COUNT(BP15)*10%)+(COUNT(AV15)*10%)+(COUNT(AZ15)*10%),0) -> 1 | BS15: =IF(BT15>0,WEEKNUM(BT15,1)&"-"&YEAR(BT15),"") -> 47-2026 | BT15: =AP15+3 -> 46342 | BU15: =IF(BV15>0,WEEKNUM(BV15,1)&"-"&YEAR(BV15),"") -> 45-2026 | BV15: 46331 | BW15: =IF(BX15>0,WEEKNUM(BX15,1)&"-"&YEAR(BX15),"") -> 45-2026 | BX15: =IF(CA15="",BV15+CD15,CA15+CD15) -> 46333.42 | BY15: 46335 | BZ15: 10/29/26: ISP + 5 MH only; No Need DD | CB15: =IF(AI15<>0,CC15*0.25,0) -> 0 | CC15: 2 | CD15: =IF(R15=0,IFERROR(Q15/(CC15)/1.25,0),IFERROR(R15/(CC15)/1.25,0)) -> 2.42 | CE15: ASSURE | CF15: BOTH | CG15: Rainer, Michael, Richard, Ron | CH15: =IF(CA15="","NOT STARTED",IF(CA15<>"","ON GOING EXTRACTION",IF(CV15<>"","EXTRACTION COMPLETED"))) -> NOT STARTED | CI15: =IFERROR(CQ15/CM15,0) -> 0 | CM15: =AG15 -> 5 | CN15: =AI15 -> 0 | CR15: =CM15-CQ15 -> 5 | CU15: =CS15+CT15 -> 0
A16: 46235 | B16: RFE | C16: PART OF 233 | D16: NLZ | E16: 16.41527 | F16: 120.58939 | G16: Baguio City | H16: Benguet | I16: Baguio | J16: Rowlan | K16: Q1 | M16: IRUP0013 | N16: Baguio Toll Exchange | O16: Exchange-S | P16: =IF(OR(NOT(ISNUMBER(Q16)),Q16=0),"NO DATA",IF(Q16<10,"<10 TONNES",">=10 TONNES")) -> NO DATA | Q16: 0 | R16: 0.22 | S16: =IF(CH16="CANCELLED","CANCELLED",IF(CV16<>"","EXTRACTION DONE",IF(CH16="ON GOING EXTRACTION","ON GOING EXTRACTION",IF(AR16="RFE","READY FOR EXTRACTION",IF(AR16="ON GOING PERMITTING","ON GOING PERMITTING",IF(AC16<>"","DESIGN APPROVED",IF(AB16<>"","DESIGN SUBMITTED",IF(AA16<>"","DESIGN COMPLETED",IF(Z16<>"","ON GOING DESIGN",IF(Y16<>"","ON GOING SURVEY","NOT STARTED")))))))))) -> ON GOING PERMITTING | T16: =IFERROR((AN16*33%)+(BR16*27%)+(CI16*40%),0) -> 0.291 | U16: =IF(V16>0,WEEKNUM(V16,1)&"-"&YEAR(V16),"") -> 42-2026 | V16: 46306 | W16: =V16 -> 46306 | X16: =IF(AD16>0,"DESIGN WITH CONCERN",IF(AC16>0,"DESIGN APPROVED",IF(AB16>0,"DESIGN FOR APPROVAL",IF(AA16>0,"DESIGN FOR SUBMISSION",IF(Z16>0,"ON GOING DESIGN",IF(Y16>0,"ON GOING SURVEY","FOR SURVEY")))))) -> DESIGN FOR APPROVAL | Y16: 46302 | Z16: 46304 | AA16: 46307 | AB16: 46322 | AE16: Both | AF16: =IF(AA16-Y16<0,0,AA16-Y16) -> 5 | AG16: =AH16+AI16 -> 1 | AH16: 1 | AN16: =COUNT(Y16:AC16)/5 -> 0.8 | AO16: =IF(AQ16>0,WEEKNUM(AQ16,1)&"-"&YEAR(AQ16),"") -> 47-2026 | AP16: 46342 | AQ16: 46346 | AR16: =IF(AA16="","WAITING FOR PLAN",IF(AU16="","PERMITTING NOT STARTED",IF(BR16>=100%,"RFE","ON GOING PERMITTING"))) -> ON GOING PERMITTING | AS16: NA | AT16: NA | AU16: 46324 | AV16: 46324 | BC16: 46324 | BE16: 1 | BF16: 1 | BG16: 46324 | BI16: 1 | BK16: 46324 | BR16: =IFERROR((COUNT(BD16)*40%)+(COUNT(BL16)*20%)+(COUNT(BH16)*10%)+(COUNT(BP16)*10%)+(COUNT(AV16)*10%)+(COUNT(AZ16)*10%),0) -> 0.1 | BS16: =IF(BT16>0,WEEKNUM(BT16,1)&"-"&YEAR(BT16),"") -> 47-2026 | BT16: =AP16+3 -> 46345 | BU16: =IF(BV16>0,WEEKNUM(BV16,1)&"-"&YEAR(BV16),"") -> 48-2026 | BV16: 46350 | BW16: =IF(BX16>0,WEEKNUM(BX16,1)&"-"&YEAR(BX16),"") -> 48-2026 | BX16: =IF(CA16="",BV16+CD16,CA16+CD16) -> 46350.088 | BY16: =IF(CA16="",BV16+CD16,CA16+CD16) -> 46350.088 | CB16: =IF(AI16<>0,CC16*0.25,0) -> 0 | CC16: 2 | CD16: =IF(R16=0,IFERROR(Q16/(CC16)/1.25,0),IFERROR(R16/(CC16)/1.25,0)) -> 0.088 | CH16: =IF(CA16="","NOT STARTED",IF(CA16<>"","ON GOING EXTRACTION",IF(CV16<>"","EXTRACTION COMPLETED"))) -> NOT STARTED | CI16: =IFERROR(CQ16/CM16,0) -> 0 | CM16: =AG16 -> 1 | CN16: =AI16 -> 0 | CR16: =CM16-CQ16 -> 1 | CU16: =CS16+CT16 -> 0
A17: 46235 | B17: RFE | C17: PART OF 233 | D17: NLZ | E17: 15.348306 | F17: 120.59311 | G17: Capas | H17: Tarlac | I17: Tarlac-NE | J17: Rowlan | K17: Q1 | L17: T-37262327I-1-NLZ-00013 | M17: IRUP0014 | N17: Capas Sub-Exchange/CO | O17: Sub-Exchange-S | P17: =IF(OR(NOT(ISNUMBER(Q17)),Q17=0),"NO DATA",IF(Q17<10,"<10 TONNES",">=10 TONNES")) -> NO DATA | Q17: 0 | R17: 9.79 | S17: =IF(CH17="CANCELLED","CANCELLED",IF(CV17<>"","EXTRACTION DONE",IF(CH17="ON GOING EXTRACTION","ON GOING EXTRACTION",IF(AR17="RFE","READY FOR EXTRACTION",IF(AR17="ON GOING PERMITTING","ON GOING PERMITTING",IF(AC17<>"","DESIGN APPROVED",IF(AB17<>"","DESIGN SUBMITTED",IF(AA17<>"","DESIGN COMPLETED",IF(Z17<>"","ON GOING DESIGN",IF(Y17<>"","ON GOING SURVEY","NOT STARTED")))))))))) -> ON GOING PERMITTING | T17: =IFERROR((AN17*33%)+(BR17*27%)+(CI17*40%),0) -> 0.357 | U17: =IF(V17>0,WEEKNUM(V17,1)&"-"&YEAR(V17),"") -> 42-2026 | V17: 46307 | W17: =V17 -> 46307 | X17: =IF(AD17>0,"DESIGN WITH CONCERN",IF(AC17>0,"DESIGN APPROVED",IF(AB17>0,"DESIGN FOR APPROVAL",IF(AA17>0,"DESIGN FOR SUBMISSION",IF(Z17>0,"ON GOING DESIGN",IF(Y17>0,"ON GOING SURVEY","FOR SURVEY")))))) -> DESIGN APPROVED | Y17: 46297 | Z17: 46298 | AA17: 46304 | AB17: 46305 | AC17: 46309 | AE17: ISP only | AF17: =IF(AA17-Y17<0,0,AA17-Y17) -> 7 | AG17: =AH17+AI17 -> 37 | AH17: 2 | AI17: 35 | AJ17: 31 | AK17: 4 | AL17: 0 | AN17: =COUNT(Y17:AC17)/5 -> 1 | AO17: =IF(AQ17>0,WEEKNUM(AQ17,1)&"-"&YEAR(AQ17),"") -> 48-2026 | AP17: 46343 | AQ17: 46353 | AR17: =IF(AA17="","WAITING FOR PLAN",IF(AU17="","PERMITTING NOT STARTED",IF(BR17>=100%,"RFE","ON GOING PERMITTING"))) -> ON GOING PERMITTING | AS17: NA | AT17: NA | AU17: 46324 | AV17: 46324 | BA17: 4 | BQ17: ON-HOLD | BR17: =IFERROR((COUNT(BD17)*40%)+(COUNT(BL17)*20%)+(COUNT(BH17)*10%)+(COUNT(BP17)*10%)+(COUNT(AV17)*10%)+(COUNT(AZ17)*10%),0) -> 0.1 | BS17: =IF(BT17>0,WEEKNUM(BT17,1)&"-"&YEAR(BT17),"") -> 47-2026 | BT17: =AP17+3 -> 46346 | BU17: =IF(BV17>0,WEEKNUM(BV17,1)&"-"&YEAR(BV17),"") -> 50-2026 | BV17: 46363 | BW17: =IF(BX17>0,WEEKNUM(BX17,1)&"-"&YEAR(BX17),"") -> 50-2026 | BX17: =IF(CA17="",BV17+CD17,CA17+CD17) -> 46366.916 | BY17: 46367 | CB17: =IF(AI17<>0,CC17*0.25,0) -> 0.5 | CC17: 2 | CD17: =IF(R17=0,IFERROR(Q17/(CC17)/1.25,0),IFERROR(R17/(CC17)/1.25,0)) -> 3.916 | CH17: =IF(CA17="","NOT STARTED",IF(CA17<>"","ON GOING EXTRACTION",IF(CV17<>"","EXTRACTION COMPLETED"))) -> NOT STARTED | CI17: =IFERROR(CQ17/CM17,0) -> 0 | CM17: =AG17 -> 37 | CN17: =AI17 -> 35 | CR17: =CM17-CQ17 -> 37 | CU17: =CS17+CT17 -> 0
A18: 46235 | B18: RFE | C18: PART OF 233 | D18: NLZ | E18: 15.925289 | F18: 120.34704 | G18: San Carlos City | H18: Pangasinan | I18: Pangasinan | J18: Rowlan | K18: Q1 | M18: IRUP0015 | N18: San Carlos | O18: Exchange-S | P18: =IF(OR(NOT(ISNUMBER(Q18)),Q18=0),"NO DATA",IF(Q18<10,"<10 TONNES",">=10 TONNES")) -> NO DATA | Q18: 0 | S18: =IF(CH18="CANCELLED","CANCELLED",IF(CV18<>"","EXTRACTION DONE",IF(CH18="ON GOING EXTRACTION","ON GOING EXTRACTION",IF(AR18="RFE","READY FOR EXTRACTION",IF(AR18="ON GOING PERMITTING","ON GOING PERMITTING",IF(AC18<>"","DESIGN APPROVED",IF(AB18<>"","DESIGN SUBMITTED",IF(AA18<>"","DESIGN COMPLETED",IF(Z18<>"","ON GOING DESIGN",IF(Y18<>"","ON GOING SURVEY","NOT STARTED")))))))))) -> ON GOING PERMITTING | T18: =IFERROR((AN18*33%)+(BR18*27%)+(CI18*40%),0) -> 0.372 | U18: =IF(V18>0,WEEKNUM(V18,1)&"-"&YEAR(V18),"") -> 42-2026 | V18: 46312 | W18: =V18 -> 46312 | X18: =IF(AD18>0,"DESIGN WITH CONCERN",IF(AC18>0,"DESIGN APPROVED",IF(AB18>0,"DESIGN FOR APPROVAL",IF(AA18>0,"DESIGN FOR SUBMISSION",IF(Z18>0,"ON GOING DESIGN",IF(Y18>0,"ON GOING SURVEY","FOR SURVEY")))))) -> DESIGN FOR APPROVAL | Y18: 46307 | Z18: 46314 | AA18: 46314 | AB18: 46322 | AE18: ISP only | AF18: =IF(AA18-Y18<0,0,AA18-Y18) -> 7 | AG18: =AH18+AI18 -> 35 | AH18: 12 | AI18: 23 | AJ18: 23 | AN18: =COUNT(Y18:AC18)/5 -> 0.8 | AO18: =IF(AQ18>0,WEEKNUM(AQ18,1)&"-"&YEAR(AQ18),"") -> 48-2026 | AP18: 46353 | AQ18: 46353 | AR18: =IF(AA18="","WAITING FOR PLAN",IF(AU18="","PERMITTING NOT STARTED",IF(BR18>=100%,"RFE","ON GOING PERMITTING"))) -> ON GOING PERMITTING | AS18: NA | AT18: NA | AU18: 46322 | AV18: 46324 | AW18: NA | AX18: NA | AY18: 46322 | AZ18: 46322 | BA18: 12 | BC18: 46322 | BE18: 1 | BG18: 46322 | BI18: 1 | BJ18: 1 | BK18: 46324 | BL18: 46324 | BR18: =IFERROR((COUNT(BD18)*40%)+(COUNT(BL18)*20%)+(COUNT(BH18)*10%)+(COUNT(BP18)*10%)+(COUNT(AV18)*10%)+(COUNT(AZ18)*10%),0) -> 0.4 | BS18: =IF(BT18>0,WEEKNUM(BT18,1)&"-"&YEAR(BT18),"") -> 49-2026 | BT18: =AP18+3 -> 46356 | BU18: =IF(BV18>0,WEEKNUM(BV18,1)&"-"&YEAR(BV18),"") -> 50-2026 | BV18: 46363 | BW18: =IF(BX18>0,WEEKNUM(BX18,1)&"-"&YEAR(BX18),"") -> 50-2026 | BX18: =IF(CA18="",BV18+CD18,CA18+CD18) -> 46363 | BY18: =IF(CA18="",BV18+CD18,CA18+CD18) -> 46363 | CB18: =IF(AI18<>0,CC18*0.25,0) -> 0.5 | CC18: 2 | CD18: =IF(R18=0,IFERROR(Q18/(CC18)/1.25,0),IFERROR(R18/(CC18)/1.25,0)) -> 0 | CH18: =IF(CA18="","NOT STARTED",IF(CA18<>"","ON GOING EXTRACTION",IF(CV18<>"","EXTRACTION COMPLETED"))) -> NOT STARTED | CI18: =IFERROR(CQ18/CM18,0) -> 0 | CM18: =AG18 -> 35 | CN18: =AI18 -> 23 | CR18: =CM18-CQ18 -> 35 | CU18: =CS18+CT18 -> 0
A19: 46235 | B19: RFE | C19: PART OF 233 | D19: NLZ | E19: 15.491379 | F19: 120.5932 | G19: Tarlac City | H19: Tarlac | I19: Tarlac-NE | J19: Rowlan | K19: Q1 | L19: T-37262327I-1-NLZ-00011 | M19: IRUP0016 | N19: Tarlac Exchange | O19: Sub-Exchange-S | P19: =IF(OR(NOT(ISNUMBER(Q19)),Q19=0),"NO DATA",IF(Q19<10,"<10 TONNES",">=10 TONNES")) -> >=10 TONNES | Q19: 38.3 | R19: 11.55 | S19: =IF(CH19="CANCELLED","CANCELLED",IF(CV19<>"","EXTRACTION DONE",IF(CH19="ON GOING EXTRACTION","ON GOING EXTRACTION",IF(AR19="RFE","READY FOR EXTRACTION",IF(AR19="ON GOING PERMITTING","ON GOING PERMITTING",IF(AC19<>"","DESIGN APPROVED",IF(AB19<>"","DESIGN SUBMITTED",IF(AA19<>"","DESIGN COMPLETED",IF(Z19<>"","ON GOING DESIGN",IF(Y19<>"","ON GOING SURVEY","NOT STARTED")))))))))) -> READY FOR EXTRACTION | T19: =IFERROR((AN19*33%)+(BR19*27%)+(CI19*40%),0) -> 0.6 | U19: =IF(V19>0,WEEKNUM(V19,1)&"-"&YEAR(V19),"") -> 40-2026 | V19: 46298 | W19: =V19 -> 46298 | X19: =IF(AD19>0,"DESIGN WITH CONCERN",IF(AC19>0,"DESIGN APPROVED",IF(AB19>0,"DESIGN FOR APPROVAL",IF(AA19>0,"DESIGN FOR SUBMISSION",IF(Z19>0,"ON GOING DESIGN",IF(Y19>0,"ON GOING SURVEY","FOR SURVEY")))))) -> DESIGN APPROVED | Y19: 46293 | Z19: 46294 | AA19: 46296 | AB19: 46297 | AC19: 46300 | AE19: Both | AF19: =IF(AA19-Y19<0,0,AA19-Y19) -> 3 | AG19: =AH19+AI19 -> 25 | AH19: 25 | AN19: =COUNT(Y19:AC19)/5 -> 1 | AO19: =IF(AQ19>0,WEEKNUM(AQ19,1)&"-"&YEAR(AQ19),"") -> 46-2026 | AP19: 46334 | AQ19: 46334 | AR19: =IF(AA19="","WAITING FOR PLAN",IF(AU19="","PERMITTING NOT STARTED",IF(BR19>=100%,"RFE","ON GOING PERMITTING"))) -> RFE | AS19: NA | AT19: NA | AU19: 46316 | AV19: 46316 | AW19: NA | AX19: NA | AY19: 46316 | AZ19: 46316 | BA19: 7 | BB19: 7 | BC19: 46301 | BD19: 46318 | BE19: 1 | BF19: 1 | BG19: 46315 | BH19: 46318 | BI19: 1 | BJ19: 1 | BK19: 46301 | BL19: 46301 | BM19: 1 | BN19: 1 | BO19: 46301 | BP19: 46301 | BQ19: 19-Oct-26 Tarlac City Hall Activity: Follow up order of payment Activity Output: order of payment havent made yet. and to be finalize tomorrow.City engineer advice me to return tomorrow 10am for the Order of payment Engr Allan Paras (0956) 642 1262 13-Oct-26 Tarlac City Hall Activity: Site Inspection Activity Output: Done site inspection. as per Engr Allan he will write an report on thursday for the reason that he is on leave tomorrow because of his birthday. he also mentioned that its posible to have an update on Monday regarding on the municipal permit. 8-Oct-26 (Bgry San Vicente Number of Manholes: 8 San Vicente - MH 015, TRC _MH 001, TRC_MH 002, TRC_MH 003, TRC_MH 004, TRC_MH 006, TRC_MH 008, TRC_MH 009 Activity: Brgy Clearance/Permit Payment Activity Output: Permit secured valid until the end of our mobilization BRGY 5/7 LGU 0/1) --- (Brgy San Nicolas Number of Manholes: 6 San Nicolas - MH 011, MH 010, TRC_MH 010, TRC_MH 011, TRC_MH 012, TRC_MH 013 Activity: Follow up brgy permit/clearance application Activity Output: as per Brgy Secretary. Brgy Captain were not around and have some ongoing activity/seminar. she didnt mention if the brgy captain will be back on the barangay hall. i advice her that if ever the brgy captain arrived, she can msg me for the SOA so that i can request the budget Brgy 4/7 LGU 0/1) ---- Brgy Poblacion Number of Manhole: 1 Brgy Poblacion MH001 Activity: Brgy Permit/Clearance Payment Activity Output: Permit Secured with AR BRGY 3/7 LGU 0/1 ----- 7-Oct-26 (Bgry Santo Cristo Activity: Brgy Clearance/Permit Application Activity Output: Plan and LOI Recieved by Mam Marinel Vitermo SOA Secured for the 6 manholes. a payment of 1,000 AR for the validity of 1yr) --- (Bgry San Nicolas Activity: Brgy Clearance/Permit Application Activity Output: Plan and LOI were recieved by Mam Anne Baylon (barangay Secretary) and to be forwarded to the Barangay Captain as per Mam Anne, Brgy Captain were currently not around. she will message me regarding to the SOA later. upon payment Barangay San Nicolas will issue an OR) ---- ( Brgy Poblacion Number of manhole: 1 (MH001) Activity: Brgy Permit/Clearance Application Activity Output: Plan and LOI received by Kagawad Byron. SOA Secured. the Amount for the Permit/Clearance is 1,000 AR) ---- Bgry San Roque Activity: Brgy Clearance/Permit Application Activity Output: Brgy Clearance/Permit Secured with no amount to pay -Brgy Clearance/Permit validity is good for 6 months ---- 6-Oct-26 (Brgy Ligtasan Activity: Brgy Permit/Clearance Application for the Manholes: MH016, MH050 Activity Output: Plan and LoI received by Brgy Secretary Brgy Permit/Clearance Secured with no Amount to Pay) ----- Brgy San Vicente Activity: Brgy Permit/Clearance Application for the following Manholes San Vicente - MH 015, TRC _MH 001, TRC_MH 002, TRC_MH 003, TRC_MH 004, TRC_MH 006, TRC_MH 008, TRC_MH 009 Activity Output: Plan and LOI submitted and received by Mam Lourdes Manakil. As per Mam Lourdes M Manakil, Brgy Chairman is currently not around. she advice me to return after lunch for the posiblity to get the SOA | BR19: =IFERROR((COUNT(BD19)*40%)+(COUNT(BL19)*20%)+(COUNT(BH19)*10%)+(COUNT(BP19)*10%)+(COUNT(AV19)*10%)+(COUNT(AZ19)*10%),0) -> 1 | BS19: =IF(BT19>0,WEEKNUM(BT19,1)&"-"&YEAR(BT19),"") -> 46-2026 | BT19: =AP19+3 -> 46337 | BU19: =IF(BV19>0,WEEKNUM(BV19,1)&"-"&YEAR(BV19),"") -> 46-2026 | BV19: 46335 | BW19: =IF(BX19>0,WEEKNUM(BX19,1)&"-"&YEAR(BX19),"") -> 46-2026 | BX19: =IF(CA19="",BV19+CD19,CA19+CD19) -> 46339.62 | BY19: 46342 | BZ19: 10/29/26: DD: 11/9 | CB19: =IF(AI19<>0,CC19*0.25,0) -> 0 | CC19: 2 | CD19: =IF(R19=0,IFERROR(Q19/(CC19)/1.25,0),IFERROR(R19/(CC19)/1.25,0)) -> 4.62 | CE19: ELECTRUMLINES | CH19: =IF(CA19="","NOT STARTED",IF(CA19<>"","ON GOING EXTRACTION",IF(CV19<>"","EXTRACTION COMPLETED"))) -> NOT STARTED | CI19: =IFERROR(CQ19/CM19,0) -> 0 | CM19: =AG19 -> 25 | CN19: =AI19 -> 0 | CR19: =CM19-CQ19 -> 25 | CU19: =CS19+CT19 -> 0
A20: 46235 | B20: RFE | C20: PART OF 233 | D20: NLZ | E20: 15.006995 | F20: 120.08463 | G20: San Narciso | H20: Zambales | I20: PamBatZam | J20: Limwell | K20: Q1 | L20: T-37262327I-1-NLZ-00009 | M20: IRUP0017 | N20: San Narciso Sub-Exchange | O20: Sub-Exchange-S | P20: =IF(OR(NOT(ISNUMBER(Q20)),Q20=0),"NO DATA",IF(Q20<10,"<10 TONNES",">=10 TONNES")) -> >=10 TONNES | Q20: 31.5 | R20: 0.25 | S20: =IF(CH20="CANCELLED","CANCELLED",IF(CV20<>"","EXTRACTION DONE",IF(CH20="ON GOING EXTRACTION","ON GOING EXTRACTION",IF(AR20="RFE","READY FOR EXTRACTION",IF(AR20="ON GOING PERMITTING","ON GOING PERMITTING",IF(AC20<>"","DESIGN APPROVED",IF(AB20<>"","DESIGN SUBMITTED",IF(AA20<>"","DESIGN COMPLETED",IF(Z20<>"","ON GOING DESIGN",IF(Y20<>"","ON GOING SURVEY","NOT STARTED")))))))))) -> READY FOR EXTRACTION | T20: =IFERROR((AN20*33%)+(BR20*27%)+(CI20*40%),0) -> 0.6 | U20: =IF(V20>0,WEEKNUM(V20,1)&"-"&YEAR(V20),"") -> 41-2026 | V20: 46299 | W20: =V20 -> 46299 | X20: =IF(AD20>0,"DESIGN WITH CONCERN",IF(AC20>0,"DESIGN APPROVED",IF(AB20>0,"DESIGN FOR APPROVAL",IF(AA20>0,"DESIGN FOR SUBMISSION",IF(Z20>0,"ON GOING DESIGN",IF(Y20>0,"ON GOING SURVEY","FOR SURVEY")))))) -> DESIGN APPROVED | Y20: 46300 | Z20: 46301 | AA20: 46301 | AB20: 46303 | AC20: 46309 | AE20: Both | AF20: =IF(AA20-Y20<0,0,AA20-Y20) -> 1 | AG20: =AH20+AI20 -> 1 | AH20: 1 | AI20: 0 | AJ20: 0 | AK20: 1 | AL20: 0 | AN20: =COUNT(Y20:AC20)/5 -> 1 | AO20: =IF(AQ20>0,WEEKNUM(AQ20,1)&"-"&YEAR(AQ20),"") -> 46-2026 | AP20: 46335 | AQ20: 46335 | AR20: =IF(AA20="","WAITING FOR PLAN",IF(AU20="","PERMITTING NOT STARTED",IF(BR20>=100%,"RFE","ON GOING PERMITTING"))) -> RFE | AS20: NA | AT20: NA | AU20: 46316 | AV20: 46316 | AW20: NA | AX20: NA | AY20: 46316 | AZ20: 46316 | BA20: 1 | BB20: 1 | BC20: 46308 | BD20: 46310 | BE20: 1 | BF20: 1 | BG20: 46308 | BH20: 46308 | BI20: 1 | BJ20: 1 | BK20: 46311 | BL20: 46311 | BM20: 1 | BN20: 1 | BO20: 46311 | BP20: 46311 | BQ20: 13-Oct-26 RFE Sites Cluster 1 of San Narciso sub exchange Location: Zambales Grantor: Brgy Patrocinio MH#: MH001 Activity: submision of LOI and Plan Activity output:As per Kap. Edwin, regarding the certification/permit , please go back to him only when the implementation is about to start. The permit fee is ₱120. Note: Approved for implementation , just get the permit on the day you deploy. | BR20: =IFERROR((COUNT(BD20)*40%)+(COUNT(BL20)*20%)+(COUNT(BH20)*10%)+(COUNT(BP20)*10%)+(COUNT(AV20)*10%)+(COUNT(AZ20)*10%),0) -> 1 | BS20: =IF(BT20>0,WEEKNUM(BT20,1)&"-"&YEAR(BT20),"") -> 46-2026 | BT20: =AP20+3 -> 46338 | BU20: =IF(BV20>0,WEEKNUM(BV20,1)&"-"&YEAR(BV20),"") -> 45-2026 | BV20: 46329 | BW20: =IF(BX20>0,WEEKNUM(BX20,1)&"-"&YEAR(BX20),"") -> 45-2026 | BX20: =IF(CA20="",BV20+CD20,CA20+CD20) -> 46329.1 | BY20: 46329 | BZ20: 10/29/26: DD: 11/3 | CB20: =IF(AI20<>0,CC20*0.25,0) -> 0 | CC20: 2 | CD20: =IF(R20=0,IFERROR(Q20/(CC20)/1.25,0),IFERROR(R20/(CC20)/1.25,0)) -> 0.1 | CE20: ELECTRUMLINES | CF20: BOTH | CH20: =IF(CA20="","NOT STARTED",IF(CA20<>"","ON GOING EXTRACTION",IF(CV20<>"","EXTRACTION COMPLETED"))) -> NOT STARTED | CI20: =IFERROR(CQ20/CM20,0) -> 0 | CM20: =AG20 -> 1 | CN20: =AI20 -> 0 | CR20: =CM20-CQ20 -> 1 | CU20: =CS20+CT20 -> 0
A21: 46235 | B21: RFE | C21: PART OF 233 | D21: NLZ | E21: 14.626994 | F21: 120.57542 | G21: Orion | H21: Bataan | I21: PamBatZam | J21: Limwell | K21: Q1 | L21: T-37262327I-1-NLZ-00002 | M21: IRUP0018 | N21: Orion Sub-Exchange | O21: Sub-Exchange-S | P21: =IF(OR(NOT(ISNUMBER(Q21)),Q21=0),"NO DATA",IF(Q21<10,"<10 TONNES",">=10 TONNES")) -> >=10 TONNES | Q21: 31.5 | R21: 9.17 | S21: =IF(CH21="CANCELLED","CANCELLED",IF(CV21<>"","EXTRACTION DONE",IF(CH21="ON GOING EXTRACTION","ON GOING EXTRACTION",IF(AR21="RFE","READY FOR EXTRACTION",IF(AR21="ON GOING PERMITTING","ON GOING PERMITTING",IF(AC21<>"","DESIGN APPROVED",IF(AB21<>"","DESIGN SUBMITTED",IF(AA21<>"","DESIGN COMPLETED",IF(Z21<>"","ON GOING DESIGN",IF(Y21<>"","ON GOING SURVEY","NOT STARTED")))))))))) -> READY FOR EXTRACTION | T21: =IFERROR((AN21*33%)+(BR21*27%)+(CI21*40%),0) -> 0.6 | U21: =IF(V21>0,WEEKNUM(V21,1)&"-"&YEAR(V21),"") -> 41-2026 | V21: 46300 | W21: =V21 -> 46300 | X21: =IF(AD21>0,"DESIGN WITH CONCERN",IF(AC21>0,"DESIGN APPROVED",IF(AB21>0,"DESIGN FOR APPROVAL",IF(AA21>0,"DESIGN FOR SUBMISSION",IF(Z21>0,"ON GOING DESIGN",IF(Y21>0,"ON GOING SURVEY","FOR SURVEY")))))) -> DESIGN APPROVED | Y21: 46292 | Z21: 46293 | AA21: 46296 | AB21: 46300 | AC21: 46302 | AE21: Both | AF21: =IF(AA21-Y21<0,0,AA21-Y21) -> 4 | AG21: =AH21+AI21 -> 6 | AH21: 6 | AI21: 0 | AJ21: 0 | AK21: 0 | AL21: 0 | AN21: =COUNT(Y21:AC21)/5 -> 1 | AO21: =IF(AQ21>0,WEEKNUM(AQ21,1)&"-"&YEAR(AQ21),"") -> 46-2026 | AP21: 46336 | AQ21: 46336 | AR21: =IF(AA21="","WAITING FOR PLAN",IF(AU21="","PERMITTING NOT STARTED",IF(BR21>=100%,"RFE","ON GOING PERMITTING"))) -> RFE | AS21: NA | AT21: NA | AU21: 46316 | AV21: 46316 | AW21: NA | AX21: NA | AY21: 46316 | AZ21: 46316 | BA21: 3 | BB21: 3 | BC21: 46301 | BD21: 46303 | BE21: 1 | BF21: 1 | BG21: 46302 | BH21: 46302 | BI21: 1 | BJ21: 1 | BK21: 46302 | BL21: 46302 | BM21: 1 | BN21: 1 | BO21: 46302 | BP21: 46302 | BQ21: 8-Oct-26 - RFE Sites 7-Oct-26 LGU of Orion Activity: Brgy Permit/Clearance Application for the following Manholes LGU of Orion - MH001, MH002, MH003, MH004, MH005, MH006 Activity Output: Plan and LOI submitted as per engr. Adrian R. Agustin we dont need a dpwh permit , just comply the necessary requirements for to secure rhe lgu permit. The permit cost 1440 pesos ----- 6-Oct-26 Brgy Arellano Activity: Brgy Permit/Clearance Application for the following Manholes San Vicente - MH006 Activity Output: Plan and LOI submitted and received by Mam Lourdes Manakil. -LOI and plan recieved by kap. Eva Manansala, the permit fee is 500 pesos(OR) | BR21: =IFERROR((COUNT(BD21)*40%)+(COUNT(BL21)*20%)+(COUNT(BH21)*10%)+(COUNT(BP21)*10%)+(COUNT(AV21)*10%)+(COUNT(AZ21)*10%),0) -> 1 | BS21: =IF(BT21>0,WEEKNUM(BT21,1)&"-"&YEAR(BT21),"") -> 46-2026 | BT21: =AP21+3 -> 46339 | BU21: =IF(BV21>0,WEEKNUM(BV21,1)&"-"&YEAR(BV21),"") -> 45-2026 | BV21: 46331 | BW21: =IF(BX21>0,WEEKNUM(BX21,1)&"-"&YEAR(BX21),"") -> 46-2026 | BX21: =IF(CA21="",BV21+CD21,CA21+CD21) -> 46334.668 | BY21: 46337 | BZ21: 10/29/26: DD: 11/5 | CB21: =IF(AI21<>0,CC21*0.25,0) -> 0 | CC21: 2 | CD21: =IF(R21=0,IFERROR(Q21/(CC21)/1.25,0),IFERROR(R21/(CC21)/1.25,0)) -> 3.668 | CE21: ELECTRUMLINES | CF21: BOTH | CG21: Richard, Ronnel | CH21: =IF(CA21="","NOT STARTED",IF(CA21<>"","ON GOING EXTRACTION",IF(CV21<>"","EXTRACTION COMPLETED"))) -> NOT STARTED | CI21: =IFERROR(CQ21/CM21,0) -> 0 | CM21: =AG21 -> 6 | CN21: =AI21 -> 0 | CR21: =CM21-CQ21 -> 6 | CU21: =CS21+CT21 -> 0
A22: 46235 | B22: RFE | C22: PART OF 233 | D22: NLZ | E22: 14.959237 | F22: 120.16963 | G22: San Marcelino | H22: Zambales | I22: PamBatZam | J22: Limwell | K22: Q1 | L22: T-37262327I-1-NLZ-00010 | M22: IRUP0019 | N22: San Marcelino Sub-Exchange | O22: Sub-Exchange-S | P22: =IF(OR(NOT(ISNUMBER(Q22)),Q22=0),"NO DATA",IF(Q22<10,"<10 TONNES",">=10 TONNES")) -> >=10 TONNES | Q22: 31.5 | R22: 0.31 | S22: =IF(CH22="CANCELLED","CANCELLED",IF(CV22<>"","EXTRACTION DONE",IF(CH22="ON GOING EXTRACTION","ON GOING EXTRACTION",IF(AR22="RFE","READY FOR EXTRACTION",IF(AR22="ON GOING PERMITTING","ON GOING PERMITTING",IF(AC22<>"","DESIGN APPROVED",IF(AB22<>"","DESIGN SUBMITTED",IF(AA22<>"","DESIGN COMPLETED",IF(Z22<>"","ON GOING DESIGN",IF(Y22<>"","ON GOING SURVEY","NOT STARTED")))))))))) -> READY FOR EXTRACTION | T22: =IFERROR((AN22*33%)+(BR22*27%)+(CI22*40%),0) -> 0.6 | U22: =IF(V22>0,WEEKNUM(V22,1)&"-"&YEAR(V22),"") -> 41-2026 | V22: 46299 | W22: =V22 -> 46299 | X22: =IF(AD22>0,"DESIGN WITH CONCERN",IF(AC22>0,"DESIGN APPROVED",IF(AB22>0,"DESIGN FOR APPROVAL",IF(AA22>0,"DESIGN FOR SUBMISSION",IF(Z22>0,"ON GOING DESIGN",IF(Y22>0,"ON GOING SURVEY","FOR SURVEY")))))) -> DESIGN APPROVED | Y22: 46300 | Z22: 46301 | AA22: 46303 | AB22: 46303 | AC22: 46309 | AE22: Both | AF22: =IF(AA22-Y22<0,0,AA22-Y22) -> 3 | AG22: =AH22+AI22 -> 1 | AH22: 1 | AI22: 0 | AJ22: 0 | AK22: 0 | AL22: 0 | AN22: =COUNT(Y22:AC22)/5 -> 1 | AO22: =IF(AQ22>0,WEEKNUM(AQ22,1)&"-"&YEAR(AQ22),"") -> 46-2026 | AP22: 46335 | AQ22: 46335 | AR22: =IF(AA22="","WAITING FOR PLAN",IF(AU22="","PERMITTING NOT STARTED",IF(BR22>=100%,"RFE","ON GOING PERMITTING"))) -> RFE | AS22: NA | AT22: NA | AU22: 46316 | AV22: 46316 | AW22: NA | AX22: NA | AY22: 46316 | AZ22: 46316 | BA22: 1 | BB22: 1 | BC22: 46308 | BD22: 46308 | BE22: 1 | BF22: 1 | BG22: 46311 | BH22: 46311 | BI22: 1 | BJ22: 1 | BK22: 46311 | BL22: 46311 | BM22: 1 | BN22: 1 | BO22: 46311 | BP22: 46311 | BQ22: 13-Oct-26 (Secured Permit) Cluster 1 of San Marcelino sub exchange Location: Zambales Grantor: Brgy Nagbunga MH#: MH001 Activity: submision of LOI and Plan Activity output: documents submitted /500 for the permit | BR22: =IFERROR((COUNT(BD22)*40%)+(COUNT(BL22)*20%)+(COUNT(BH22)*10%)+(COUNT(BP22)*10%)+(COUNT(AV22)*10%)+(COUNT(AZ22)*10%),0) -> 1 | BS22: =IF(BT22>0,WEEKNUM(BT22,1)&"-"&YEAR(BT22),"") -> 46-2026 | BT22: =AP22+3 -> 46338 | BU22: =IF(BV22>0,WEEKNUM(BV22,1)&"-"&YEAR(BV22),"") -> 45-2026 | BV22: 46329 | BW22: =IF(BX22>0,WEEKNUM(BX22,1)&"-"&YEAR(BX22),"") -> 45-2026 | BX22: =IF(CA22="",BV22+CD22,CA22+CD22) -> 46329.124 | BY22: 46329 | BZ22: 10/29/26: DD: 11/3 | CB22: =IF(AI22<>0,CC22*0.25,0) -> 0 | CC22: 2 | CD22: =IF(R22=0,IFERROR(Q22/(CC22)/1.25,0),IFERROR(R22/(CC22)/1.25,0)) -> 0.124 | CE22: ELECTRUMLINES | CF22: BOTH | CH22: =IF(CA22="","NOT STARTED",IF(CA22<>"","ON GOING EXTRACTION",IF(CV22<>"","EXTRACTION COMPLETED"))) -> NOT STARTED | CI22: =IFERROR(CQ22/CM22,0) -> 0 | CM22: =AG22 -> 1 | CN22: =AI22 -> 0 | CR22: =CM22-CQ22 -> 1 | CU22: =CS22+CT22 -> 0
A23: 46235 | B23: RFE | C23: PART OF 233 | D23: NLZ | E23: 15.686392 | F23: 120.40967 | G23: Camiling | H23: Tarlac | I23: Tarlac-NE | J23: Rowlan | K23: Q1 | L23: T-37262327I-1-NLZ-00012 | M23: IRUP0020 | N23: Camiling Sub-Exchange | O23: Sub-Exchange-S | P23: =IF(OR(NOT(ISNUMBER(Q23)),Q23=0),"NO DATA",IF(Q23<10,"<10 TONNES",">=10 TONNES")) -> >=10 TONNES | Q23: 13.4 | R23: 3.94 | S23: =IF(CH23="CANCELLED","CANCELLED",IF(CV23<>"","EXTRACTION DONE",IF(CH23="ON GOING EXTRACTION","ON GOING EXTRACTION",IF(AR23="RFE","READY FOR EXTRACTION",IF(AR23="ON GOING PERMITTING","ON GOING PERMITTING",IF(AC23<>"","DESIGN APPROVED",IF(AB23<>"","DESIGN SUBMITTED",IF(AA23<>"","DESIGN COMPLETED",IF(Z23<>"","ON GOING DESIGN",IF(Y23<>"","ON GOING SURVEY","NOT STARTED")))))))))) -> ON GOING PERMITTING | T23: =IFERROR((AN23*33%)+(BR23*27%)+(CI23*40%),0) -> 0.438 | U23: =IF(V23>0,WEEKNUM(V23,1)&"-"&YEAR(V23),"") -> 41-2026 | V23: 46301 | W23: =V23 -> 46301 | X23: =IF(AD23>0,"DESIGN WITH CONCERN",IF(AC23>0,"DESIGN APPROVED",IF(AB23>0,"DESIGN FOR APPROVAL",IF(AA23>0,"DESIGN FOR SUBMISSION",IF(Z23>0,"ON GOING DESIGN",IF(Y23>0,"ON GOING SURVEY","FOR SURVEY")))))) -> DESIGN APPROVED | Y23: 46297 | Z23: 46298 | AA23: 46301 | AB23: 46301 | AC23: 46302 | AE23: ISP only | AF23: =IF(AA23-Y23<0,0,AA23-Y23) -> 4 | AG23: =AH23+AI23 -> 35 | AH23: 10 | AI23: 25 | AJ23: 0 | AK23: 25 | AL23: 0 | AN23: =COUNT(Y23:AC23)/5 -> 1 | AO23: =IF(AQ23>0,WEEKNUM(AQ23,1)&"-"&YEAR(AQ23),"") -> 46-2026 | AP23: 46337 | AQ23: 46337 | AR23: =IF(AA23="","WAITING FOR PLAN",IF(AU23="","PERMITTING NOT STARTED",IF(BR23>=100%,"RFE","ON GOING PERMITTING"))) -> ON GOING PERMITTING | AS23: NA | AT23: NA | AU23: 46316 | AV23: 46316 | AW23: NA | AX23: NA | AY23: 46316 | AZ23: 46316 | BA23: 8 | BB23: 6 | BC23: 46310 | BI23: 1 | BJ23: 1 | BK23: 46324 | BL23: 46324 | BQ23: Oct 23 Brgy Sawat Activity: Follow up application Activity Output: no personel on duty in brgy hall, i have tried to call the brgy Secretary but he didnt answer my call to follow up next week BRGY 1/13 DPWH 0/1 LGU- Oct 23: BRGY:Poblacio A Activity: Follow up application for order of payment Activity Output: as per Kagawad Aquino he havent talk to brgy Capt yet. i leave my phone number incase theres an update regarding to the amount of brgy Permit/Clearance BRGY 1/13 DPWH 0/1 OCT 23Brgy Surgui 3rd Activity: Follow up application for order of payment Activity Output: Brgy Permit/Clearance Fee: 500 OR BRGY 1/13 LGU- DPWH 0/1 Contact Person: Brgy Kagawad Castro (0956) 246 8801 Oct 23 Brgy Tuec Number of Manholes: 2 all not Accessible Activity: Brgy/Permit Clearance Application Activity Output: Plan and LOI submitted and received by Brgy Captain Bernardo Pagarigan. Brgy Permit/Clearance Fee: 500 OR BRGY 1/13 LGU DPWH -01/ Contact Person: Bernardo Pagarigan Brgy Captain 0931 902 4573 OCT 23 Brgy Malacampa Activity: Follow up application for Order of payment Activitt Output: As per the brgy treasurer brgy captain have some urgent meeting this morning. she will endorse the cp number that i leave so that i can talk to brgy thru phone. 0CT 22 Cluster 1 of Camiling Sub-Exchange Brgy Malacampa Activity: Follow up application for Order of payment Activitt Output: As per the brgy treasurer brgy captain have some urgent meeting this morning. she will endorse the cp number that i leave so that i can talk to brgy thru phone. Grantor: Poblacion J Number of Manhole : 1 Accessible Poblacion J - MH001 Activity: Brgy Permit/Clearance Application Activity Output: Plan and LOI received by Brgy Captain Michael M. Antonio Permit/Clearance Fee: 100 OR Brgy 1/13 LGU- DPWH - 0/1 Contact Person: Michael M Antonio Brgy Captain 09099943795 OCT 22 Cluster 1 of Camiling Sub-exchange Grantor: Camiling Municipal Hall Engineering office Activity: Inquiry of requirements for municipal permit Activity Output: i have spoke to ENGR. GEAN CARLO P. ZACARIAS (ENGINEER II) thru phone and ask about the requirements in order for us to get municipal permit. as per Engr Gean Carlo Zacarias, theres no need for permit in municipal, he just advice me to submit the brgy clearances and DPWH permit to the Engineerings Office before we start implementing our project BRGY 1/13 LGU - DPWH 0/1 Contact Person Jp Madriaga Admin Aide OCT 22 Poblacion A Activity: Brgy Permit/Clearance Application Activity Output: Plan and LOI received by Kag. Reynaldo Aquino Plan and LOI is for review by the Brgy Captain To follow up tomorrow Brgy 1/13 LGU 0/1 DPWH OCT 22-Grantor:. Poblacion G Activity: Brgy Permit/Clearance Application Activity Output: Plan and LOI received by Brgy Captain Marlon B. Mangino As per him we need to verify first the location of Manhole under Poblacion G jurisdiction. he note also that if we will restore the cement/asphalt make sure that it will restore strong/properly. Brgy Permit Fee is 500 OR Brgy 1/13 LGU 0/1 DPWH Contact Person Marlon B Mangino Brgy Captain 09778117070 15-Oct-26 Brgy Bilad Number of Manhole: 6. 2 accessible and 4 not Accessible Bilad - CML_MH003, CML_MH006, CML_MH007, CML_MH008, CML_MH010, CML_MH005 Activity: Brgy Permit/Clearance Application Activity Output: Amount of 1,500 for the permit vaild until the end of our Mobilization | BR23: =IFERROR((COUNT(BD23)*40%)+(COUNT(BL23)*20%)+(COUNT(BH23)*10%)+(COUNT(BP23)*10%)+(COUNT(AV23)*10%)+(COUNT(AZ23)*10%),0) -> 0.4 | BS23: =IF(BT23>0,WEEKNUM(BT23,1)&"-"&YEAR(BT23),"") -> 46-2026 | BT23: =AP23+3 -> 46340 | BU23: =IF(BV23>0,WEEKNUM(BV23,1)&"-"&YEAR(BV23),"") -> 47-2026 | BV23: 46346 | BW23: =IF(BX23>0,WEEKNUM(BX23,1)&"-"&YEAR(BX23),"") -> 47-2026 | BX23: =IF(CA23="",BV23+CD23,CA23+CD23) -> 46347.576 | BY23: =IF(CA23="",BV23+CD23,CA23+CD23) -> 46347.576 | CB23: =IF(AI23<>0,CC23*0.25,0) -> 0.5 | CC23: 2 | CD23: =IF(R23=0,IFERROR(Q23/(CC23)/1.25,0),IFERROR(R23/(CC23)/1.25,0)) -> 1.576 | CH23: =IF(CA23="","NOT STARTED",IF(CA23<>"","ON GOING EXTRACTION",IF(CV23<>"","EXTRACTION COMPLETED"))) -> NOT STARTED | CI23: =IFERROR(CQ23/CM23,0) -> 0 | CM23: =AG23 -> 35 | CN23: =AI23 -> 25 | CR23: =CM23-CQ23 -> 35 | CU23: =CS23+CT23 -> 0
A24: 46235 | B24: RFE | C24: PART OF 233 | D24: NLZ | E24: 15.671202 | F24: 120.58139 | G24: Paniqui | H24: Tarlac | I24: Tarlac-NE | J24: Rowlan | K24: Q1 | L24: T-37262327I-1-NLZ-00014 | M24: IRUP0021 | N24: Paniqui Sub-Exchange | O24: Sub-Exchange-S | P24: =IF(OR(NOT(ISNUMBER(Q24)),Q24=0),"NO DATA",IF(Q24<10,"<10 TONNES",">=10 TONNES")) -> >=10 TONNES | Q24: 10.6 | R24: 3.38 | S24: =IF(CH24="CANCELLED","CANCELLED",IF(CV24<>"","EXTRACTION DONE",IF(CH24="ON GOING EXTRACTION","ON GOING EXTRACTION",IF(AR24="RFE","READY FOR EXTRACTION",IF(AR24="ON GOING PERMITTING","ON GOING PERMITTING",IF(AC24<>"","DESIGN APPROVED",IF(AB24<>"","DESIGN SUBMITTED",IF(AA24<>"","DESIGN COMPLETED",IF(Z24<>"","ON GOING DESIGN",IF(Y24<>"","ON GOING SURVEY","NOT STARTED")))))))))) -> ON GOING PERMITTING | T24: =IFERROR((AN24*33%)+(BR24*27%)+(CI24*40%),0) -> 0.438 | U24: =IF(V24>0,WEEKNUM(V24,1)&"-"&YEAR(V24),"") -> 40-2026 | V24: 46297 | W24: =V24 -> 46297 | X24: =IF(AD24>0,"DESIGN WITH CONCERN",IF(AC24>0,"DESIGN APPROVED",IF(AB24>0,"DESIGN FOR APPROVAL",IF(AA24>0,"DESIGN FOR SUBMISSION",IF(Z24>0,"ON GOING DESIGN",IF(Y24>0,"ON GOING SURVEY","FOR SURVEY")))))) -> DESIGN APPROVED | Y24: 46297 | Z24: 46302 | AA24: 46302 | AB24: 46303 | AC24: 46309 | AE24: Both | AF24: =IF(AA24-Y24<0,0,AA24-Y24) -> 5 | AG24: =AH24+AI24 -> 10 | AH24: 2 | AI24: 8 | AJ24: 0 | AK24: 8 | AL24: 0 | AN24: =COUNT(Y24:AC24)/5 -> 1 | AO24: =IF(AQ24>0,WEEKNUM(AQ24,1)&"-"&YEAR(AQ24),"") -> 45-2026 | AP24: 46333 | AQ24: 46333 | AR24: =IF(AA24="","WAITING FOR PLAN",IF(AU24="","PERMITTING NOT STARTED",IF(BR24>=100%,"RFE","ON GOING PERMITTING"))) -> ON GOING PERMITTING | AS24: NA | AT24: NA | AU24: 46316 | AV24: 46316 | AW24: NA | AX24: NA | AY24: 46316 | AZ24: 46316 | BA24: 1 | BB24: 1 | BC24: 46309 | BE24: 1 | BG24: 46310 | BI24: 1 | BJ24: 1 | BK24: 46324 | BL24: 46324 | BQ24: 14-Oct-26 Brgy Poblacion Norte Number of Manholes: 4-not Accessible. 2-Accessible Poblacion Norte - PB_001, PQI_MH008, PQI_MH007, PQI_MH003, PQI_MH001, PQI_MH009 Activity: Submission of Plan and LOI for Brgy Permit/Clearance Application Activity Output: Brgy Permit/Clearance Secured amounting 130 valid until end of our mobilization BRGY 1/2 | BR24: =IFERROR((COUNT(BD24)*40%)+(COUNT(BL24)*20%)+(COUNT(BH24)*10%)+(COUNT(BP24)*10%)+(COUNT(AV24)*10%)+(COUNT(AZ24)*10%),0) -> 0.4 | BS24: =IF(BT24>0,WEEKNUM(BT24,1)&"-"&YEAR(BT24),"") -> 46-2026 | BT24: =AP24+3 -> 46336 | BU24: =IF(BV24>0,WEEKNUM(BV24,1)&"-"&YEAR(BV24),"") -> 47-2026 | BV24: 46344 | BW24: =IF(BX24>0,WEEKNUM(BX24,1)&"-"&YEAR(BX24),"") -> 47-2026 | BX24: =IF(CA24="",BV24+CD24,CA24+CD24) -> 46345.352 | BY24: =IF(CA24="",BV24+CD24,CA24+CD24) -> 46345.352 | CB24: =IF(AI24<>0,CC24*0.25,0) -> 0.5 | CC24: 2 | CD24: =IF(R24=0,IFERROR(Q24/(CC24)/1.25,0),IFERROR(R24/(CC24)/1.25,0)) -> 1.352 | CH24: =IF(CA24="","NOT STARTED",IF(CA24<>"","ON GOING EXTRACTION",IF(CV24<>"","EXTRACTION COMPLETED"))) -> NOT STARTED | CI24: =IFERROR(CQ24/CM24,0) -> 0 | CM24: =AG24 -> 10 | CN24: =AI24 -> 8 | CR24: =CM24-CQ24 -> 10 | CU24: =CS24+CT24 -> 0
A25: 46235 | B25: RFE | C25: PART OF 233 | D25: NLZ | E25: 16.046343 | F25: 120.33908 | G25: Dagupan City | H25: Pangasinan | I25: Pangasinan | J25: Rowlan | K25: Q1 | L25: T-37262327I-1-NLZ-00006 | M25: IRUP0022 | N25: Dagupan Exchange | O25: Exchange-M | P25: =IF(OR(NOT(ISNUMBER(Q25)),Q25=0),"NO DATA",IF(Q25<10,"<10 TONNES",">=10 TONNES")) -> >=10 TONNES | Q25: 107.6 | R25: 33.62 | S25: =IF(CH25="CANCELLED","CANCELLED",IF(CV25<>"","EXTRACTION DONE",IF(CH25="ON GOING EXTRACTION","ON GOING EXTRACTION",IF(AR25="RFE","READY FOR EXTRACTION",IF(AR25="ON GOING PERMITTING","ON GOING PERMITTING",IF(AC25<>"","DESIGN APPROVED",IF(AB25<>"","DESIGN SUBMITTED",IF(AA25<>"","DESIGN COMPLETED",IF(Z25<>"","ON GOING DESIGN",IF(Y25<>"","ON GOING SURVEY","NOT STARTED")))))))))) -> ON GOING PERMITTING | T25: =IFERROR((AN25*33%)+(BR25*27%)+(CI25*40%),0) -> 0.546 | U25: =IF(V25>0,WEEKNUM(V25,1)&"-"&YEAR(V25),"") -> 41-2026 | V25: 46301 | W25: =V25 -> 46301 | X25: =IF(AD25>0,"DESIGN WITH CONCERN",IF(AC25>0,"DESIGN APPROVED",IF(AB25>0,"DESIGN FOR APPROVAL",IF(AA25>0,"DESIGN FOR SUBMISSION",IF(Z25>0,"ON GOING DESIGN",IF(Y25>0,"ON GOING SURVEY","FOR SURVEY")))))) -> DESIGN APPROVED | Y25: 46295 | Z25: 46297 | AA25: 46302 | AB25: 46303 | AC25: 46316 | AE25: Both | AF25: =IF(AA25-Y25<0,0,AA25-Y25) -> 7 | AG25: =AH25+AI25 -> 42 | AH25: 33 | AI25: 9 | AJ25: 7 | AK25: 2 | AL25: 0 | AN25: =COUNT(Y25:AC25)/5 -> 1 | AO25: =IF(AQ25>0,WEEKNUM(AQ25,1)&"-"&YEAR(AQ25),"") -> 47-2026 | AP25: 46343 | AQ25: 46346 | AR25: =IF(AA25="","WAITING FOR PLAN",IF(AU25="","PERMITTING NOT STARTED",IF(BR25>=100%,"RFE","ON GOING PERMITTING"))) -> ON GOING PERMITTING | AS25: NA | AT25: NA | AU25: 46316 | AV25: 46316 | AW25: NA | AX25: NA | AY25: 46316 | AZ25: 46316 | BA25: 8 | BB25: 8 | BC25: 46308 | BD25: 46309 | BE25: 1 | BG25: 46314 | BI25: 1 | BJ25: 1 | BK25: 46324 | BL25: 46324 | BQ25: 19-Oct-26 DPWH Contact Person: Eirol Tulud Designation: Engr Contact No.: +639174811683 Here at DPWH Pangasinan 2nd DEO. Negotiated with the engr to separate the application for manhole opening and excavation. He agreed. He will send the checklist on my viber. BRGY: 8/8 DPWH: 0/1 LGU: 0/1 15-Oct-26 Brgy Herrero Accessible: DGP_MH_0010 MH 003 Permit secured with OR. 13-Oct-26 Dagupan Exchange Mh - DPGMH005 Grantor- Tapuac Brgy hall Contact Person: Sidney Lomboy Designation: Brgy Captain Remarks: Received and noted by the Brgy secretary that we don't need to secure a permit, as advised by the brgy captain. | BR25: =IFERROR((COUNT(BD25)*40%)+(COUNT(BL25)*20%)+(COUNT(BH25)*10%)+(COUNT(BP25)*10%)+(COUNT(AV25)*10%)+(COUNT(AZ25)*10%),0) -> 0.8 | BS25: =IF(BT25>0,WEEKNUM(BT25,1)&"-"&YEAR(BT25),"") -> 47-2026 | BT25: =AP25+3 -> 46346 | BU25: =IF(BV25>0,WEEKNUM(BV25,1)&"-"&YEAR(BV25),"") -> 48-2026 | BV25: 46351 | BW25: =IF(BX25>0,WEEKNUM(BX25,1)&"-"&YEAR(BX25),"") -> 50-2026 | BX25: =IF(CA25="",BV25+CD25,CA25+CD25) -> 46364.448 | BY25: =IF(CA25="",BV25+CD25,CA25+CD25) -> 46364.448 | CB25: =IF(AI25<>0,CC25*0.25,0) -> 0.5 | CC25: 2 | CD25: =IF(R25=0,IFERROR(Q25/(CC25)/1.25,0),IFERROR(R25/(CC25)/1.25,0)) -> 13.448 | CH25: =IF(CA25="","NOT STARTED",IF(CA25<>"","ON GOING EXTRACTION",IF(CV25<>"","EXTRACTION COMPLETED"))) -> NOT STARTED | CI25: =IFERROR(CQ25/CM25,0) -> 0 | CM25: =AG25 -> 42 | CN25: =AI25 -> 9 | CR25: =CM25-CQ25 -> 42 | CU25: =CS25+CT25 -> 0
A26: 46235 | B26: CANCELLED | C26: PART OF 233 | D26: NLZ | E26: 17.579119 | F26: 120.38896 | G26: Vigan City | H26: Ilocos Sur | I26: Ilocos | J26: Limwell | K26: CANCELLED | M26: IRUP0023 | N26: Vigan | O26: Exchange-M | P26: =IF(OR(NOT(ISNUMBER(Q26)),Q26=0),"NO DATA",IF(Q26<10,"<10 TONNES",">=10 TONNES")) -> >=10 TONNES | Q26: 156.8 | S26: =IF(CH26="CANCELLED","CANCELLED",IF(CV26<>"","EXTRACTION DONE",IF(CH26="ON GOING EXTRACTION","ON GOING EXTRACTION",IF(AR26="RFE","READY FOR EXTRACTION",IF(AR26="ON GOING PERMITTING","ON GOING PERMITTING",IF(AC26<>"","DESIGN APPROVED",IF(AB26<>"","DESIGN SUBMITTED",IF(AA26<>"","DESIGN COMPLETED",IF(Z26<>"","ON GOING DESIGN",IF(Y26<>"","ON GOING SURVEY","NOT STARTED")))))))))) -> CANCELLED | T26: =IFERROR((AN26*33%)+(BR26*27%)+(CI26*40%),0) -> 0 | U26: =IF(V26>0,WEEKNUM(V26,1)&"-"&YEAR(V26),"") -> 41-2026 | V26: 46304 | W26: =V26 -> 46304 | X26: =IF(AD26>0,"DESIGN WITH CONCERN",IF(AC26>0,"DESIGN APPROVED",IF(AB26>0,"DESIGN FOR APPROVAL",IF(AA26>0,"DESIGN FOR SUBMISSION",IF(Z26>0,"ON GOING DESIGN",IF(Y26>0,"ON GOING SURVEY","FOR SURVEY")))))) -> DESIGN WITH CONCERN | AD26: 10/6/26: CANCELLED SITE 10/2/26: SURVEY ISSUE | AF26: =IF(AA26-Y26<0,0,AA26-Y26) -> 0 | AG26: =AH26+AI26 -> 0 | AN26: =COUNT(Y26:AC26)/5 -> 0 | AO26: =IF(AQ26>0,WEEKNUM(AQ26,1)&"-"&YEAR(AQ26),"") | AQ26: 0 | AR26: =IF(AA26="","WAITING FOR PLAN",IF(AU26="","PERMITTING NOT STARTED",IF(BR26>=100%,"RFE","ON GOING PERMITTING"))) -> WAITING FOR PLAN | BR26: =IFERROR((COUNT(BD26)*40%)+(COUNT(BL26)*20%)+(COUNT(BH26)*10%)+(COUNT(BP26)*10%)+(COUNT(AV26)*10%)+(COUNT(AZ26)*10%),0) -> 0 | BS26: =IF(BT26>0,WEEKNUM(BT26,1)&"-"&YEAR(BT26),"") | BU26: =IF(BV26>0,WEEKNUM(BV26,1)&"-"&YEAR(BV26),"") | BW26: =IF(BX26>0,WEEKNUM(BX26,1)&"-"&YEAR(BX26),"") -> 9-1900 | BX26: =IF(CA26="",BV26+CD26,CA26+CD26) -> 62.72 | CB26: =IF(AI26<>0,CC26*0.25,0) -> 0 | CC26: 2 | CD26: =IF(R26=0,IFERROR(Q26/(CC26)/1.25,0),IFERROR(R26/(CC26)/1.25,0)) -> 62.72 | CH26: CANCELLED | CI26: =IFERROR(CQ26/CM26,0) -> 0 | CM26: =AG26 -> 0 | CN26: =AI26 -> 0 | CR26: =CM26-CQ26 -> 0 | CU26: =CS26+CT26 -> 0
A27: 46235 | B27: RFE | C27: PART OF 233 | D27: NLZ | E27: 16.616037 | F27: 120.31417 | G27: San Fernando | H27: La Union | I27: Ilocos | J27: Rowlan | K27: Q1 | M27: IRUP0024 | N27: SFU Exchange | O27: Exchange-M | P27: =IF(OR(NOT(ISNUMBER(Q27)),Q27=0),"NO DATA",IF(Q27<10,"<10 TONNES",">=10 TONNES")) -> >=10 TONNES | Q27: 156.8 | S27: =IF(CH27="CANCELLED","CANCELLED",IF(CV27<>"","EXTRACTION DONE",IF(CH27="ON GOING EXTRACTION","ON GOING EXTRACTION",IF(AR27="RFE","READY FOR EXTRACTION",IF(AR27="ON GOING PERMITTING","ON GOING PERMITTING",IF(AC27<>"","DESIGN APPROVED",IF(AB27<>"","DESIGN SUBMITTED",IF(AA27<>"","DESIGN COMPLETED",IF(Z27<>"","ON GOING DESIGN",IF(Y27<>"","ON GOING SURVEY","NOT STARTED")))))))))) -> ON GOING PERMITTING | T27: =IFERROR((AN27*33%)+(BR27*27%)+(CI27*40%),0) -> 0.357 | U27: =IF(V27>0,WEEKNUM(V27,1)&"-"&YEAR(V27),"") -> 42-2026 | V27: 46307 | W27: =V27 -> 46307 | X27: =IF(AD27>0,"DESIGN WITH CONCERN",IF(AC27>0,"DESIGN APPROVED",IF(AB27>0,"DESIGN FOR APPROVAL",IF(AA27>0,"DESIGN FOR SUBMISSION",IF(Z27>0,"ON GOING DESIGN",IF(Y27>0,"ON GOING SURVEY","FOR SURVEY")))))) -> DESIGN APPROVED | Y27: 46302 | Z27: 46305 | AA27: 46314 | AB27: 46314 | AC27: 46316 | AE27: Both | AF27: =IF(AA27-Y27<0,0,AA27-Y27) -> 12 | AG27: =AH27+AI27 -> 61 | AH27: 20 | AI27: 41 | AJ27: 32 | AK27: 9 | AN27: =COUNT(Y27:AC27)/5 -> 1 | AO27: =IF(AQ27>0,WEEKNUM(AQ27,1)&"-"&YEAR(AQ27),"") -> 48-2026 | AP27: 46343 | AQ27: 46351 | AR27: =IF(AA27="","WAITING FOR PLAN",IF(AU27="","PERMITTING NOT STARTED",IF(BR27>=100%,"RFE","ON GOING PERMITTING"))) -> ON GOING PERMITTING | AS27: NA | AT27: NA | AU27: 46324 | AV27: 46324 | BR27: =IFERROR((COUNT(BD27)*40%)+(COUNT(BL27)*20%)+(COUNT(BH27)*10%)+(COUNT(BP27)*10%)+(COUNT(AV27)*10%)+(COUNT(AZ27)*10%),0) -> 0.1 | BS27: =IF(BT27>0,WEEKNUM(BT27,1)&"-"&YEAR(BT27),"") -> 47-2026 | BT27: =AP27+3 -> 46346 | BU27: =IF(BV27>0,WEEKNUM(BV27,1)&"-"&YEAR(BV27),"") -> 49-2026 | BV27: 46356 | BW27: =IF(BX27>0,WEEKNUM(BX27,1)&"-"&YEAR(BX27),"") -> 6-2027 | BX27: =IF(CA27="",BV27+CD27,CA27+CD27) -> 46418.72 | BY27: =IF(CA27="",BV27+CD27,CA27+CD27) -> 46418.72 | CB27: =IF(AI27<>0,CC27*0.25,0) -> 0.5 | CC27: 2 | CD27: =IF(R27=0,IFERROR(Q27/(CC27)/1.25,0),IFERROR(R27/(CC27)/1.25,0)) -> 62.72 | CH27: =IF(CA27="","NOT STARTED",IF(CA27<>"","ON GOING EXTRACTION",IF(CV27<>"","EXTRACTION COMPLETED"))) -> NOT STARTED | CI27: =IFERROR(CQ27/CM27,0) -> 0 | CM27: =AG27 -> 61 | CN27: =AI27 -> 41 | CR27: =CM27-CQ27 -> 61 | CU27: =CS27+CT27 -> 0
A28: 46327 | B28: RFE | C28: PART OF 233 | D28: GMM | E28: 14.652672 | F28: 120.98642 | G28: Caloocan City | H28: Metropolitan Manila | I28: CaMaNaVa | J28: Dan | K28: Q1 | L28: T-37262327I-1-GMM-00005 | M28: IRUP0025 | N28: Grace Park Exchange (SXS) | O28: Exchange-L | P28: =IF(OR(NOT(ISNUMBER(Q28)),Q28=0),"NO DATA",IF(Q28<10,"<10 TONNES",">=10 TONNES")) -> >=10 TONNES | Q28: 726.5 | R28: 95.1 | S28: =IF(CH28="CANCELLED","CANCELLED",IF(CV28<>"","EXTRACTION DONE",IF(CH28="ON GOING EXTRACTION","ON GOING EXTRACTION",IF(AR28="RFE","READY FOR EXTRACTION",IF(AR28="ON GOING PERMITTING","ON GOING PERMITTING",IF(AC28<>"","DESIGN APPROVED",IF(AB28<>"","DESIGN SUBMITTED",IF(AA28<>"","DESIGN COMPLETED",IF(Z28<>"","ON GOING DESIGN",IF(Y28<>"","ON GOING SURVEY","NOT STARTED")))))))))) -> ON GOING PERMITTING | T28: =IFERROR((AN28*33%)+(BR28*27%)+(CI28*40%),0) -> 0.384 | U28: =IF(V28>0,WEEKNUM(V28,1)&"-"&YEAR(V28),"") -> 41-2026 | V28: 46300 | W28: =V28 -> 46300 | X28: =IF(AD28>0,"DESIGN WITH CONCERN",IF(AC28>0,"DESIGN APPROVED",IF(AB28>0,"DESIGN FOR APPROVAL",IF(AA28>0,"DESIGN FOR SUBMISSION",IF(Z28>0,"ON GOING DESIGN",IF(Y28>0,"ON GOING SURVEY","FOR SURVEY")))))) -> DESIGN APPROVED | Y28: 46288 | Z28: 46294 | AA28: 46302 | AB28: 46303 | AC28: 46309 | AE28: Both | AF28: =IF(AA28-Y28<0,0,AA28-Y28) -> 14 | AG28: =AH28+AI28 -> 447 | AH28: 235 | AI28: 212 | AJ28: 92 | AK28: 120 | AL28: 0 | AN28: =COUNT(Y28:AC28)/5 -> 1 | AO28: =IF(AQ28>0,WEEKNUM(AQ28,1)&"-"&YEAR(AQ28),"") -> 47-2026 | AP28: 46343 | AQ28: 46346 | AR28: =IF(AA28="","WAITING FOR PLAN",IF(AU28="","PERMITTING NOT STARTED",IF(BR28>=100%,"RFE","ON GOING PERMITTING"))) -> ON GOING PERMITTING | AS28: NA | AT28: NA | AU28: 46316 | AV28: 46316 | AW28: NA | AX28: NA | AY28: 46316 | AZ28: 46316 | BA28: 37 | BB28: 41 | BC28: 46307 | BE28: 2 | BG28: 46309 | BQ28: Oct 24 Brgy. 39-1 MH ( 1 Not Accessible) Contact name: JOANNE DE VERA Designation: BRGY. Secretary Contact number: 09762625989 Permit validity: END OF THE YEAR DEC 2026 Permit fee: 2,000 / OR Remarks: Permit Secured but the OR comeback by monday due to the treasurer are not available in the meeting. Note. Need to go to bgry hall 1st before to proced the activity and We can start the activity after All Saints Day due to the location of manhole is busy road Oct 24 Brgy. 157-1 MH ( Not Accessible) Contact name: Danilo Singh Designation: Brgy. Chairman Contact number: 09478799763 Permit validity: 6 Months Permit fee: 2500 / AR Remarks: Still waiting for Secretary as per Brgy. Chairman Note. Need to go to 1st to brgy. Hall to inform that will start the activity Oct 23 Brgy Pag ibig Nayon Permit Secured Oct 23 Bgry Sanjose Permit Secured Oct 23 Brgy Masambong Grantor Name masambong REMARKS: brgy captain agreed 10,000 pesos instead of 12,000 pesos permit secured cash bond paid 5,000 Oct 23 Brgy Manresa Permit secured Oct 23 Brgy:122 MH (2 Accessible) Remarks: As per Chairwoman Carmelita of Brgy. 122 the MH is not under their jurisdiction its under Brgy. 105. Brgy: 0/22 LGU: 0/1 DPWH: 0/1 DPSTM: 0/1 Oct 23 Barangay 121 - 6 MH (5 Accessible, 1 Not Accessible) Contact name: Jennifer Penilla Designation: Brgy. Staff Contact number: 09453418216 Permit fee / Receipt: Permit type: Permit validity: Remarks: LOI and Plan submitted. Secretary is out of Brgy. Brgy: 0/22 LGU: 0/1 DPWH: 0/1 DPSTM: 0/1 Oct 23 2K PER MANHOLE WE HAVE 20 MANHOLE INCLUDING MH 146 IT IS UNDER BRGY UNANG SIGAW. 40,000 OR , I negotiate it to 20,000 pesos OR plus 3k for sec as per secretary they are not signing any form of AR 3k will be good as donation without Ar but he will cooperate by giving his number Oct 22 Brgy. 50-1 MH ( 1 Accessible) Contact name: Rachelle E. Habitan Designation: Brgy. Secretary Contact number: 09995530001 Permit validity: END OF THE YEAR DEC. 2026 Permit fee: 500 (AR) Remarks: For Payment (TUESDAY) Note: Before start the activity needs to proceed first to brgy. Hall for information the brgy. and also we cant do the activity at night due to busy road. Brgy: 0/14 LGU: 0/1 DPWH: 0/1 Oct 22 Barangay 63 - 5 MH (1 Accessible, 4 Not Accessible) Contact name: Louie Serrano Designation: Brgy. Secretary Contact number: 09458900171 Permit fee / Receipt: 5,000.00 / AR Permit type: Working & Excavation Permit Permit validity: 6months Remarks: For payment. 1,000.00 per MH. Brgy: 0/22 LGU: 0/1 DPWH: 0/1 DPSTM: 0/1 Oct 22 Barangay 64 - 3 MH (3 Not Accessible) Contact name: Fe Conapa Designation: Brgy. Secretary Contact number: 09983958401 Permit fee / Receipt: Permit type: Permit validity: Remarks: LOA and Plan submitted. As per Sec she will contact me once Chairman is in Brgy. because this week he is busy in Municipal. Brgy: 0/22 LGU: 0/1 DPWH: 0/1 DPSTM: 0/1 Oct 22 Brgy. 45-1 MH ( 1 Accessible) Contact name: Leriza Lachica Designation: Brgy. Secretary Contact number: 09268727512 Permit validity: 6 Months Permit fee: 500 (AR) Remarks: For Payment (Monday) Note: Before start the activity needs to proceed first to brgy. Hall for information the brgy. and also we cant do the activity at morning. Brgy: 0/14 LGU: 0/1 DPWH: 0/1Oct 22 Barangay 65 - 2 MH (Not Accessible) Contact name: Ferdinand Boquiaza Designation: Brgy. Staff Contact number: 09155005267 Permit fee / Receipt: Permit type: Permit validity: Remarks: LOI and Plan submitted. Brgy: 0/22 LGU: 0/1 DPWH: 0/1 DPSTM: 0/1 OCT 22 Brgy. 42-1 MH ( 1 Not Accessible) Contact name: Anthony Santos Designation: Brgy EX.O Contact number: 09566421754 Permit validity: 3 Months Permit fee: 500 (AR) Remarks: For Payment (MONDAY) Note: Before start the activity needs to proceed first to brgy. Hall for information the brgy. and also we cant do the activity at morning. Brgy: 0/14 LGU: 0/1 DPWH: 0/1 OCT 22 Barangay 67 - 3 MH (1 Accessible, 2 Not Accessible) Contact name: Odette Cruz Designation: Brgy. Secretary Contact number: 09853881354 Permit fee / Receipt: 2000.00 per Manhole / OR Permit type: Working and Excavation Permit Permit validity: 6 months Remarks: For Payment. Brgy: 0/22 LGU: 0/1 DPWH: 0/1 DPSTM: 0/1 OCT 22-Brgy. 41-4 MH ( 4 Accessible) Contact name: Ronald Veluz Designation: Brgy. Chairman Contact number: 09669520949 Permit validity: END OF THE YEAR DEC 2026 Permit fee: 2,000 / (AR) Remarks: For payment (SATURDAY) Notes: Start activity Night due to busy road need to go to 1st in Brgy. hall to present permit and permission to brgy. for the activity. 21-Oct-26 153-1 MH ( Not Accessible) Contact name: Marissa de Torres Designation: Brgy. Secretary Contact number: 09686194412 Permit validity: Permit fee: Remarks: ongoing to the location of manhole Brgy: 16/21 LGU: 0/1 DPWH: 0/1 19-Oct-26 Brgy potrero Contact name MARILOU GARCIA contact number 09064725253 designtion- brgy TREASURER Validity of Permit - 6 MONTHS Working hours/days Permit fee -FREE Remarks: LOI is good as permit permit Brgy - 1/1 LGU - 0/1 TRAFFIC - 0/ DPWH - NA 15-Oct-26 (Brgy. 139-10 MH (3 Accessiable , 7 Not Accessible) Contact name: Cherish Anne Griffrth Designation: Brgy. Secretary Contact number: 09217233281 Permit validity: December 2026 Permit fee: 2,000 Remarks: For Payment Brgy: 9/ 21 LGU: 0/1 DPWH: 0/1 ) (Brgy. 90 - 9 MH (8 Accessible/ 1 Not Accessible) Remarks: LOI and Plan submitted. Advised to come back after lunch because Sec is not yet in Brgy. Brgy: 1/17 LGU: 0/1 DPWH: 0/1 PSTMD: 0/1) Brgy. 138-4MH (2 Accessiable 2 Not Accessible) Contact name: Tita O. Boringot Designation: Brgy. Secretary Contact number: 09911129748 Permit validity: December 2026 (renewable) Permit fee: 4000/ AR Remarks: For Payment Notes from 5,000 nego to 4,000 Brgy: 9/ 21 LGU: 0/1 DPWH: 0/1 ------------- 14-Oct-26 Wilna Yecla Designation: Brgy. Secretary Contact number: 09369864484 / 09227303791 Permit validity: 1 yr Permit fee: 6,000 2,000 per Manhole Remarks: waiting for chairwomen for payment process Brgy: 6/21 LGU: 0/1 DPWH: 0/1 13-Oct-26 Brgy. 74 - 1 MH (1 Accessible) Contact name: Reychelle Hypie N. Dela Cruz Designation: Brgy. Staff Contact number: 09675611914 Remarks: LOI and Plan submitted. Advised to comeback because Secretary is not yet in Brgy. Brgy: 0/17 LGU: 0/1 DPWH: 0/1 12-Oct-26 Brgy. 78 - 9MH (7 Accessible/ 2 Overlayed) Contact name: Rubelita Aquino Designation: Kagawad Contact number: 09913846879 Permit validity: December 2026 Permit fee: 1000 / AR Remarks: For Payment. Brgy: 0/3" | BR28: =IFERROR((COUNT(BD28)*40%)+(COUNT(BL28)*20%)+(COUNT(BH28)*10%)+(COUNT(BP28)*10%)+(COUNT(AV28)*10%)+(COUNT(AZ28)*10%),0) -> 0.2 | BS28: =IF(BT28>0,WEEKNUM(BT28,1)&"-"&YEAR(BT28),"") -> 47-2026 | BT28: =AP28+3 -> 46346 | BU28: =IF(BV28>0,WEEKNUM(BV28,1)&"-"&YEAR(BV28),"") -> 48-2026 | BV28: 46350 | BW28: =IF(BX28>0,WEEKNUM(BX28,1)&"-"&YEAR(BX28),"") -> 51-2026 | BX28: =IF(CA28="",BV28+CD28,CA28+CD28) -> 46375.36 | BY28: =IF(CA28="",BV28+CD28,CA28+CD28) -> 46375.36 | CB28: =IF(AI28<>0,CC28*0.25,0) -> 0.75 | CC28: 3 | CD28: =IF(R28=0,IFERROR(Q28/(CC28)/1.25,0),IFERROR(R28/(CC28)/1.25,0)) -> 25.36 | CG28: Frederick, Randy, Mjay, Loyd, Rafael, Winston, Mathew | CH28: =IF(CA28="","NOT STARTED",IF(CA28<>"","ON GOING EXTRACTION",IF(CV28<>"","EXTRACTION COMPLETED"))) -> NOT STARTED | CI28: =IFERROR(CQ28/CM28,0) -> 0 | CM28: =AG28 -> 447 | CN28: =AI28 -> 212 | CR28: =CM28-CQ28 -> 447 | CU28: =CS28+CT28 -> 0
B29: RFE | C29: ADDITIONAL | D29: GMM | E29: 14.6982 | F29: 121.1236 | G29: San Mateo | I29: Marikina | J29: Jessa | K29: Q1 | L29: T-37262327I-1-GMM-00004 | M29: IRUP0026 | N29: Digitel San Mateo MSU | O29: Exchange-S | P29: =IF(OR(NOT(ISNUMBER(Q29)),Q29=0),"NO DATA",IF(Q29<10,"<10 TONNES",">=10 TONNES")) -> >=10 TONNES | Q29: 11 | R29: 8.53 | S29: =IF(CH29="CANCELLED","CANCELLED",IF(CV29<>"","EXTRACTION DONE",IF(CH29="ON GOING EXTRACTION","ON GOING EXTRACTION",IF(AR29="RFE","READY FOR EXTRACTION",IF(AR29="ON GOING PERMITTING","ON GOING PERMITTING",IF(AC29<>"","DESIGN APPROVED",IF(AB29<>"","DESIGN SUBMITTED",IF(AA29<>"","DESIGN COMPLETED",IF(Z29<>"","ON GOING DESIGN",IF(Y29<>"","ON GOING SURVEY","NOT STARTED")))))))))) -> ON GOING PERMITTING | T29: =IFERROR((AN29*33%)+(BR29*27%)+(CI29*40%),0) -> 0.384 | U29: =IF(V29>0,WEEKNUM(V29,1)&"-"&YEAR(V29),"") -> 40-2026 | V29: 46297 | W29: =V29 -> 46297 | X29: =IF(AD29>0,"DESIGN WITH CONCERN",IF(AC29>0,"DESIGN APPROVED",IF(AB29>0,"DESIGN FOR APPROVAL",IF(AA29>0,"DESIGN FOR SUBMISSION",IF(Z29>0,"ON GOING DESIGN",IF(Y29>0,"ON GOING SURVEY","FOR SURVEY")))))) -> DESIGN APPROVED | Y29: 46295 | Z29: 46296 | AA29: 46296 | AB29: 46297 | AC29: 46300 | AE29: both | AF29: =IF(AA29-Y29<0,0,AA29-Y29) -> 1 | AG29: =AH29+AI29 -> 5 | AH29: 5 | AI29: 0 | AJ29: 0 | AK29: 0 | AL29: 0 | AN29: =COUNT(Y29:AC29)/5 -> 1 | AO29: =IF(AQ29>0,WEEKNUM(AQ29,1)&"-"&YEAR(AQ29),"") -> 45-2026 | AP29: 46340 | AQ29: 46333 | AR29: =IF(AA29="","WAITING FOR PLAN",IF(AU29="","PERMITTING NOT STARTED",IF(BR29>=100%,"RFE","ON GOING PERMITTING"))) -> ON GOING PERMITTING | AS29: NA | AT29: NA | AU29: 46316 | AV29: 46316 | AW29: NA | AX29: NA | AY29: 46316 | AZ29: 46316 | BA29: 1 | BB29: 3 | BC29: 46301 | BE29: 1 | BG29: 46301 | BI29: 1 | BK29: 46311 | BM29: 1 | BR29: =IFERROR((COUNT(BD29)*40%)+(COUNT(BL29)*20%)+(COUNT(BH29)*10%)+(COUNT(BP29)*10%)+(COUNT(AV29)*10%)+(COUNT(AZ29)*10%),0) -> 0.2 | BS29: =IF(BT29>0,WEEKNUM(BT29,1)&"-"&YEAR(BT29),"") -> 47-2026 | BT29: =AP29+3 -> 46343 | BU29: =IF(BV29>0,WEEKNUM(BV29,1)&"-"&YEAR(BV29),"") -> 46-2026 | BV29: 46337 | BW29: =IF(BX29>0,WEEKNUM(BX29,1)&"-"&YEAR(BX29),"") -> 46-2026 | BX29: =IF(CA29="",BV29+CD29,CA29+CD29) -> 46340.412 | BY29: =IF(CA29="",BV29+CD29,CA29+CD29) -> 46340.412 | CB29: =IF(AI29<>0,CC29*0.25,0) -> 0 | CC29: 2 | CD29: =IF(R29=0,IFERROR(Q29/(CC29)/1.25,0),IFERROR(R29/(CC29)/1.25,0)) -> 3.412 | CG29: Leny, Judy, Mark Sun, Raymark, Luis | CH29: =IF(CA29="","NOT STARTED",IF(CA29<>"","ON GOING EXTRACTION",IF(CV29<>"","EXTRACTION COMPLETED"))) -> NOT STARTED | CI29: =IFERROR(CQ29/CM29,0) -> 0 | CM29: =AG29 -> 5 | CN29: =AI29 -> 0 | CR29: =CM29-CQ29 -> 5 | CU29: =CS29+CT29 -> 0
A30: 46327 | B30: RFE | C30: PART OF 233 | D30: GMM | E30: 14.675793 | F30: 121.08143 | G30: Quezon City | H30: Metropolitan Manila | I30: North QC | J30: Jessa | K30: Q1 | L30: T-37262327I-1-GMM-00016 | M30: IRUP0027 | N30: Balara Exchange | O30: Exchange-M | P30: =IF(OR(NOT(ISNUMBER(Q30)),Q30=0),"NO DATA",IF(Q30<10,"<10 TONNES",">=10 TONNES")) -> >=10 TONNES | Q30: 228.5 | R30: 71.44 | S30: =IF(CH30="CANCELLED","CANCELLED",IF(CV30<>"","EXTRACTION DONE",IF(CH30="ON GOING EXTRACTION","ON GOING EXTRACTION",IF(AR30="RFE","READY FOR EXTRACTION",IF(AR30="ON GOING PERMITTING","ON GOING PERMITTING",IF(AC30<>"","DESIGN APPROVED",IF(AB30<>"","DESIGN SUBMITTED",IF(AA30<>"","DESIGN COMPLETED",IF(Z30<>"","ON GOING DESIGN",IF(Y30<>"","ON GOING SURVEY","NOT STARTED")))))))))) -> ON GOING PERMITTING | T30: =IFERROR((AN30*33%)+(BR30*27%)+(CI30*40%),0) -> 0.384 | U30: =IF(V30>0,WEEKNUM(V30,1)&"-"&YEAR(V30),"") -> 42-2026 | V30: 46307 | W30: =V30 -> 46307 | X30: =IF(AD30>0,"DESIGN WITH CONCERN",IF(AC30>0,"DESIGN APPROVED",IF(AB30>0,"DESIGN FOR APPROVAL",IF(AA30>0,"DESIGN FOR SUBMISSION",IF(Z30>0,"ON GOING DESIGN",IF(Y30>0,"ON GOING SURVEY","FOR SURVEY")))))) -> DESIGN APPROVED | Y30: 46294 | Z30: 46295 | AA30: 46307 | AB30: 46308 | AC30: 46309 | AE30: Both | AF30: =IF(AA30-Y30<0,0,AA30-Y30) -> 13 | AG30: =AH30+AI30 -> 198 | AH30: 79 | AI30: 119 | AJ30: 84 | AK30: 48 | AN30: =COUNT(Y30:AC30)/5 -> 1 | AO30: =IF(AQ30>0,WEEKNUM(AQ30,1)&"-"&YEAR(AQ30),"") -> 47-2026 | AP30: 46343 | AQ30: 46347 | AR30: =IF(AA30="","WAITING FOR PLAN",IF(AU30="","PERMITTING NOT STARTED",IF(BR30>=100%,"RFE","ON GOING PERMITTING"))) -> ON GOING PERMITTING | AS30: NA | AT30: NA | AU30: 46316 | AV30: 46316 | AW30: NA | AX30: NA | AY30: 46316 | AZ30: 46316 | BA30: 12 | BB30: 1 | BC30: 46310 | BE30: 1 | BG30: 46309 | BM30: 2 | BO30: 46310 | BQ30: Oct 23 Brgy PAYATAS Activity: submit LOI nad design plan for permitting Output: As per maam Sonia mendoza CRO, the permit cost is 25000 down to 15000 . Sonia Mendoza CRO Oct 23 MMDA Activity: Inquire for the requirements of permit Output: According to the Information Desk Officer, the Traffic Engineering Center (MMDA) is closed every Friday, so I was told to come back on Monday. LGU: 0/1 HOA: 0/? DPWH: 0/1 MMDA: 0/1 BARANGAY: 1/10 OCT 22-DPWH 1st district of QC DPWH 2st district of QC Activity: coordinate MH's covered by asphalt Output:As per Engr. Jillian, 2nd Engineer of the Maintenance Division at DPWH 1st District, Quezon City ,They will first look for the documents and check who they have been coordinating with at PLDT. They will just message me once they find them.15-Oct-26 DPWH 2st district of QC Activity: coordinate MH's covered by asphalt Output:As per Engr. Kiko, we need to complete our requirements first. We also need to submit the SLD tomorrow for site verification to determine which areas fall within their vicinity. They would also like to schedule a meeting for next Monday at 10:00 AM with PLDT. | BR30: =IFERROR((COUNT(BD30)*40%)+(COUNT(BL30)*20%)+(COUNT(BH30)*10%)+(COUNT(BP30)*10%)+(COUNT(AV30)*10%)+(COUNT(AZ30)*10%),0) -> 0.2 | BS30: =IF(BT30>0,WEEKNUM(BT30,1)&"-"&YEAR(BT30),"") -> 47-2026 | BT30: =AP30+3 -> 46346 | BU30: =IF(BV30>0,WEEKNUM(BV30,1)&"-"&YEAR(BV30),"") -> 48-2026 | BV30: 46352 | BW30: =IF(BX30>0,WEEKNUM(BX30,1)&"-"&YEAR(BX30),"") -> 51-2026 | BX30: =IF(CA30="",BV30+CD30,CA30+CD30) -> 46371.051 | BY30: =IF(CA30="",BV30+CD30,CA30+CD30) -> 46371.051 | CB30: =IF(AI30<>0,CC30*0.25,0) -> 0.75 | CC30: 3 | CD30: =IF(R30=0,IFERROR(Q30/(CC30)/1.25,0),IFERROR(R30/(CC30)/1.25,0)) -> 19.050667 | CG30: Leny, Judy, Mark Sun, Raymark, Luis | CH30: =IF(CA30="","NOT STARTED",IF(CA30<>"","ON GOING EXTRACTION",IF(CV30<>"","EXTRACTION COMPLETED"))) -> NOT STARTED | CI30: =IFERROR(CQ30/CM30,0) -> 0 | CM30: =AG30 -> 198 | CN30: =AI30 -> 119 | CR30: =CM30-CQ30 -> 198 | CU30: =CS30+CT30 -> 0
A31: 46327 | B31: RFE | C31: PART OF 233 | D31: GMM | E31: 14.712238 | F31: 121.03953 | G31: Quezon City | H31: Metropolitan Manila | I31: North QC | J31: Dan | K31: Q1 | M31: IRUP0028 | N31: Novaliches Exchange | O31: Exchange-M | P31: =IF(OR(NOT(ISNUMBER(Q31)),Q31=0),"NO DATA",IF(Q31<10,"<10 TONNES",">=10 TONNES")) -> >=10 TONNES | Q31: 638.7 | R31: 192.3 | S31: =IF(CH31="CANCELLED","CANCELLED",IF(CV31<>"","EXTRACTION DONE",IF(CH31="ON GOING EXTRACTION","ON GOING EXTRACTION",IF(AR31="RFE","READY FOR EXTRACTION",IF(AR31="ON GOING PERMITTING","ON GOING PERMITTING",IF(AC31<>"","DESIGN APPROVED",IF(AB31<>"","DESIGN SUBMITTED",IF(AA31<>"","DESIGN COMPLETED",IF(Z31<>"","ON GOING DESIGN",IF(Y31<>"","ON GOING SURVEY","NOT STARTED")))))))))) -> ON GOING PERMITTING | T31: =IFERROR((AN31*33%)+(BR31*27%)+(CI31*40%),0) -> 0.318 | U31: =IF(V31>0,WEEKNUM(V31,1)&"-"&YEAR(V31),"") -> 42-2026 | V31: 46311 | W31: =V31 -> 46311 | X31: =IF(AD31>0,"DESIGN WITH CONCERN",IF(AC31>0,"DESIGN APPROVED",IF(AB31>0,"DESIGN FOR APPROVAL",IF(AA31>0,"DESIGN FOR SUBMISSION",IF(Z31>0,"ON GOING DESIGN",IF(Y31>0,"ON GOING SURVEY","FOR SURVEY")))))) -> DESIGN FOR APPROVAL | Y31: 46291 | Z31: 46295 | AA31: 46310 | AB31: 46322 | AE31: Both | AF31: =IF(AA31-Y31<0,0,AA31-Y31) -> 19 | AG31: =AH31+AI31 -> 421 | AH31: 234 | AI31: 187 | AJ31: 148 | AK31: 33 | AN31: =COUNT(Y31:AC31)/5 -> 0.8 | AO31: =IF(AQ31>0,WEEKNUM(AQ31,1)&"-"&YEAR(AQ31),"") -> 48-2026 | AP31: 46356 | AQ31: 46351 | AR31: =IF(AA31="","WAITING FOR PLAN",IF(AU31="","PERMITTING NOT STARTED",IF(BR31>=100%,"RFE","ON GOING PERMITTING"))) -> ON GOING PERMITTING | AS31: NA | AT31: NA | AU31: 46322 | AV31: 46322 | AW31: NA | AX31: NA | AY31: 46322 | AZ31: 46322 | BA31: 21 | BB31: 2 | BC31: 46322 | BR31: =IFERROR((COUNT(BD31)*40%)+(COUNT(BL31)*20%)+(COUNT(BH31)*10%)+(COUNT(BP31)*10%)+(COUNT(AV31)*10%)+(COUNT(AZ31)*10%),0) -> 0.2 | BS31: =IF(BT31>0,WEEKNUM(BT31,1)&"-"&YEAR(BT31),"") -> 49-2026 | BT31: =AP31+3 -> 46359 | BU31: =IF(BV31>0,WEEKNUM(BV31,1)&"-"&YEAR(BV31),"") -> 49-2026 | BV31: 46355 | BW31: =IF(BX31>0,WEEKNUM(BX31,1)&"-"&YEAR(BX31),"") -> 2-2027 | BX31: =IF(CA31="",BV31+CD31,CA31+CD31) -> 46393.46 | BY31: =IF(CA31="",BV31+CD31,CA31+CD31) -> 46393.46 | CB31: =IF(AI31<>0,CC31*0.25,0) -> 1 | CC31: 4 | CD31: =IF(R31=0,IFERROR(Q31/(CC31)/1.25,0),IFERROR(R31/(CC31)/1.25,0)) -> 38.46 | CG31: Leny, Judy, Mark Sun, Raymark, Luis | CH31: =IF(CA31="","NOT STARTED",IF(CA31<>"","ON GOING EXTRACTION",IF(CV31<>"","EXTRACTION COMPLETED"))) -> NOT STARTED | CI31: =IFERROR(CQ31/CM31,0) -> 0 | CM31: =AG31 -> 421 | CN31: =AI31 -> 187 | CR31: =CM31-CQ31 -> 421 | CU31: =CS31+CT31 -> 0
A32: 46327 | B32: RFE | C32: PART OF 233 | D32: GMM | E32: 14.647577 | F32: 121.02346 | G32: Quezon City | H32: Metropolitan Manila | I32: South QC | J32: Dan | K32: Q1 | L32: T-37262327I-1-GMM-00008 | M32: IRUP0029 | N32: South Triangle CO/Service Yard | O32: Exchange-M | P32: =IF(OR(NOT(ISNUMBER(Q32)),Q32=0),"NO DATA",IF(Q32<10,"<10 TONNES",">=10 TONNES")) -> >=10 TONNES | Q32: 171.6 | R32: 53.71 | S32: =IF(CH32="CANCELLED","CANCELLED",IF(CV32<>"","EXTRACTION DONE",IF(CH32="ON GOING EXTRACTION","ON GOING EXTRACTION",IF(AR32="RFE","READY FOR EXTRACTION",IF(AR32="ON GOING PERMITTING","ON GOING PERMITTING",IF(AC32<>"","DESIGN APPROVED",IF(AB32<>"","DESIGN SUBMITTED",IF(AA32<>"","DESIGN COMPLETED",IF(Z32<>"","ON GOING DESIGN",IF(Y32<>"","ON GOING SURVEY","NOT STARTED")))))))))) -> ON GOING PERMITTING | T32: =IFERROR((AN32*33%)+(BR32*27%)+(CI32*40%),0) -> 0.384 | U32: =IF(V32>0,WEEKNUM(V32,1)&"-"&YEAR(V32),"") -> 40-2026 | V32: 46297 | W32: =V32 -> 46297 | X32: =IF(AD32>0,"DESIGN WITH CONCERN",IF(AC32>0,"DESIGN APPROVED",IF(AB32>0,"DESIGN FOR APPROVAL",IF(AA32>0,"DESIGN FOR SUBMISSION",IF(Z32>0,"ON GOING DESIGN",IF(Y32>0,"ON GOING SURVEY","FOR SURVEY")))))) -> DESIGN APPROVED | Y32: 46296 | Z32: 46297 | AA32: 46298 | AB32: 46300 | AC32: 46300 | AE32: Both | AF32: =IF(AA32-Y32<0,0,AA32-Y32) -> 2 | AG32: =AH32+AI32 -> 144 | AH32: 64 | AI32: 80 | AJ32: 66 | AK32: 14 | AL32: 0 | AN32: =COUNT(Y32:AC32)/5 -> 1 | AO32: =IF(AQ32>0,WEEKNUM(AQ32,1)&"-"&YEAR(AQ32),"") -> 47-2026 | AP32: 46339 | AQ32: 46346 | AR32: =IF(AA32="","WAITING FOR PLAN",IF(AU32="","PERMITTING NOT STARTED",IF(BR32>=100%,"RFE","ON GOING PERMITTING"))) -> ON GOING PERMITTING | AS32: NA | AT32: NA | AU32: 46316 | AV32: 46316 | AW32: NA | AX32: NA | AY32: 46316 | AZ32: 46316 | BA32: 4 | BB32: 11 | BC32: 46301 | BQ32: oCT 23 Brgy. Del Monte Contact Name: Cornelio Pabustan Contact Number: 09190942134 Designation: Brgy. Chairman Validity of Permit: 6months / Renewable Permit fee: 15k AR -- Remarks: Done payment. Permit acquired. Chairman did not provide ID for privacy. NOTE: ASK COURTESY TO BRGY FIRST BEFORE IMPLEMENTATION STARTS OCT 22 Cluster 2.3 of South Triangle CO MH Nos.: MH7576, MH7573, MH7575, MH7574, MH7572, MH7595, MH7761, SB_007 Grantor Name: Brgy. San Antonio Contact name: Chairman Daniel Leon Berroyo Contact number: 09178278917 Designation: BRGY CHAIRMAN TOTAL AMOUNT: 46,000 OR Validity: 3 months Remarks: Tried to negotiate again to lower the permit fee amounting 46,000. However, Kap explained that the transportation and proper handling of equipment are covered by the barangay ordinance and are included in the Order of Payment due to the potential traffic congestion they may cause. This is why additional charges are imposed. The barangay is already upset due to the repeated negotiations. They also intend to get back the Order of Payment and revert the permit fee to ₱196,000, with a 1% cash bond (CB) based on the total project cost. BRGY - 0/4 DPWH - 0/1 LGU - 0/1 TTMD - 0/1 19-Oct-26 Brgy. Paraiso Contact name: Connee P. Dalmacio Contact number: 09189053739 Designation: Treasurer Validity of Permit: 6months/ renewable Permit fee: 15,000 / OR (Excavation Permit for 8 MH) Remarks: As per Ma’am Connee, the permit fee is stated in their ordinance, and they will issue an Official Receipt (OR) to us. However, if we insist on negotiating the permit fee, Chairman may instead require us to pay the ₱100,000 cash bond (CB) that he initially required. 15-Oct-26 HOA Heroes Hill Civic Association Inc. Remarks: for verification and application 14-Oct-26 - BRGY. NAYONG KANLURAN CONTACT NAME:Rowena Serano CONTACT NUNBER: 85648382 DESIGNATION:Brgy. Admin VALIDITY OF PERMIT: 6months PERMIT FEE: 100 OR REMARKS: Permit Acquired. Make sure to log in to Brgy first before starting implementation. BRGY - 3/4 LGU - 0/1 DPWH - 0/1 TRAFFIC() BRGY. NAYONG KANLURAN CONTACT NAME:Rowena Serano CONTACT NUNBER: 85648382 DESIGNATION:Brgy. Admin VALIDITY OF PERMIT: PERMIT FEE: REMARKS: for payment, waiting for maam Rowena BRGY - 2/4 LGU - 0/1 DPWH - 0/1 TRAFFIC 12-Oct-26 Brgy. Obrero Permit Fee - 2,000 OR Validity: 3 months Remarks: For payment, waiting for Treas. As per maam Kim, the payment cancelled for today because the Treasurer is reportedly in the hospital and there is no confirmation on when she will return. The Treasurer is the only person authorized to process payments, so the payment and permit processing will need to be rescheduled. For follow up tomorrow. ----- 8-Oct-26 Brgy. Paltok Contact name: Regino C. Pasaraba Contact number: 09568069372 Designation: Brgy. Admin Validity of Permit: 6months validity/ Renewable Permit fee: 3,000 Maintenance Permit fee/ OR, 6,000 Excavation Permit fee (3 MH)/ OR, 5,000 Cashbond/ AR Remarks: For Payment, For apply in LGU, DPWH and TTMD because Baler st and Mabuhay Lane is busy road. Requires 2 Tanod for posting during implementation. Brgy.: 0/4 LGU: 0/1 TTMD: 0/1 DPWH: 0/1 7-Oct-26 Brgy. Del Monte, Brgy. San Antonio, Sta. Cruz SITENAME: Kalookan Exchange CO Cluster No.: 2 | BR32: =IFERROR((COUNT(BD32)*40%)+(COUNT(BL32)*20%)+(COUNT(BH32)*10%)+(COUNT(BP32)*10%)+(COUNT(AV32)*10%)+(COUNT(AZ32)*10%),0) -> 0.2 | BS32: =IF(BT32>0,WEEKNUM(BT32,1)&"-"&YEAR(BT32),"") -> 47-2026 | BT32: =AP32+3 -> 46342 | BU32: =IF(BV32>0,WEEKNUM(BV32,1)&"-"&YEAR(BV32),"") -> 48-2026 | BV32: 46350 | BW32: =IF(BX32>0,WEEKNUM(BX32,1)&"-"&YEAR(BX32),"") -> 50-2026 | BX32: =IF(CA32="",BV32+CD32,CA32+CD32) -> 46364.323 | BY32: =IF(CA32="",BV32+CD32,CA32+CD32) -> 46364.323 | CB32: =IF(AI32<>0,CC32*0.25,0) -> 0.75 | CC32: 3 | CD32: =IF(R32=0,IFERROR(Q32/(CC32)/1.25,0),IFERROR(R32/(CC32)/1.25,0)) -> 14.322667 | CG32: Leny, Judy, Mark Sun, Raymark, Luis | CH32: =IF(CA32="","NOT STARTED",IF(CA32<>"","ON GOING EXTRACTION",IF(CV32<>"","EXTRACTION COMPLETED"))) -> NOT STARTED | CI32: =IFERROR(CQ32/CM32,0) -> 0 | CM32: =AG32 -> 144 | CN32: =AI32 -> 80 | CR32: =CM32-CQ32 -> 144 | CU32: =CS32+CT32 -> 0
A33: 46327 | B33: RFE | C33: PART OF 233 | D33: NLZ | E33: 15.487171 | F33: 120.96974 | G33: Cabanatuan City | H33: Nueva Ecija | I33: Tarlac-NE | J33: Rowlan | K33: Q1 | L33: T-37262327I-1-NLZ-00001 | M33: IRUP0030 | N33: Cabanatuan Exchange | O33: Exchange-M | P33: =IF(OR(NOT(ISNUMBER(Q33)),Q33=0),"NO DATA",IF(Q33<10,"<10 TONNES",">=10 TONNES")) -> >=10 TONNES | Q33: 76.6 | R33: 25.92 | S33: =IF(CH33="CANCELLED","CANCELLED",IF(CV33<>"","EXTRACTION DONE",IF(CH33="ON GOING EXTRACTION","ON GOING EXTRACTION",IF(AR33="RFE","READY FOR EXTRACTION",IF(AR33="ON GOING PERMITTING","ON GOING PERMITTING",IF(AC33<>"","DESIGN APPROVED",IF(AB33<>"","DESIGN SUBMITTED",IF(AA33<>"","DESIGN COMPLETED",IF(Z33<>"","ON GOING DESIGN",IF(Y33<>"","ON GOING SURVEY","NOT STARTED")))))))))) -> READY FOR EXTRACTION | T33: =IFERROR((AN33*33%)+(BR33*27%)+(CI33*40%),0) -> 0.6 | U33: =IF(V33>0,WEEKNUM(V33,1)&"-"&YEAR(V33),"") -> 40-2026 | V33: 46293 | W33: =V33 -> 46293 | X33: =IF(AD33>0,"DESIGN WITH CONCERN",IF(AC33>0,"DESIGN APPROVED",IF(AB33>0,"DESIGN FOR APPROVAL",IF(AA33>0,"DESIGN FOR SUBMISSION",IF(Z33>0,"ON GOING DESIGN",IF(Y33>0,"ON GOING SURVEY","FOR SURVEY")))))) -> DESIGN APPROVED | Y33: 46290 | Z33: 46291 | AA33: 46292 | AB33: 46297 | AC33: 46300 | AE33: Both | AF33: =IF(AA33-Y33<0,0,AA33-Y33) -> 2 | AG33: =AH33+AI33 -> 21 | AH33: 21 | AI33: 0 | AJ33: 0 | AK33: 0 | AL33: 0 | AN33: =COUNT(Y33:AC33)/5 -> 1 | AO33: =IF(AQ33>0,WEEKNUM(AQ33,1)&"-"&YEAR(AQ33),"") -> 45-2026 | AP33: 46329 | AQ33: 46329 | AR33: =IF(AA33="","WAITING FOR PLAN",IF(AU33="","PERMITTING NOT STARTED",IF(BR33>=100%,"RFE","ON GOING PERMITTING"))) -> RFE | AS33: NA | AT33: NA | AU33: 46316 | AV33: 46316 | AW33: NA | AX33: NA | AY33: 46316 | AZ33: 46316 | BA33: 10 | BB33: 10 | BC33: 46296 | BD33: 46301 | BE33: 1 | BF33: 1 | BG33: 46302 | BH33: 46304 | BI33: 1 | BJ33: 1 | BK33: 46307 | BL33: 46302 | BM33: 1 | BN33: 1 | BO33: 46302 | BP33: 46307 | BQ33: 12-Oct-26 - RFE Sites Secured LGU 6-Oct-26 ENGINEERING OFFICE of Cabanatuan . we need LGU application bec of manholes location in front of the LGU building. - need 3 sets of signed and sealed of plan (A3) - BOM/BOQ - excavation form also need to be signed and sealed of CE or Architect. -ID PTR of PROFESSIONAL ----- 2-Oct-26 (BRGY. DIMASALANG POB. Contact Name: ROUELLA DAYOJA Designation - BRGY. SECRETARY Validity permit - 1 YEAR Permit Fee - 1000 (AR) Remarks : done payment. - permit secured ) --- (Brgy. SAN ROQUE NORTE MH013 Submitted LOI. as per Bgry. SECRETARY Annie the fee for Bgry. Clearance is NOT YET DETERMINED. and she will ask first the brgy tres. if there's a FEE.. She also told me to just come back on Monday morning for the permit. CONTACT PERSON : ANNIE ROSE DEL ROSARIO BARANGAY SECRETARY 0955-209-5902) --- (Brgy. MELOJAVILLA MH022 Submitted LOI. as per Bgry. SECRETARY Elvie the fee for Bgry. Clearance is NOT YET DETERMINED. She also told me to just come back on Monday morning so I could speak to the barangay captain in person about this. CONTACT PERSON : Elvie Madiraga BARANGAY SECRETARY 0991-910-5119) ---- (@Brgy. DIMASALANG MH015,MH016 Submitted LOI. as per Bgry. SECRETARY the fee for Bgry. Clearance is NOT YET DETERMINED and they talked about it with the brgy. councils. validity of permit is 1 YEAR. CONTACT PERSON : ROUELLA DAYOJA BARANGAY SECRETARY 0953-521-6571) ---- 1-Oct-26 (Brgy. SAN JUAN POB. (ACOFA) MH036,MH037 Submitted LOI. as per Bgry. Secretary Nida the fee for Bgry. Clearance is not yet determined and she will contact me when she confirmed it. and the validity of permit is 1 YEAR. CONTACT PERSON : NIDA de Jesus Brgy. SECRETARY 0976-123-7920) --- Bgry. Captian JEFFREY VILLEGAS the fee for Bgry. Clearance is 1000. and they can only provide ACKNOWLEDGE RECIEPT. validity of permit is 1 YEAR. CONTACT PERSON : JEFFREY VILLEGAS Brgy. CAPTAIN 09704862495 | BR33: =IFERROR((COUNT(BD33)*40%)+(COUNT(BL33)*20%)+(COUNT(BH33)*10%)+(COUNT(BP33)*10%)+(COUNT(AV33)*10%)+(COUNT(AZ33)*10%),0) -> 1 | BS33: =IF(BT33>0,WEEKNUM(BT33,1)&"-"&YEAR(BT33),"") -> 44-2026 | BT33: 46323 | BU33: =IF(BV33>0,WEEKNUM(BV33,1)&"-"&YEAR(BV33),"") -> 45-2026 | BV33: 46329 | BW33: =IF(BX33>0,WEEKNUM(BX33,1)&"-"&YEAR(BX33),"") -> 46-2026 | BX33: =IF(CA33="",BV33+CD33,CA33+CD33) -> 46339.368 | BY33: 46340 | BZ33: 10/29/26: DD:10/30 | CB33: =IF(AI33<>0,CC33*0.25,0) -> 0 | CC33: 2 | CD33: =IF(R33=0,IFERROR(Q33/(CC33)/1.25,0),IFERROR(R33/(CC33)/1.25,0)) -> 10.368 | CE33: ASSURE | CF33: BOTH | CG33: Rainer, Michael, Richard, Ron | CH33: =IF(CA33="","NOT STARTED",IF(CA33<>"","ON GOING EXTRACTION",IF(CV33<>"","EXTRACTION COMPLETED"))) -> NOT STARTED | CI33: =IFERROR(CQ33/CM33,0) -> 0 | CM33: =AG33 -> 21 | CN33: =AI33 -> 0 | CR33: =CM33-CQ33 -> 21 | CU33: =CS33+CT33 -> 0
A34: 46327 | B34: RFE | C34: PART OF 233 | D34: NLZ | E34: 14.849437 | F34: 120.81382 | G34: Malolos | H34: Bulacan | I34: Bulacan | J34: Limwell | K34: Q1 | M34: IRUP0031 | N34: Malolos Exchange | O34: Exchange-M | P34: =IF(OR(NOT(ISNUMBER(Q34)),Q34=0),"NO DATA",IF(Q34<10,"<10 TONNES",">=10 TONNES")) -> >=10 TONNES | Q34: 75.3 | R34: 23.56 | S34: =IF(CH34="CANCELLED","CANCELLED",IF(CV34<>"","EXTRACTION DONE",IF(CH34="ON GOING EXTRACTION","ON GOING EXTRACTION",IF(AR34="RFE","READY FOR EXTRACTION",IF(AR34="ON GOING PERMITTING","ON GOING PERMITTING",IF(AC34<>"","DESIGN APPROVED",IF(AB34<>"","DESIGN SUBMITTED",IF(AA34<>"","DESIGN COMPLETED",IF(Z34<>"","ON GOING DESIGN",IF(Y34<>"","ON GOING SURVEY","NOT STARTED")))))))))) -> ON GOING PERMITTING | T34: =IFERROR((AN34*33%)+(BR34*27%)+(CI34*40%),0) -> 0.372 | U34: =IF(V34>0,WEEKNUM(V34,1)&"-"&YEAR(V34),"") -> 42-2026 | V34: 46307 | W34: =V34 -> 46307 | X34: =IF(AD34>0,"DESIGN WITH CONCERN",IF(AC34>0,"DESIGN APPROVED",IF(AB34>0,"DESIGN FOR APPROVAL",IF(AA34>0,"DESIGN FOR SUBMISSION",IF(Z34>0,"ON GOING DESIGN",IF(Y34>0,"ON GOING SURVEY","FOR SURVEY")))))) -> DESIGN FOR APPROVAL | Y34: 46297 | Z34: 46297 | AA34: 46307 | AB34: 46321 | AE34: Both | AF34: =IF(AA34-Y34<0,0,AA34-Y34) -> 10 | AG34: =AH34+AI34 -> 85 | AH34: 20 | AI34: 65 | AJ34: 35 | AK34: 30 | AN34: =COUNT(Y34:AC34)/5 -> 0.8 | AO34: =IF(AQ34>0,WEEKNUM(AQ34,1)&"-"&YEAR(AQ34),"") -> 47-2026 | AP34: 46349 | AQ34: 46346 | AR34: =IF(AA34="","WAITING FOR PLAN",IF(AU34="","PERMITTING NOT STARTED",IF(BR34>=100%,"RFE","ON GOING PERMITTING"))) -> ON GOING PERMITTING | AS34: NA | AT34: NA | AU34: 46317 | AV34: 46317 | AW34: NA | AX34: NA | AY34: 46317 | AZ34: 46317 | BA34: 15 | BB34: 7 | BC34: 46311 | BE34: 1 | BG34: 46322 | BI34: 1 | BJ34: 1 | BK34: 46324 | BL34: 46324 | BQ34: Oct 23 Brgy Mabolo, Malolos Bulacan Remarks:/Report: As per the barangay Captain, the locations indicated in the development plan are not under their jurisdiction. Oct 23 Brgy Mojon, Malolos Bulacan Contact name: Willie Dela Rosa Contact name: 09626426314 Designation: brgy Sec Validit of Permit: Permit Fee: Remarks:/Report: LOI has been submitted. As per the barangay personnel, Kapitan will review the letter first. They’ll just contact me once I can come back to speak with Kapitan Oct 23 Brgy Dakila, Malolos Bulacan Contact name: Jan Marithe Dela Pena Contact name: 09637007497 Designation: brgy Clerk Validit of Permit: Permit Fee: Remarks:/Report: LOI has been submitted. As per the barangay personnel, Kapitan will review the letter first. They’ll just contact me once I can come back to speak with Kapitan. Brgy Dakila, Malolos Bulacan Contact name: Jan Marithe Dela Pena Contact name: 09637007497 Designation: brgy Clerk Validit of Permit: Permit Fee: Remarks:/Report: LOI has been submitted. As per the barangay personnel, Kapitan will review the letter first. They’ll just contact me once I can come back to speak with Kapitan. Brgy Dakila, Malolos Bulacan Contact name: Jan Marithe Dela Pena Contact name: 09637007497 Designation: brgy Clerk Validit of Permit: Permit Fee: Remarks:/Report: LOI has been submitted. As per the barangay personnel, Kapitan will review the letter first. They’ll just contact me once I can come back to speak with Kapitan. Brgy Dakila, Malolos Bulacan Contact name: Jan Marithe Dela Pena Contact name: 09637007497 Designation: brgy Clerk Validit of Permit: Permit Fee: Remarks:/Report: LOI has been submitted. As per the barangay personnel, Kapitan will review the letter first. They’ll just contact me once I can come back to speak with Kapitan. Oct 22 Brgy Sumapang Matanda, Malolos Bulacan Remarks:/Report: I was able to speak with the Barangay Secretary and submit the LOI. I was advised to return on Monday morning to meet with the Barangay Captain. Brgy Sumapang Matanda, Malolos Bulacan Remarks:/Report: I was able to speak with the Barangay Secretary and submit the LOI. I was advised to return on Monday morning to meet with the Barangay Captain. Brgy Sumapang Matanda, Malolos Bulacan Remarks:/Report: I was able to speak with the Barangay Secretary and submit the LOI. I was advised to return on Monday morning to meet with the Barangay Captain. Oct 22 Brgy Guinhawa, Malolos Bulacan Contact name: Maria Cristina Santiago contact number: 09670563516 Designation: Brgy Sec Validity of Permit - 2 years Permit fee - 2,000 per manhole Remarks:/Report: As I discussed with the Brgy. Captain, I presented all the locations of the manholes that we will be opening. Upon checking, almost all of our manholes fall under their jurisdiction. Even some of the manholes indicated under Brgy. Catmon in the development plan turned out to be under their jurisdiction, bringing the total to 13 manholes: 6 manholes under Cluster 1 and 7 manholes under Cluster 4. Most of these manholes are located along the national road. The Brgy. Captain initially quoted a fee of ₱3,000 per manhole due to their new Revenue Code. However, I was able to negotiate the fee down to ₱2,000 per manhole. The total fee for all 13 manholes is ₱26,000, with ₱12,000 for Cluster 1 and ₱14,000 for Cluster 4. OCT 22 Brgy Catmon, Malolos Bulacan Contact name: Rose Garcia contact number: 0975689336 Designation: Chief of staff Validity of Permit - Permit fee - for verification Remarks:/Report: waiting for kap. Brgy Catmon, Malolos Bulacan Contact name: Rose Garcia contact number: 0975689336 Designation: Chief of staff Validity of Permit - Permit fee - for verification Remarks:/Report: waiting for kap. 20-Oct-26Brgy San Agustin, Malolos Bulacan Contact name: Sec Joselyn Mendoza contact number: 09615619354 Designation: Brgy Secretary Validity of Permit - until the end of the year Permit fee - 500 Remarks:/Report: As per the barangay personnel, the permit fee is 500 pesos. They only request that proper precautions be taken and that the holes not be dug all at once to avoid traffic congestion. Brgy: 2/7 LGU Traffic DPWH 19-Oct-26 Brgy Liang, Malolos Bulacan Contact name: Sec. June Dacullo contact number: 7943589 Designation: Brgy Sec Validity of Permit - 6 months Permit fee - 300 Remarks:/Report: Permit Secured Brgy - 1/ LGU - 0/1 TRAFFIC - 0/1 DPWH - Thank you 16-Oct-26 Brgy Liang, Malolos Bulacan Contact name: Sec. June Dacullo contact number: 7943589 Designation: Brgy Sec Validity of Permit - Permit fee - Remarks:/Report: The Secretary advised me to return on Monday since Kap was not available to sign the permit. The work clearance fee is ₱300 only. Brgy - LGU - 0/1 TRAFFIC - 0/1 DPWH - " | BR34: =IFERROR((COUNT(BD34)*40%)+(COUNT(BL34)*20%)+(COUNT(BH34)*10%)+(COUNT(BP34)*10%)+(COUNT(AV34)*10%)+(COUNT(AZ34)*10%),0) -> 0.4 | BS34: =IF(BT34>0,WEEKNUM(BT34,1)&"-"&YEAR(BT34),"") -> 48-2026 | BT34: =AP34+3 -> 46352 | BU34: =IF(BV34>0,WEEKNUM(BV34,1)&"-"&YEAR(BV34),"") -> 48-2026 | BV34: 46350 | BW34: =IF(BX34>0,WEEKNUM(BX34,1)&"-"&YEAR(BX34),"") -> 49-2026 | BX34: =IF(CA34="",BV34+CD34,CA34+CD34) -> 46359.424 | BY34: 46368 | CB34: =IF(AI34<>0,CC34*0.25,0) -> 0.5 | CC34: 2 | CD34: =IF(R34=0,IFERROR(Q34/(CC34)/1.25,0),IFERROR(R34/(CC34)/1.25,0)) -> 9.424 | CH34: =IF(CA34="","NOT STARTED",IF(CA34<>"","ON GOING EXTRACTION",IF(CV34<>"","EXTRACTION COMPLETED"))) -> NOT STARTED | CI34: =IFERROR(CQ34/CM34,0) -> 0 | CM34: =AG34 -> 85 | CN34: =AI34 -> 65 | CR34: =CM34-CQ34 -> 85 | CU34: =CS34+CT34 -> 0
A35: 46327 | B35: RFE | C35: PART OF 233 | D35: GMM | E35: 14.529946 | F35: 121.15113 | G35: Angono | H35: Rizal | I35: CTAABMT | J35: Jessa | K35: Q1 | L35: T-37262327I-1-GMM-00007 | M35: IRUP0032 | N35: Angono Exchange | O35: Exchange-S | P35: =IF(OR(NOT(ISNUMBER(Q35)),Q35=0),"NO DATA",IF(Q35<10,"<10 TONNES",">=10 TONNES")) -> >=10 TONNES | Q35: 23.8 | R35: 18.31 | S35: =IF(CH35="CANCELLED","CANCELLED",IF(CV35<>"","EXTRACTION DONE",IF(CH35="ON GOING EXTRACTION","ON GOING EXTRACTION",IF(AR35="RFE","READY FOR EXTRACTION",IF(AR35="ON GOING PERMITTING","ON GOING PERMITTING",IF(AC35<>"","DESIGN APPROVED",IF(AB35<>"","DESIGN SUBMITTED",IF(AA35<>"","DESIGN COMPLETED",IF(Z35<>"","ON GOING DESIGN",IF(Y35<>"","ON GOING SURVEY","NOT STARTED")))))))))) -> ON GOING PERMITTING | T35: =IFERROR((AN35*33%)+(BR35*27%)+(CI35*40%),0) -> 0.438 | U35: =IF(V35>0,WEEKNUM(V35,1)&"-"&YEAR(V35),"") -> 42-2026 | V35: 46307 | W35: =V35 -> 46307 | X35: =IF(AD35>0,"DESIGN WITH CONCERN",IF(AC35>0,"DESIGN APPROVED",IF(AB35>0,"DESIGN FOR APPROVAL",IF(AA35>0,"DESIGN FOR SUBMISSION",IF(Z35>0,"ON GOING DESIGN",IF(Y35>0,"ON GOING SURVEY","FOR SURVEY")))))) -> DESIGN APPROVED | Y35: 46293 | Z35: 46295 | AA35: 46304 | AB35: 46305 | AC35: 46309 | AE35: Both | AF35: =IF(AA35-Y35<0,0,AA35-Y35) -> 11 | AG35: =AH35+AI35 -> 83 | AH35: 18 | AI35: 65 | AJ35: 48 | AK35: 17 | AL35: 0 | AN35: =COUNT(Y35:AC35)/5 -> 1 | AO35: =IF(AQ35>0,WEEKNUM(AQ35,1)&"-"&YEAR(AQ35),"") -> 47-2026 | AP35: 46343 | AQ35: 46346 | AR35: =IF(AA35="","WAITING FOR PLAN",IF(AU35="","PERMITTING NOT STARTED",IF(BR35>=100%,"RFE","ON GOING PERMITTING"))) -> ON GOING PERMITTING | AS35: NA | AT35: NA | AU35: 46316 | AV35: 46316 | AW35: NA | AX35: NA | AY35: 46316 | AZ35: 46316 | BA35: 1 | BB35: 11 | BC35: 46307 | BG35: 46296 | BI35: 1 | BJ35: 1 | BK35: 46324 | BL35: 46324 | BM35: 1 | BO35: 46308 | BQ35: Oct 22 Brgy kalayaan Brgy Sec : Loudes Monteloyola -0935-183-6173 OR/AR : OR Permit fee : 2,000 Working hrs : 10pm to 4am Remarks : Done meeting with the brgy officials , they want to give them the timeline of works , issuance of permits will be on tomorrow for release and pick up . 19-Oct-26 Brgy San Isidro Brgy Sec : Jamela Bengania -0962-8183-718 OR/AR : Permit fee : Working hrs : Remarks : as per talk to brgy Captain calberon he wants/demand to attend PLDT itself to discuss the unfinished issues before .regarding ftth,fttb,cabinet,rta. reschedule of meeting on Wednesday Oct 21 @1pm . 15-Oct-26 Brgy kalayaan Brgy Sec : Loudes Monteloyola -0935-183-6173 OR/AR : Permit fee : Working hrs : Remarks : as per brgy Sec . Our proposed loi discuss on Monday for Brgy session. 14-Oct-26 (Brgy San Roque Brgy Staff : Stephanie Cabusi -0915-5172-1892 OR/AR : Permit fee : Working hrs : Remarks : as per brgy staff be back tomorrow due to brgy sec and brgy Captain is on emergency meeting .) Brgy Muzon Brgy admin : cherry Mendoza -0929-1635-162 OR/AR : AR Permit fee : 3,000.00 (3,060.00) including charge for cash out Working hrs : 10pm to 4am. 13-Oct-26 Dpwh MH : for Binangonan 21MH, for Angono 68MH. Remarks : sop asking for 50K tried to negotiate meet half way 25K . Engineer Isha insists amouting 30K for both municipality. Angono and Binangonan. - we have revision of plan if we can mark the MH along the national road already discussed this to design team to make the revision . 12-Oct-26 Brgy Pag -Asa Contact name : Sarah Cayetano Designation : Admin Contact number: 0975-1627-1927 Validity : 1 month AR/OR : 0R Permit Fee: Php : 4,000 Working hrs : 10pm to 4am - 1 -Php 1,000 per MH" | BR35: =IFERROR((COUNT(BD35)*40%)+(COUNT(BL35)*20%)+(COUNT(BH35)*10%)+(COUNT(BP35)*10%)+(COUNT(AV35)*10%)+(COUNT(AZ35)*10%),0) -> 0.4 | BS35: =IF(BT35>0,WEEKNUM(BT35,1)&"-"&YEAR(BT35),"") -> 47-2026 | BT35: =AP35+3 -> 46346 | BU35: =IF(BV35>0,WEEKNUM(BV35,1)&"-"&YEAR(BV35),"") -> 48-2026 | BV35: 46351 | BW35: =IF(BX35>0,WEEKNUM(BX35,1)&"-"&YEAR(BX35),"") -> 49-2026 | BX35: =IF(CA35="",BV35+CD35,CA35+CD35) -> 46358.324 | BY35: =IF(CA35="",BV35+CD35,CA35+CD35) -> 46358.324 | CB35: =IF(AI35<>0,CC35*0.25,0) -> 0.5 | CC35: 2 | CD35: =IF(R35=0,IFERROR(Q35/(CC35)/1.25,0),IFERROR(R35/(CC35)/1.25,0)) -> 7.324 | CG35: Jed, Mark, Ron, Adrian, Jerome, Naj, Alain | CH35: =IF(CA35="","NOT STARTED",IF(CA35<>"","ON GOING EXTRACTION",IF(CV35<>"","EXTRACTION COMPLETED"))) -> NOT STARTED | CI35: =IFERROR(CQ35/CM35,0) -> 0 | CM35: =AG35 -> 83 | CN35: =AI35 -> 65 | CR35: =CM35-CQ35 -> 83 | CU35: =CS35+CT35 -> 0
A36: 46327 | B36: RFE | C36: PART OF 233 | D36: GMM | E36: 14.478468 | F36: 121.1883 | G36: Binangonan | H36: Rizal | I36: CTAABMT | J36: Jessa | K36: Q1 | L36: T-37262327I-1-GMM-00006 | M36: IRUP0033 | N36: Binangonan RSU Exchange | O36: Exchange-S | P36: =IF(OR(NOT(ISNUMBER(Q36)),Q36=0),"NO DATA",IF(Q36<10,"<10 TONNES",">=10 TONNES")) -> >=10 TONNES | Q36: 24.5 | R36: 7.8 | S36: =IF(CH36="CANCELLED","CANCELLED",IF(CV36<>"","EXTRACTION DONE",IF(CH36="ON GOING EXTRACTION","ON GOING EXTRACTION",IF(AR36="RFE","READY FOR EXTRACTION",IF(AR36="ON GOING PERMITTING","ON GOING PERMITTING",IF(AC36<>"","DESIGN APPROVED",IF(AB36<>"","DESIGN SUBMITTED",IF(AA36<>"","DESIGN COMPLETED",IF(Z36<>"","ON GOING DESIGN",IF(Y36<>"","ON GOING SURVEY","NOT STARTED")))))))))) -> ON GOING PERMITTING | T36: =IFERROR((AN36*33%)+(BR36*27%)+(CI36*40%),0) -> 0.48 | U36: =IF(V36>0,WEEKNUM(V36,1)&"-"&YEAR(V36),"") -> 40-2026 | V36: 46298 | W36: =V36 -> 46298 | X36: =IF(AD36>0,"DESIGN WITH CONCERN",IF(AC36>0,"DESIGN APPROVED",IF(AB36>0,"DESIGN FOR APPROVAL",IF(AA36>0,"DESIGN FOR SUBMISSION",IF(Z36>0,"ON GOING DESIGN",IF(Y36>0,"ON GOING SURVEY","FOR SURVEY")))))) -> DESIGN FOR APPROVAL | Y36: 46290 | Z36: 46291 | AA36: 46295 | AB36: 46322 | AE36: Both | AF36: =IF(AA36-Y36<0,0,AA36-Y36) -> 5 | AG36: =AH36+AI36 -> 23 | AH36: 4 | AI36: 19 | AJ36: 19 | AN36: =COUNT(Y36:AC36)/5 -> 0.8 | AO36: =IF(AQ36>0,WEEKNUM(AQ36,1)&"-"&YEAR(AQ36),"") -> 45-2026 | AP36: 46341 | AQ36: 46332 | AR36: =IF(AA36="","WAITING FOR PLAN",IF(AU36="","PERMITTING NOT STARTED",IF(BR36>=100%,"RFE","ON GOING PERMITTING"))) -> ON GOING PERMITTING | AS36: NA | AT36: NA | AU36: 46316 | AV36: 46316 | AW36: NA | AX36: NA | AY36: 46316 | AZ36: 46316 | BA36: 5 | BB36: 5 | BC36: 46300 | BD36: 46305 | BE36: 1 | BG36: 46296 | BI36: 1 | BJ36: 1 | BK36: 46324 | BL36: 46324 | BM36: 1 | BO36: 46308 | BQ36: 13-Oct-26 Dpwh MH : for Binangonan 21MH, for Angono 68MH. Remarks : sop asking for 50K tried to negotiate meet half way 25K . Engineer Isha insists amouting 30K for both municipality. Angono and Binangonan. - we have revision of plan if we can mark the MH along the national road already discussed this to design team to make the revision . 12-Oct-26 Binangonan dpwh - as per eng. Isaiah schedule of survey tomorrow 1:30pm. together with PS technical team. fyr mam @⁨Nena Feliciano⁩ requesting service tomorrow . po 8-Oct-26 Binangonan LGU. - as per LGU need to secured first the DPWH . - secured the Requirements. 5-Oct-26 Brgy Bilibiran c1 MH028, 026,030. Brgy chairman : Leonardo Mateo 0961-6152-2382 BC - Validity for 1month working hrs : 10pm to 4am fee : 1,500 /AR | BR36: =IFERROR((COUNT(BD36)*40%)+(COUNT(BL36)*20%)+(COUNT(BH36)*10%)+(COUNT(BP36)*10%)+(COUNT(AV36)*10%)+(COUNT(AZ36)*10%),0) -> 0.8 | BS36: =IF(BT36>0,WEEKNUM(BT36,1)&"-"&YEAR(BT36),"") -> 47-2026 | BT36: =AP36+3 -> 46344 | BU36: =IF(BV36>0,WEEKNUM(BV36,1)&"-"&YEAR(BV36),"") -> 46-2026 | BV36: 46337 | BW36: =IF(BX36>0,WEEKNUM(BX36,1)&"-"&YEAR(BX36),"") -> 46-2026 | BX36: =IF(CA36="",BV36+CD36,CA36+CD36) -> 46340.12 | BY36: =IF(CA36="",BV36+CD36,CA36+CD36) -> 46340.12 | CB36: =IF(AI36<>0,CC36*0.25,0) -> 0.5 | CC36: 2 | CD36: =IF(R36=0,IFERROR(Q36/(CC36)/1.25,0),IFERROR(R36/(CC36)/1.25,0)) -> 3.12 | CG36: Jed, Mark, Ron, Adrian, Jerome, Naj, Alain | CH36: =IF(CA36="","NOT STARTED",IF(CA36<>"","ON GOING EXTRACTION",IF(CV36<>"","EXTRACTION COMPLETED"))) -> NOT STARTED | CI36: =IFERROR(CQ36/CM36,0) -> 0 | CM36: =AG36 -> 23 | CN36: =AI36 -> 19 | CR36: =CM36-CQ36 -> 23 | CU36: =CS36+CT36 -> 0
A37: 46327 | B37: RFE | C37: PART OF 233 | D37: NLZ | G37: Ilagan City | H37: Isabela | I37: Cagayan | K37: Q2 | M37: IRUP0034 | N37: Ilagan Sub Exchange | O37: Exchange-M | P37: =IF(OR(NOT(ISNUMBER(Q37)),Q37=0),"NO DATA",IF(Q37<10,"<10 TONNES",">=10 TONNES")) -> >=10 TONNES | Q37: 31.5 | S37: =IF(CH37="CANCELLED","CANCELLED",IF(CV37<>"","EXTRACTION DONE",IF(CH37="ON GOING EXTRACTION","ON GOING EXTRACTION",IF(AR37="RFE","READY FOR EXTRACTION",IF(AR37="ON GOING PERMITTING","ON GOING PERMITTING",IF(AC37<>"","DESIGN APPROVED",IF(AB37<>"","DESIGN SUBMITTED",IF(AA37<>"","DESIGN COMPLETED",IF(Z37<>"","ON GOING DESIGN",IF(Y37<>"","ON GOING SURVEY","NOT STARTED")))))))))) -> ON GOING SURVEY | T37: =IFERROR((AN37*33%)+(BR37*27%)+(CI37*40%),0) -> 0.066 | U37: =IF(V37>0,WEEKNUM(V37,1)&"-"&YEAR(V37),"") | W37: =V37 -> 0 | X37: =IF(AD37>0,"DESIGN WITH CONCERN",IF(AC37>0,"DESIGN APPROVED",IF(AB37>0,"DESIGN FOR APPROVAL",IF(AA37>0,"DESIGN FOR SUBMISSION",IF(Z37>0,"ON GOING DESIGN",IF(Y37>0,"ON GOING SURVEY","FOR SURVEY")))))) -> ON GOING SURVEY | Y37: 46293 | AE37: ISP only | AF37: =IF(AA37-Y37<0,0,AA37-Y37) -> 0 | AG37: =AH37+AI37 -> 0 | AN37: =COUNT(Y37:AC37)/5 -> 0.2 | AO37: =IF(AQ37>0,WEEKNUM(AQ37,1)&"-"&YEAR(AQ37),"") | AP37: 46371 | AQ37: 0 | AR37: =IF(AA37="","WAITING FOR PLAN",IF(AU37="","PERMITTING NOT STARTED",IF(BR37>=100%,"RFE","ON GOING PERMITTING"))) -> WAITING FOR PLAN | BR37: =IFERROR((COUNT(BD37)*40%)+(COUNT(BL37)*20%)+(COUNT(BH37)*10%)+(COUNT(BP37)*10%)+(COUNT(AV37)*10%)+(COUNT(AZ37)*10%),0) -> 0 | BS37: =IF(BT37>0,WEEKNUM(BT37,1)&"-"&YEAR(BT37),"") | BU37: =IF(BV37>0,WEEKNUM(BV37,1)&"-"&YEAR(BV37),"") | BW37: =IF(BX37>0,WEEKNUM(BX37,1)&"-"&YEAR(BX37),"") -> 2-1900 | BX37: =IF(CA37="",BV37+CD37,CA37+CD37) -> 12.6 | CB37: =IF(AI37<>0,CC37*0.25,0) -> 0 | CC37: 2 | CD37: =IF(R37=0,IFERROR(Q37/(CC37)/1.25,0),IFERROR(R37/(CC37)/1.25,0)) -> 12.6 | CH37: =IF(CA37="","NOT STARTED",IF(CA37<>"","ON GOING EXTRACTION",IF(CV37<>"","EXTRACTION COMPLETED"))) -> NOT STARTED | CI37: =IFERROR(CQ37/CM37,0) -> 0 | CM37: =AG37 -> 0 | CN37: =AI37 -> 0 | CR37: =CM37-CQ37 -> 0 | CU37: =CS37+CT37 -> 0
A38: 46327 | B38: RFE | C38: PART OF 233 | D38: NLZ | E38: 14.913841 | F38: 120.56745 | G38: Lubao | H38: Pampanga | I38: PamBatZam | J38: Limwell | K38: Q1 | M38: IRUP0035 | N38: Lubao Sub-Exchange | O38: Exchange-M | P38: =IF(OR(NOT(ISNUMBER(Q38)),Q38=0),"NO DATA",IF(Q38<10,"<10 TONNES",">=10 TONNES")) -> >=10 TONNES | Q38: 29.4 | S38: =IF(CH38="CANCELLED","CANCELLED",IF(CV38<>"","EXTRACTION DONE",IF(CH38="ON GOING EXTRACTION","ON GOING EXTRACTION",IF(AR38="RFE","READY FOR EXTRACTION",IF(AR38="ON GOING PERMITTING","ON GOING PERMITTING",IF(AC38<>"","DESIGN APPROVED",IF(AB38<>"","DESIGN SUBMITTED",IF(AA38<>"","DESIGN COMPLETED",IF(Z38<>"","ON GOING DESIGN",IF(Y38<>"","ON GOING SURVEY","NOT STARTED")))))))))) -> ON GOING PERMITTING | T38: =IFERROR((AN38*33%)+(BR38*27%)+(CI38*40%),0) -> 0.372 | U38: =IF(V38>0,WEEKNUM(V38,1)&"-"&YEAR(V38),"") -> 42-2026 | V38: 46312 | W38: =V38 -> 46312 | X38: =IF(AD38>0,"DESIGN WITH CONCERN",IF(AC38>0,"DESIGN APPROVED",IF(AB38>0,"DESIGN FOR APPROVAL",IF(AA38>0,"DESIGN FOR SUBMISSION",IF(Z38>0,"ON GOING DESIGN",IF(Y38>0,"ON GOING SURVEY","FOR SURVEY")))))) -> DESIGN FOR APPROVAL | Y38: 46311 | Z38: 46311 | AA38: 46314 | AB38: 46322 | AE38: Both | AF38: =IF(AA38-Y38<0,0,AA38-Y38) -> 3 | AG38: =AH38+AI38 -> 26 | AH38: 11 | AI38: 15 | AK38: 15 | AN38: =COUNT(Y38:AC38)/5 -> 0.8 | AO38: =IF(AQ38>0,WEEKNUM(AQ38,1)&"-"&YEAR(AQ38),"") -> 47-2026 | AP38: 46356 | AQ38: 46346 | AR38: =IF(AA38="","WAITING FOR PLAN",IF(AU38="","PERMITTING NOT STARTED",IF(BR38>=100%,"RFE","ON GOING PERMITTING"))) -> ON GOING PERMITTING | AS38: NA | AT38: NA | AU38: 46317 | AV38: 46317 | AW38: NA | AX38: NA | AY38: 46317 | AZ38: 46317 | BA38: 2 | BB38: 3 | BC38: 46317 | BE38: 1 | BI38: 1 | BJ38: 1 | BK38: 46324 | BL38: 46324 | BQ38: Oct 23 CLUSTER 1 OF LUBAO SUB EXCHANGE CONTACT PERSON: RITA LAXAMANA CONTACT NUMBER: 09560593792 DESIGNATION: ADMIN AIDE VI DPWH- According to Ma’am Rita, we need to submit an LOI addressed to their District Engineer, Engr. Magelan V. Arcega. The LOI must specify the location of our project, and the signed plan must also be attached. Oct 23 BRGY. SANTA CRUZ- Permit fee: 500 OR Validity: 3months Remarks: No cashier today OCT 22 SAN AGUSTIN CONTACT PERSON: Mario P. Garcia CONTACT NUMBER:09266935767 DESIGNATION:Brgy. Captain VALIDITY OF PERMIT: AMOUNT: OR/AR: TIME OF WOR: REMARKS: According to him, there is no fee for the permit. However, he advised me to return on Monday because his secretary, who will prepare the permit, is currently unavailable and will only be back at work on Monday. BRGY.-0/5 LGU-0/1 DPWH-0/1 | BR38: =IFERROR((COUNT(BD38)*40%)+(COUNT(BL38)*20%)+(COUNT(BH38)*10%)+(COUNT(BP38)*10%)+(COUNT(AV38)*10%)+(COUNT(AZ38)*10%),0) -> 0.4 | BS38: =IF(BT38>0,WEEKNUM(BT38,1)&"-"&YEAR(BT38),"") -> 49-2026 | BT38: =AP38+3 -> 46359 | BU38: =IF(BV38>0,WEEKNUM(BV38,1)&"-"&YEAR(BV38),"") -> 49-2026 | BV38: 46359 | BW38: =IF(BX38>0,WEEKNUM(BX38,1)&"-"&YEAR(BX38),"") -> 51-2026 | BX38: =IF(CA38="",BV38+CD38,CA38+CD38) -> 46370.76 | BY38: 46371 | CB38: =IF(AI38<>0,CC38*0.25,0) -> 0.5 | CC38: 2 | CD38: =IF(R38=0,IFERROR(Q38/(CC38)/1.25,0),IFERROR(R38/(CC38)/1.25,0)) -> 11.76 | CH38: =IF(CA38="","NOT STARTED",IF(CA38<>"","ON GOING EXTRACTION",IF(CV38<>"","EXTRACTION COMPLETED"))) -> NOT STARTED | CI38: =IFERROR(CQ38/CM38,0) -> 0 | CM38: =AG38 -> 26 | CN38: =AI38 -> 15 | CR38: =CM38-CQ38 -> 26 | CU38: =CS38+CT38 -> 0
A39: 46419 | B39: RFE | C39: ADDITIONAL | D39: GMM | E39: 14.5907 | F39: 121.1139 | G39: Cainta | H39: Rizal | I39: CTAABMT | J39: Jessa | K39: Q1 | M39: IRUP0036 | N39: Digitel Cainta MSU | O39: Exchange-M | P39: =IF(OR(NOT(ISNUMBER(Q39)),Q39=0),"NO DATA",IF(Q39<10,"<10 TONNES",">=10 TONNES")) -> NO DATA | Q39: 0 | R39: 23.42 | S39: =IF(CH39="CANCELLED","CANCELLED",IF(CV39<>"","EXTRACTION DONE",IF(CH39="ON GOING EXTRACTION","ON GOING EXTRACTION",IF(AR39="RFE","READY FOR EXTRACTION",IF(AR39="ON GOING PERMITTING","ON GOING PERMITTING",IF(AC39<>"","DESIGN APPROVED",IF(AB39<>"","DESIGN SUBMITTED",IF(AA39<>"","DESIGN COMPLETED",IF(Z39<>"","ON GOING DESIGN",IF(Y39<>"","ON GOING SURVEY","NOT STARTED")))))))))) -> ON GOING PERMITTING | T39: =IFERROR((AN39*33%)+(BR39*27%)+(CI39*40%),0) -> 0.357 | U39: =IF(V39>0,WEEKNUM(V39,1)&"-"&YEAR(V39),"") -> 44-2026 | V39: 46320 | W39: =V39 -> 46320 | X39: =IF(AD39>0,"DESIGN WITH CONCERN",IF(AC39>0,"DESIGN APPROVED",IF(AB39>0,"DESIGN FOR APPROVAL",IF(AA39>0,"DESIGN FOR SUBMISSION",IF(Z39>0,"ON GOING DESIGN",IF(Y39>0,"ON GOING SURVEY","FOR SURVEY")))))) -> DESIGN APPROVED | Y39: 46295 | Z39: 46296 | AA39: 46298 | AB39: 46303 | AC39: 46309 | AE39: Both | AF39: =IF(AA39-Y39<0,0,AA39-Y39) -> 3 | AG39: =AH39+AI39 -> 29 | AH39: 11 | AI39: 18 | AJ39: 16 | AK39: 2 | AL39: 0 | AN39: =COUNT(Y39:AC39)/5 -> 1 | AO39: =IF(AQ39>0,WEEKNUM(AQ39,1)&"-"&YEAR(AQ39),"") -> 46-2026 | AP39: 46356 | AQ39: 46340 | AR39: =IF(AA39="","WAITING FOR PLAN",IF(AU39="","PERMITTING NOT STARTED",IF(BR39>=100%,"RFE","ON GOING PERMITTING"))) -> ON GOING PERMITTING | AS39: 2 | AU39: 46310 | AW39: NA | AX39: NA | AY39: 46316 | AZ39: 46316 | BA39: 1 | BB39: 1 | BC39: 46302 | BQ39: 20-Oct-26 Vista Verde Hoa Contact Name: Mike Villaya Remarks: For Submission of LOI Waiting for Sir Mike | BR39: =IFERROR((COUNT(BD39)*40%)+(COUNT(BL39)*20%)+(COUNT(BH39)*10%)+(COUNT(BP39)*10%)+(COUNT(AV39)*10%)+(COUNT(AZ39)*10%),0) -> 0.1 | BS39: =IF(BT39>0,WEEKNUM(BT39,1)&"-"&YEAR(BT39),"") -> 49-2026 | BT39: =AP39+3 -> 46359 | BU39: =IF(BV39>0,WEEKNUM(BV39,1)&"-"&YEAR(BV39),"") -> 47-2026 | BV39: 46344 | BW39: =IF(BX39>0,WEEKNUM(BX39,1)&"-"&YEAR(BX39),"") -> 48-2026 | BX39: =IF(CA39="",BV39+CD39,CA39+CD39) -> 46353.368 | BY39: =IF(CA39="",BV39+CD39,CA39+CD39) -> 46353.368 | CB39: =IF(AI39<>0,CC39*0.25,0) -> 0.5 | CC39: 2 | CD39: =IF(R39=0,IFERROR(Q39/(CC39)/1.25,0),IFERROR(R39/(CC39)/1.25,0)) -> 9.368 | CG39: Jed, Mark, Ron, Adrian, Jerome, Naj, Alain | CH39: =IF(CA39="","NOT STARTED",IF(CA39<>"","ON GOING EXTRACTION",IF(CV39<>"","EXTRACTION COMPLETED"))) -> NOT STARTED | CI39: =IFERROR(CQ39/CM39,0) -> 0 | CJ39: 10/6/26: Cainta MSU will be continue as part of our Q1 in replacement of Vigan due to no copper cable confirmed by PLDT and Accenture. | CM39: =AG39 -> 29 | CN39: =AI39 -> 18 | CR39: =CM39-CQ39 -> 29 | CU39: =CS39+CT39 -> 0
A40: 46235 | B40: RFE | C40: PART OF 233 | D40: NLZ | E40: 15.143814 | F40: 120.97423 | G40: San Miguel | H40: Bulacan | I40: Bulacan | J40: Limwell | K40: Q1 | L40: T-37262327I-1-NLZ-00007 | M40: IRUP0037 | N40: San Miguel Sub-Exchange | O40: Exchange-S | P40: =IF(OR(NOT(ISNUMBER(Q40)),Q40=0),"NO DATA",IF(Q40<10,"<10 TONNES",">=10 TONNES")) -> >=10 TONNES | Q40: 25.1 | R40: 7.82 | S40: =IF(CH40="CANCELLED","CANCELLED",IF(CV40<>"","EXTRACTION DONE",IF(CH40="ON GOING EXTRACTION","ON GOING EXTRACTION",IF(AR40="RFE","READY FOR EXTRACTION",IF(AR40="ON GOING PERMITTING","ON GOING PERMITTING",IF(AC40<>"","DESIGN APPROVED",IF(AB40<>"","DESIGN SUBMITTED",IF(AA40<>"","DESIGN COMPLETED",IF(Z40<>"","ON GOING DESIGN",IF(Y40<>"","ON GOING SURVEY","NOT STARTED")))))))))) -> ON GOING PERMITTING | T40: =IFERROR((AN40*33%)+(BR40*27%)+(CI40*40%),0) -> 0.384 | U40: =IF(V40>0,WEEKNUM(V40,1)&"-"&YEAR(V40),"") -> 41-2026 | V40: 46304 | W40: =V40 -> 46304 | X40: =IF(AD40>0,"DESIGN WITH CONCERN",IF(AC40>0,"DESIGN APPROVED",IF(AB40>0,"DESIGN FOR APPROVAL",IF(AA40>0,"DESIGN FOR SUBMISSION",IF(Z40>0,"ON GOING DESIGN",IF(Y40>0,"ON GOING SURVEY","FOR SURVEY")))))) -> DESIGN APPROVED | Y40: 46297 | Z40: 46297 | AA40: 46298 | AB40: 46300 | AC40: 46300 | AE40: Both | AF40: =IF(AA40-Y40<0,0,AA40-Y40) -> 1 | AG40: =AH40+AI40 -> 31 | AH40: 21 | AI40: 10 | AJ40: 0 | AK40: 10 | AL40: 0 | AN40: =COUNT(Y40:AC40)/5 -> 1 | AO40: =IF(AQ40>0,WEEKNUM(AQ40,1)&"-"&YEAR(AQ40),"") -> 46-2026 | AP40: 46340 | AQ40: 46334 | AR40: =IF(AA40="","WAITING FOR PLAN",IF(AU40="","PERMITTING NOT STARTED",IF(BR40>=100%,"RFE","ON GOING PERMITTING"))) -> ON GOING PERMITTING | AS40: NA | AT40: NA | AU40: 46316 | AV40: 46316 | AW40: NA | AX40: NA | AY40: 46316 | AZ40: 46316 | BA40: 3 | BB40: 9 | BC40: 46303 | BE40: 1 | BG40: 46310 | BQ40: 15-Oct-26 LGU of San Miguel Bulacan Contact name: Ryan Ausan contact number: 09152597828 Validity of Permit - Permit fee - Remarks:/Report: As per the Engineering Office of San Miguel, Bulacan, they will first verify if excavation permits for all manholes have been secured before. If permits have already been secured, there will be no need to apply for new ones. They will provide an update by tomorrow after completing the verification. They also advised us to prioritize securing the DPWH permit since all our manholes are located along national roads. Brgy - 11/11 LGU - 0/1 TRAFFIC - 0/1 DPWH - Thank you. 12-Oct-26 (Brgy Tigpalas San Miguel Bulacan Contact name: Sec Rhea De Leon contact number: 09473711343 Validity of Permit - until the end of the year Permit fee - Free Remarks:/Report: For Application of Brgy Clearance. BC secured. Brgy - 4/11 LGU - 0/1 TRAFFIC - 0/1 DPWH - ) Brgy Poblacion San Miguel Bulacan Contact name: contact number: Validity of Permit - Permit fee - Remarks:/Report: Upon confirmation with the barangay, the manhole along Cagayan Valley Road is not under their jurisdiction. Brgy - 2/11 LGU - 0/1 TRAFFIC - 0/1 DPWH - ----- 8-Oct-26 (Brgy Santa Rita Matanda, San Miguel Bulacan Contact name: Cap. Frederick Yambot contact number: 09666710193 Validity of Permit - until the end of the year Permit fee - Free Remarks:/Report: For application of Brgy Certificate. Brgy Clearance Secured. Brgy - 2/12 LGU - 0/1 TRAFFIC - 0/1 DPWH - Thank you Joy Chenryl Icang ) cluster 1 of San Miguel Sub Exchange Grantor: Brgy. San Vicente San Miguel Bulacan | BR40: =IFERROR((COUNT(BD40)*40%)+(COUNT(BL40)*20%)+(COUNT(BH40)*10%)+(COUNT(BP40)*10%)+(COUNT(AV40)*10%)+(COUNT(AZ40)*10%),0) -> 0.2 | BS40: =IF(BT40>0,WEEKNUM(BT40,1)&"-"&YEAR(BT40),"") -> 47-2026 | BT40: =AP40+3 -> 46343 | BU40: =IF(BV40>0,WEEKNUM(BV40,1)&"-"&YEAR(BV40),"") -> 48-2026 | BV40: 46349 | BW40: =IF(BX40>0,WEEKNUM(BX40,1)&"-"&YEAR(BX40),"") -> 48-2026 | BX40: =IF(CA40="",BV40+CD40,CA40+CD40) -> 46352.128 | BY40: 46361 | CB40: =IF(AI40<>0,CC40*0.25,0) -> 0.5 | CC40: 2 | CD40: =IF(R40=0,IFERROR(Q40/(CC40)/1.25,0),IFERROR(R40/(CC40)/1.25,0)) -> 3.128 | CH40: =IF(CA40="","NOT STARTED",IF(CA40<>"","ON GOING EXTRACTION",IF(CV40<>"","EXTRACTION COMPLETED"))) -> NOT STARTED | CI40: =IFERROR(CQ40/CM40,0) -> 0 | CM40: =AG40 -> 31 | CN40: =AI40 -> 10 | CR40: =CM40-CQ40 -> 31 | CU40: =CS40+CT40 -> 0
A41: 46327 | B41: RFE | C41: PART OF 233 | D41: GMM | E41: 14.578598 | F41: 121.13417 | G41: Taytay | H41: Rizal | I41: CTAABMT | J41: Jessa | K41: Q1 | L41: T-37262327I-1-GMM-00009 | M41: IRUP0038 | N41: Taytay CO | O41: Exchange-M | P41: =IF(OR(NOT(ISNUMBER(Q41)),Q41=0),"NO DATA",IF(Q41<10,"<10 TONNES",">=10 TONNES")) -> >=10 TONNES | Q41: 217.2 | R41: 118.8 | S41: =IF(CH41="CANCELLED","CANCELLED",IF(CV41<>"","EXTRACTION DONE",IF(CH41="ON GOING EXTRACTION","ON GOING EXTRACTION",IF(AR41="RFE","READY FOR EXTRACTION",IF(AR41="ON GOING PERMITTING","ON GOING PERMITTING",IF(AC41<>"","DESIGN APPROVED",IF(AB41<>"","DESIGN SUBMITTED",IF(AA41<>"","DESIGN COMPLETED",IF(Z41<>"","ON GOING DESIGN",IF(Y41<>"","ON GOING SURVEY","NOT STARTED")))))))))) -> ON GOING PERMITTING | T41: =IFERROR((AN41*33%)+(BR41*27%)+(CI41*40%),0) -> 0.438 | U41: =IF(V41>0,WEEKNUM(V41,1)&"-"&YEAR(V41),"") -> 41-2026 | V41: 46302 | W41: =V41 -> 46302 | X41: =IF(AD41>0,"DESIGN WITH CONCERN",IF(AC41>0,"DESIGN APPROVED",IF(AB41>0,"DESIGN FOR APPROVAL",IF(AA41>0,"DESIGN FOR SUBMISSION",IF(Z41>0,"ON GOING DESIGN",IF(Y41>0,"ON GOING SURVEY","FOR SURVEY")))))) -> DESIGN APPROVED | Y41: 46295 | Z41: 46295 | AA41: 46298 | AB41: 46301 | AC41: 46302 | AE41: Both | AF41: =IF(AA41-Y41<0,0,AA41-Y41) -> 3 | AG41: =AH41+AI41 -> 73 | AH41: 23 | AI41: 50 | AJ41: 39 | AK41: 11 | AL41: 0 | AN41: =COUNT(Y41:AC41)/5 -> 1 | AO41: =IF(AQ41>0,WEEKNUM(AQ41,1)&"-"&YEAR(AQ41),"") -> 47-2026 | AP41: 46338 | AQ41: 46346 | AR41: =IF(AA41="","WAITING FOR PLAN",IF(AU41="","PERMITTING NOT STARTED",IF(BR41>=100%,"RFE","ON GOING PERMITTING"))) -> ON GOING PERMITTING | AS41: NA | AT41: NA | AU41: 46316 | AV41: 46316 | AW41: 2 | AX41: NA | AY41: 46310 | AZ41: 46316 | BA41: 6 | BB41: 6 | BC41: 46303 | BE41: 1 | BG41: 46322 | BI41: 1 | BJ41: 1 | BK41: 46324 | BL41: 46324 | BQ41: Oct 23 Taytay Lgu. - For Submission of BOM and GANCHARTT to ask for an Advance assessment for us to acquire Order of payment, While waiting for the PLDT to address Lgu Taytay's Concerned as Discussed During Meeting Yesterday with Lgu Engineering office and PLDT. However Lgu Taytay is Closed Today as Per Engr. Verona. Note: .Permit application is on hold Unless PLDT will Provide immediate solution of Lgu Taytay's long time Concerned 15-Oct-26 Brgy. Dolores Follow up Application, Just waiting for Engr. Naval Of Brgy. Engineering and Planning office. 12-Oct-26 Brgy. San Juan - •Brgy.Dolore- MH No.: 053,054,362,064,067.,066 •Brgy.San Isidro- 500 per Manhole MH046,047,065,SB004,MH050,051,052, 063.SB005 Brgy. 0/3 Lgu 0/1 Dpwh 0/1 SN: Cluster 1 of Taytay RSU Grantor : •Brgy. San Juan- Brgy. Already closed. MH No.: 001,002,003,004,005-A,005-B All Manhole Overlayed. Brgy. 0/1 Lgu 0/1 DPWH 0/1. @Brgy. San Juan. Brgy. Engineering office. Office Head is not Available ( Sick/On leave) Engr. Guillermo Cruz. Advised to wait Engr. Erick to process Permit application. 8-Oct-26 Brgy. San Isidro Taytay- Waiting for the Head Officer of Brgy. Special Project office. Person In charge for Application of Brgy. Working Permit. Brgy. Chairwoman is not available ( Under suspension). First Manhole of Tanay PLDT CO is under Brgy. San Isidro. MH No.: (For Cluster 2.1 ) MH298,008,007,006,051,002,001,042,043,045,044,041,040,005,050,052,049,048, 047. (For Cluster 2.3) MH046,047,065,SB004,MH050,051,052, 063.SB005 | BR41: =IFERROR((COUNT(BD41)*40%)+(COUNT(BL41)*20%)+(COUNT(BH41)*10%)+(COUNT(BP41)*10%)+(COUNT(AV41)*10%)+(COUNT(AZ41)*10%),0) -> 0.4 | BS41: =IF(BT41>0,WEEKNUM(BT41,1)&"-"&YEAR(BT41),"") -> 47-2026 | BT41: =AP41+3 -> 46341 | BU41: =IF(BV41>0,WEEKNUM(BV41,1)&"-"&YEAR(BV41),"") -> 48-2026 | BV41: 46351 | BW41: =IF(BX41>0,WEEKNUM(BX41,1)&"-"&YEAR(BX41),"") -> 51-2026 | BX41: =IF(CA41="",BV41+CD41,CA41+CD41) -> 46374.76 | BY41: =IF(CA41="",BV41+CD41,CA41+CD41) -> 46374.76 | CB41: =IF(AI41<>0,CC41*0.25,0) -> 1 | CC41: 4 | CD41: =IF(R41=0,IFERROR(Q41/(CC41)/1.25,0),IFERROR(R41/(CC41)/1.25,0)) -> 23.76 | CG41: Jed, Mark, Ron, Adrian, Jerome, Naj, Alain | CH41: =IF(CA41="","NOT STARTED",IF(CA41<>"","ON GOING EXTRACTION",IF(CV41<>"","EXTRACTION COMPLETED"))) -> NOT STARTED | CI41: =IFERROR(CQ41/CM41,0) -> 0 | CJ41: 10/6/26: Once we have Subcon, this site is Priority for ISP extraction. | CM41: =AG41 -> 73 | CN41: =AI41 -> 50 | CR41: =CM41-CQ41 -> 73 | CU41: =CS41+CT41 -> 0
B42: RFE | C42: ADDITIONAL | D42: GMM | E42: 14.562343 | F42: 121.13781 | G42: Taytay | I42: CTAABMT | J42: Jessa | K42: Q1 | L42: T-37262327I-1-GMM-00011 | M42: IRUP0039 | N42: Taytay RSU | O42: Exchange-M | P42: =IF(OR(NOT(ISNUMBER(Q42)),Q42=0),"NO DATA",IF(Q42<10,"<10 TONNES",">=10 TONNES")) -> NO DATA | Q42: 0 | R42: 2.65 | S42: =IF(CH42="CANCELLED","CANCELLED",IF(CV42<>"","EXTRACTION DONE",IF(CH42="ON GOING EXTRACTION","ON GOING EXTRACTION",IF(AR42="RFE","READY FOR EXTRACTION",IF(AR42="ON GOING PERMITTING","ON GOING PERMITTING",IF(AC42<>"","DESIGN APPROVED",IF(AB42<>"","DESIGN SUBMITTED",IF(AA42<>"","DESIGN COMPLETED",IF(Z42<>"","ON GOING DESIGN",IF(Y42<>"","ON GOING SURVEY","NOT STARTED")))))))))) -> ON GOING PERMITTING | T42: =IFERROR((AN42*33%)+(BR42*27%)+(CI42*40%),0) -> 0.372 | U42: =IF(V42>0,WEEKNUM(V42,1)&"-"&YEAR(V42),"") -> 41-2026 | V42: 46300 | W42: =V42 -> 46300 | X42: =IF(AD42>0,"DESIGN WITH CONCERN",IF(AC42>0,"DESIGN APPROVED",IF(AB42>0,"DESIGN FOR APPROVAL",IF(AA42>0,"DESIGN FOR SUBMISSION",IF(Z42>0,"ON GOING DESIGN",IF(Y42>0,"ON GOING SURVEY","FOR SURVEY")))))) -> DESIGN FOR APPROVAL | Y42: 46301 | Z42: 46301 | AA42: 46302 | AB42: 46322 | AF42: =IF(AA42-Y42<0,0,AA42-Y42) -> 1 | AG42: =AH42+AI42 -> 6 | AI42: 6 | AJ42: 6 | AN42: =COUNT(Y42:AC42)/5 -> 0.8 | AO42: =IF(AQ42>0,WEEKNUM(AQ42,1)&"-"&YEAR(AQ42),"") -> 47-2026 | AP42: 46343 | AQ42: 46346 | AR42: =IF(AA42="","WAITING FOR PLAN",IF(AU42="","PERMITTING NOT STARTED",IF(BR42>=100%,"RFE","ON GOING PERMITTING"))) -> ON GOING PERMITTING | AS42: NA | AT42: NA | AU42: 46316 | AV42: 46316 | AW42: NA | AX42: NA | AY42: 46316 | AZ42: 46316 | BA42: 1 | BB42: 0 | BC42: 46307 | BE42: 1 | BG42: 46322 | BI42: 1 | BJ42: 1 | BK42: 46324 | BL42: 46324 | BQ42: Oct 23 Taytay Lgu. - For Submission of BOM and GANCHARTT to ask for an Advance assessment for us to acquire Order of payment, While waiting for the PLDT to address Lgu Taytay's Concerned as Discussed During Meeting Yesterday with Lgu Engineering office and PLDT. However Lgu Taytay is Closed Today as Per Engr. Verona. Note: .Permit application is on hold Unless PLDT will Provide immediate solution of Lgu Taytay's long time Concerned12-Oct-26 Brgy. San Juan TayTay. Secured Order of Payment for 2 sites. Negotiated Permit Fee From 1,500 each Manhole overlayed/for Excavation. To close the Deal at 5,500 for 2 sites. MH. 002 and MH 003 Of Cluster 2.3 overlayed are negotiated not to be charged and carried as is to Sites of Tatay RSU since it has similar Area/ St. | BR42: =IFERROR((COUNT(BD42)*40%)+(COUNT(BL42)*20%)+(COUNT(BH42)*10%)+(COUNT(BP42)*10%)+(COUNT(AV42)*10%)+(COUNT(AZ42)*10%),0) -> 0.4 | BS42: =IF(BT42>0,WEEKNUM(BT42,1)&"-"&YEAR(BT42),"") -> 47-2026 | BT42: =AP42+3 -> 46346 | BU42: =IF(BV42>0,WEEKNUM(BV42,1)&"-"&YEAR(BV42),"") -> 45-2026 | BV42: 46329 | BW42: =IF(BX42>0,WEEKNUM(BX42,1)&"-"&YEAR(BX42),"") -> 45-2026 | BX42: =IF(CA42="",BV42+CD42,CA42+CD42) -> 46330.06 | BY42: 46329 | BZ42: 10/29/26: ISP only; OSP will continue based on the Permit Secured; | CB42: =IF(AI42<>0,CC42*0.25,0) -> 0.5 | CC42: 2 | CD42: =IF(R42=0,IFERROR(Q42/(CC42)/1.25,0),IFERROR(R42/(CC42)/1.25,0)) -> 1.06 | CF42: ISP ONLY | CG42: Leny, Judy, Mark Sun, Raymark, Luis | CH42: =IF(CA42="","NOT STARTED",IF(CA42<>"","ON GOING EXTRACTION",IF(CV42<>"","EXTRACTION COMPLETED"))) -> NOT STARTED | CI42: =IFERROR(CQ42/CM42,0) -> 0 | CM42: =AG42 -> 6 | CN42: =AI42 -> 6 | CR42: =CM42-CQ42 -> 6 | CU42: =CS42+CT42 -> 0
A43: 46419 | B43: NY RFE | C43: PART OF 233 | D43: SLZ | E43: 14.354645 | F43: 121.0481 | G43: San Pedro | H43: Laguna | I43: Laguna | K43: NY RFE | M43: IRUP0040 | N43: San Pedro Exchange | O43: Exchange-M | P43: =IF(OR(NOT(ISNUMBER(Q43)),Q43=0),"NO DATA",IF(Q43<10,"<10 TONNES",">=10 TONNES")) -> >=10 TONNES | Q43: 275.7 | S43: =IF(CH43="CANCELLED","CANCELLED",IF(CV43<>"","EXTRACTION DONE",IF(CH43="ON GOING EXTRACTION","ON GOING EXTRACTION",IF(AR43="RFE","READY FOR EXTRACTION",IF(AR43="ON GOING PERMITTING","ON GOING PERMITTING",IF(AC43<>"","DESIGN APPROVED",IF(AB43<>"","DESIGN SUBMITTED",IF(AA43<>"","DESIGN COMPLETED",IF(Z43<>"","ON GOING DESIGN",IF(Y43<>"","ON GOING SURVEY","NOT STARTED")))))))))) -> DESIGN SUBMITTED | T43: =IFERROR((AN43*33%)+(BR43*27%)+(CI43*40%),0) -> 0.264 | X43: =IF(AD43>0,"DESIGN WITH CONCERN",IF(AC43>0,"DESIGN APPROVED",IF(AB43>0,"DESIGN FOR APPROVAL",IF(AA43>0,"DESIGN FOR SUBMISSION",IF(Z43>0,"ON GOING DESIGN",IF(Y43>0,"ON GOING SURVEY","FOR SURVEY")))))) -> DESIGN FOR APPROVAL | Y43: 46309 | Z43: 46312 | AA43: 46316 | AB43: 46323 | AF43: =IF(AA43-Y43<0,0,AA43-Y43) -> 7 | AG43: =AH43+AI43 -> 0 | AN43: =COUNT(Y43:AC43)/5 -> 0.8 | AO43: =IF(AQ43>0,WEEKNUM(AQ43,1)&"-"&YEAR(AQ43),"") | AR43: =IF(AA43="","WAITING FOR PLAN",IF(AU43="","PERMITTING NOT STARTED",IF(BR43>=100%,"RFE","ON GOING PERMITTING"))) -> PERMITTING NOT STARTED | BR43: =IFERROR((COUNT(BD43)*40%)+(COUNT(BL43)*20%)+(COUNT(BH43)*10%)+(COUNT(BP43)*10%)+(COUNT(AV43)*10%)+(COUNT(AZ43)*10%),0) -> 0 | BS43: =IF(BT43>0,WEEKNUM(BT43,1)&"-"&YEAR(BT43),"") | BU43: =IF(BV43>0,WEEKNUM(BV43,1)&"-"&YEAR(BV43),"") | BW43: =IF(BX43>0,WEEKNUM(BX43,1)&"-"&YEAR(BX43),"") -> 16-1900 | BX43: =IF(CA43="",BV43+CD43,CA43+CD43) -> 110.28 | CB43: =IF(AI43<>0,CC43*0.25,0) -> 0 | CC43: 2 | CD43: =IF(R43=0,IFERROR(Q43/(CC43)/1.25,0),IFERROR(R43/(CC43)/1.25,0)) -> 110.28 | CH43: =IF(CA43="","NOT STARTED",IF(CA43<>"","ON GOING EXTRACTION",IF(CV43<>"","EXTRACTION COMPLETED"))) -> NOT STARTED | CI43: =IFERROR(CQ43/CM43,0) -> 0 | CM43: =AG43 -> 0 | CN43: =AI43 -> 0 | CR43: =CM43-CQ43 -> 0 | CU43: =CS43+CT43 -> 0
A44: 46419 | B44: NY RFE | C44: PART OF 233 | D44: GMM | E44: 14.568427 | F44: 121.07106 | G44: Pasig City | H44: Metropolitan Manila | I44: Pasig-Pateros-Taguig | K44: NY RFE | M44: IRUP0041 | N44: Ugong Pasig CO & Service Yard | O44: Exchange-M | P44: =IF(OR(NOT(ISNUMBER(Q44)),Q44=0),"NO DATA",IF(Q44<10,"<10 TONNES",">=10 TONNES")) -> >=10 TONNES | Q44: 125 | S44: =IF(CH44="CANCELLED","CANCELLED",IF(CV44<>"","EXTRACTION DONE",IF(CH44="ON GOING EXTRACTION","ON GOING EXTRACTION",IF(AR44="RFE","READY FOR EXTRACTION",IF(AR44="ON GOING PERMITTING","ON GOING PERMITTING",IF(AC44<>"","DESIGN APPROVED",IF(AB44<>"","DESIGN SUBMITTED",IF(AA44<>"","DESIGN COMPLETED",IF(Z44<>"","ON GOING DESIGN",IF(Y44<>"","ON GOING SURVEY","NOT STARTED")))))))))) -> DESIGN COMPLETED | T44: =IFERROR((AN44*33%)+(BR44*27%)+(CI44*40%),0) -> 0.198 | X44: =IF(AD44>0,"DESIGN WITH CONCERN",IF(AC44>0,"DESIGN APPROVED",IF(AB44>0,"DESIGN FOR APPROVAL",IF(AA44>0,"DESIGN FOR SUBMISSION",IF(Z44>0,"ON GOING DESIGN",IF(Y44>0,"ON GOING SURVEY","FOR SURVEY")))))) -> DESIGN FOR SUBMISSION | Y44: 46308 | Z44: 46309 | AA44: 46316 | AF44: =IF(AA44-Y44<0,0,AA44-Y44) -> 8 | AG44: =AH44+AI44 -> 108 | AH44: 47 | AI44: 61 | AJ44: 48 | AK44: 13 | AN44: =COUNT(Y44:AC44)/5 -> 0.6 | AO44: =IF(AQ44>0,WEEKNUM(AQ44,1)&"-"&YEAR(AQ44),"") | AR44: =IF(AA44="","WAITING FOR PLAN",IF(AU44="","PERMITTING NOT STARTED",IF(BR44>=100%,"RFE","ON GOING PERMITTING"))) -> PERMITTING NOT STARTED | BR44: =IFERROR((COUNT(BD44)*40%)+(COUNT(BL44)*20%)+(COUNT(BH44)*10%)+(COUNT(BP44)*10%)+(COUNT(AV44)*10%)+(COUNT(AZ44)*10%),0) -> 0 | BS44: =IF(BT44>0,WEEKNUM(BT44,1)&"-"&YEAR(BT44),"") | BU44: =IF(BV44>0,WEEKNUM(BV44,1)&"-"&YEAR(BV44),"") | BW44: =IF(BX44>0,WEEKNUM(BX44,1)&"-"&YEAR(BX44),"") -> 8-1900 | BX44: =IF(CA44="",BV44+CD44,CA44+CD44) -> 50 | CB44: =IF(AI44<>0,CC44*0.25,0) -> 0.5 | CC44: 2 | CD44: =IF(R44=0,IFERROR(Q44/(CC44)/1.25,0),IFERROR(R44/(CC44)/1.25,0)) -> 50 | CH44: =IF(CA44="","NOT STARTED",IF(CA44<>"","ON GOING EXTRACTION",IF(CV44<>"","EXTRACTION COMPLETED"))) -> NOT STARTED | CI44: =IFERROR(CQ44/CM44,0) -> 0 | CM44: =AG44 -> 108 | CN44: =AI44 -> 61 | CR44: =CM44-CQ44 -> 108 | CU44: =CS44+CT44 -> 0
A45: 46419 | B45: NY RFE | C45: PART OF 233 | D45: GMM | E45: 14.587237 | F45: 121.16939 | G45: Antipolo City | H45: Rizal | I45: CTAABMT | K45: NY RFE | M45: IRUP0042 | N45: Antipolo Exchange | O45: Exchange-M | P45: =IF(OR(NOT(ISNUMBER(Q45)),Q45=0),"NO DATA",IF(Q45<10,"<10 TONNES",">=10 TONNES")) -> >=10 TONNES | Q45: 192.4 | S45: =IF(CH45="CANCELLED","CANCELLED",IF(CV45<>"","EXTRACTION DONE",IF(CH45="ON GOING EXTRACTION","ON GOING EXTRACTION",IF(AR45="RFE","READY FOR EXTRACTION",IF(AR45="ON GOING PERMITTING","ON GOING PERMITTING",IF(AC45<>"","DESIGN APPROVED",IF(AB45<>"","DESIGN SUBMITTED",IF(AA45<>"","DESIGN COMPLETED",IF(Z45<>"","ON GOING DESIGN",IF(Y45<>"","ON GOING SURVEY","NOT STARTED")))))))))) -> DESIGN COMPLETED | T45: =IFERROR((AN45*33%)+(BR45*27%)+(CI45*40%),0) -> 0.198 | X45: =IF(AD45>0,"DESIGN WITH CONCERN",IF(AC45>0,"DESIGN APPROVED",IF(AB45>0,"DESIGN FOR APPROVAL",IF(AA45>0,"DESIGN FOR SUBMISSION",IF(Z45>0,"ON GOING DESIGN",IF(Y45>0,"ON GOING SURVEY","FOR SURVEY")))))) -> DESIGN FOR SUBMISSION | Y45: 46314 | Z45: 46315 | AA45: 46322 | AF45: =IF(AA45-Y45<0,0,AA45-Y45) -> 8 | AG45: =AH45+AI45 -> 0 | AN45: =COUNT(Y45:AC45)/5 -> 0.6 | AO45: =IF(AQ45>0,WEEKNUM(AQ45,1)&"-"&YEAR(AQ45),"") | AR45: =IF(AA45="","WAITING FOR PLAN",IF(AU45="","PERMITTING NOT STARTED",IF(BR45>=100%,"RFE","ON GOING PERMITTING"))) -> PERMITTING NOT STARTED | BR45: =IFERROR((COUNT(BD45)*40%)+(COUNT(BL45)*20%)+(COUNT(BH45)*10%)+(COUNT(BP45)*10%)+(COUNT(AV45)*10%)+(COUNT(AZ45)*10%),0) -> 0 | BS45: =IF(BT45>0,WEEKNUM(BT45,1)&"-"&YEAR(BT45),"") | BU45: =IF(BV45>0,WEEKNUM(BV45,1)&"-"&YEAR(BV45),"") | BW45: =IF(BX45>0,WEEKNUM(BX45,1)&"-"&YEAR(BX45),"") -> 11-1900 | BX45: =IF(CA45="",BV45+CD45,CA45+CD45) -> 76.96 | CB45: =IF(AI45<>0,CC45*0.25,0) -> 0 | CC45: 2 | CD45: =IF(R45=0,IFERROR(Q45/(CC45)/1.25,0),IFERROR(R45/(CC45)/1.25,0)) -> 76.96 | CH45: =IF(CA45="","NOT STARTED",IF(CA45<>"","ON GOING EXTRACTION",IF(CV45<>"","EXTRACTION COMPLETED"))) -> NOT STARTED | CI45: =IFERROR(CQ45/CM45,0) -> 0 | CM45: =AG45 -> 0 | CN45: =AI45 -> 0 | CR45: =CM45-CQ45 -> 0 | CU45: =CS45+CT45 -> 0
A46: 46419 | B46: NY RFE | C46: PART OF 233 | D46: GMM | E46: 14.622861 | F46: 121.05998 | G46: Quezon City | H46: Metropolitan Manila | I46: South QC | K46: NY RFE | M46: IRUP0043 | N46: Cubao Exchange | O46: Exchange-M | P46: =IF(OR(NOT(ISNUMBER(Q46)),Q46=0),"NO DATA",IF(Q46<10,"<10 TONNES",">=10 TONNES")) -> >=10 TONNES | Q46: 399.2 | S46: =IF(CH46="CANCELLED","CANCELLED",IF(CV46<>"","EXTRACTION DONE",IF(CH46="ON GOING EXTRACTION","ON GOING EXTRACTION",IF(AR46="RFE","READY FOR EXTRACTION",IF(AR46="ON GOING PERMITTING","ON GOING PERMITTING",IF(AC46<>"","DESIGN APPROVED",IF(AB46<>"","DESIGN SUBMITTED",IF(AA46<>"","DESIGN COMPLETED",IF(Z46<>"","ON GOING DESIGN",IF(Y46<>"","ON GOING SURVEY","NOT STARTED")))))))))) -> DESIGN SUBMITTED | T46: =IFERROR((AN46*33%)+(BR46*27%)+(CI46*40%),0) -> 0.264 | X46: =IF(AD46>0,"DESIGN WITH CONCERN",IF(AC46>0,"DESIGN APPROVED",IF(AB46>0,"DESIGN FOR APPROVAL",IF(AA46>0,"DESIGN FOR SUBMISSION",IF(Z46>0,"ON GOING DESIGN",IF(Y46>0,"ON GOING SURVEY","FOR SURVEY")))))) -> DESIGN FOR APPROVAL | Y46: 46307 | Z46: 46308 | AA46: 46312 | AB46: 46323 | AF46: =IF(AA46-Y46<0,0,AA46-Y46) -> 5 | AG46: =AH46+AI46 -> 298 | AH46: 105 | AI46: 193 | AJ46: 159 | AK46: 34 | AN46: =COUNT(Y46:AC46)/5 -> 0.8 | AO46: =IF(AQ46>0,WEEKNUM(AQ46,1)&"-"&YEAR(AQ46),"") | AR46: =IF(AA46="","WAITING FOR PLAN",IF(AU46="","PERMITTING NOT STARTED",IF(BR46>=100%,"RFE","ON GOING PERMITTING"))) -> PERMITTING NOT STARTED | BR46: =IFERROR((COUNT(BD46)*40%)+(COUNT(BL46)*20%)+(COUNT(BH46)*10%)+(COUNT(BP46)*10%)+(COUNT(AV46)*10%)+(COUNT(AZ46)*10%),0) -> 0 | BS46: =IF(BT46>0,WEEKNUM(BT46,1)&"-"&YEAR(BT46),"") | BU46: =IF(BV46>0,WEEKNUM(BV46,1)&"-"&YEAR(BV46),"") | BW46: =IF(BX46>0,WEEKNUM(BX46,1)&"-"&YEAR(BX46),"") -> 23-1900 | BX46: =IF(CA46="",BV46+CD46,CA46+CD46) -> 159.68 | CB46: =IF(AI46<>0,CC46*0.25,0) -> 0.5 | CC46: 2 | CD46: =IF(R46=0,IFERROR(Q46/(CC46)/1.25,0),IFERROR(R46/(CC46)/1.25,0)) -> 159.68 | CH46: =IF(CA46="","NOT STARTED",IF(CA46<>"","ON GOING EXTRACTION",IF(CV46<>"","EXTRACTION COMPLETED"))) -> NOT STARTED | CI46: =IFERROR(CQ46/CM46,0) -> 0 | CM46: =AG46 -> 298 | CN46: =AI46 -> 193 | CR46: =CM46-CQ46 -> 298 | CU46: =CS46+CT46 -> 0
A47: 46419 | B47: NY RFE | C47: PART OF 233 | D47: GMM | E47: 14.399132 | F47: 121.04414 | G47: Muntinlupa City | H47: Metropolitan Manila | I47: Alabang-Las Pinas | K47: NY RFE | M47: IRUP0044 | N47: Muntinlupa Exchange | O47: Exchange-M | P47: =IF(OR(NOT(ISNUMBER(Q47)),Q47=0),"NO DATA",IF(Q47<10,"<10 TONNES",">=10 TONNES")) -> >=10 TONNES | Q47: 115.7 | S47: =IF(CH47="CANCELLED","CANCELLED",IF(CV47<>"","EXTRACTION DONE",IF(CH47="ON GOING EXTRACTION","ON GOING EXTRACTION",IF(AR47="RFE","READY FOR EXTRACTION",IF(AR47="ON GOING PERMITTING","ON GOING PERMITTING",IF(AC47<>"","DESIGN APPROVED",IF(AB47<>"","DESIGN SUBMITTED",IF(AA47<>"","DESIGN COMPLETED",IF(Z47<>"","ON GOING DESIGN",IF(Y47<>"","ON GOING SURVEY","NOT STARTED")))))))))) -> DESIGN COMPLETED | T47: =IFERROR((AN47*33%)+(BR47*27%)+(CI47*40%),0) -> 0.198 | X47: =IF(AD47>0,"DESIGN WITH CONCERN",IF(AC47>0,"DESIGN APPROVED",IF(AB47>0,"DESIGN FOR APPROVAL",IF(AA47>0,"DESIGN FOR SUBMISSION",IF(Z47>0,"ON GOING DESIGN",IF(Y47>0,"ON GOING SURVEY","FOR SURVEY")))))) -> DESIGN FOR SUBMISSION | Y47: 46311 | Z47: 46314 | AA47: 46321 | AF47: =IF(AA47-Y47<0,0,AA47-Y47) -> 10 | AG47: =AH47+AI47 -> 0 | AN47: =COUNT(Y47:AC47)/5 -> 0.6 | AO47: =IF(AQ47>0,WEEKNUM(AQ47,1)&"-"&YEAR(AQ47),"") | AR47: =IF(AA47="","WAITING FOR PLAN",IF(AU47="","PERMITTING NOT STARTED",IF(BR47>=100%,"RFE","ON GOING PERMITTING"))) -> PERMITTING NOT STARTED | BR47: =IFERROR((COUNT(BD47)*40%)+(COUNT(BL47)*20%)+(COUNT(BH47)*10%)+(COUNT(BP47)*10%)+(COUNT(AV47)*10%)+(COUNT(AZ47)*10%),0) -> 0 | BS47: =IF(BT47>0,WEEKNUM(BT47,1)&"-"&YEAR(BT47),"") | BU47: =IF(BV47>0,WEEKNUM(BV47,1)&"-"&YEAR(BV47),"") | BW47: =IF(BX47>0,WEEKNUM(BX47,1)&"-"&YEAR(BX47),"") -> 7-1900 | BX47: =IF(CA47="",BV47+CD47,CA47+CD47) -> 46.28 | CB47: =IF(AI47<>0,CC47*0.25,0) -> 0 | CC47: 2 | CD47: =IF(R47=0,IFERROR(Q47/(CC47)/1.25,0),IFERROR(R47/(CC47)/1.25,0)) -> 46.28 | CH47: =IF(CA47="","NOT STARTED",IF(CA47<>"","ON GOING EXTRACTION",IF(CV47<>"","EXTRACTION COMPLETED"))) -> NOT STARTED | CI47: =IFERROR(CQ47/CM47,0) -> 0 | CM47: =AG47 -> 0 | CN47: =AI47 -> 0 | CR47: =CM47-CQ47 -> 0 | CU47: =CS47+CT47 -> 0
A48: 46419 | B48: NY RFE | C48: PART OF 233 | D48: GMM | E48: 14.48506 | F48: 121.04123 | G48: Parañaque City | H48: Metropolitan Manila | I48: Pasay-Paranaque | K48: NY RFE | M48: IRUP0045 | N48: North Paranaque Exchange | O48: Exchange-L | P48: =IF(OR(NOT(ISNUMBER(Q48)),Q48=0),"NO DATA",IF(Q48<10,"<10 TONNES",">=10 TONNES")) -> >=10 TONNES | Q48: 445.2 | S48: =IF(CH48="CANCELLED","CANCELLED",IF(CV48<>"","EXTRACTION DONE",IF(CH48="ON GOING EXTRACTION","ON GOING EXTRACTION",IF(AR48="RFE","READY FOR EXTRACTION",IF(AR48="ON GOING PERMITTING","ON GOING PERMITTING",IF(AC48<>"","DESIGN APPROVED",IF(AB48<>"","DESIGN SUBMITTED",IF(AA48<>"","DESIGN COMPLETED",IF(Z48<>"","ON GOING DESIGN",IF(Y48<>"","ON GOING SURVEY","NOT STARTED")))))))))) -> ON GOING DESIGN | T48: =IFERROR((AN48*33%)+(BR48*27%)+(CI48*40%),0) -> 0.132 | X48: =IF(AD48>0,"DESIGN WITH CONCERN",IF(AC48>0,"DESIGN APPROVED",IF(AB48>0,"DESIGN FOR APPROVAL",IF(AA48>0,"DESIGN FOR SUBMISSION",IF(Z48>0,"ON GOING DESIGN",IF(Y48>0,"ON GOING SURVEY","FOR SURVEY")))))) -> ON GOING DESIGN | Y48: 46312 | Z48: 46316 | AF48: =IF(AA48-Y48<0,0,AA48-Y48) -> 0 | AG48: =AH48+AI48 -> 59 | AH48: 35 | AI48: 24 | AJ48: 21 | AK48: 3 | AN48: =COUNT(Y48:AC48)/5 -> 0.4 | AO48: =IF(AQ48>0,WEEKNUM(AQ48,1)&"-"&YEAR(AQ48),"") | AR48: =IF(AA48="","WAITING FOR PLAN",IF(AU48="","PERMITTING NOT STARTED",IF(BR48>=100%,"RFE","ON GOING PERMITTING"))) -> WAITING FOR PLAN | BR48: =IFERROR((COUNT(BD48)*40%)+(COUNT(BL48)*20%)+(COUNT(BH48)*10%)+(COUNT(BP48)*10%)+(COUNT(AV48)*10%)+(COUNT(AZ48)*10%),0) -> 0 | BS48: =IF(BT48>0,WEEKNUM(BT48,1)&"-"&YEAR(BT48),"") | BU48: =IF(BV48>0,WEEKNUM(BV48,1)&"-"&YEAR(BV48),"") | BW48: =IF(BX48>0,WEEKNUM(BX48,1)&"-"&YEAR(BX48),"") -> 26-1900 | BX48: =IF(CA48="",BV48+CD48,CA48+CD48) -> 178.08 | CB48: =IF(AI48<>0,CC48*0.25,0) -> 0.5 | CC48: 2 | CD48: =IF(R48=0,IFERROR(Q48/(CC48)/1.25,0),IFERROR(R48/(CC48)/1.25,0)) -> 178.08 | CH48: =IF(CA48="","NOT STARTED",IF(CA48<>"","ON GOING EXTRACTION",IF(CV48<>"","EXTRACTION COMPLETED"))) -> NOT STARTED | CI48: =IFERROR(CQ48/CM48,0) -> 0 | CM48: =AG48 -> 59 | CN48: =AI48 -> 24 | CR48: =CM48-CQ48 -> 59 | CU48: =CS48+CT48 -> 0
A49: 46419 | B49: NY RFE | C49: PART OF 233 | D49: GMM | E49: 14.596905 | F49: 120.98935 | G49: Manila City | H49: Metropolitan Manila | I49: South Manila | K49: NY RFE | M49: IRUP0046 | N49: Quiapo Exchange | O49: Exchange-M | P49: =IF(OR(NOT(ISNUMBER(Q49)),Q49=0),"NO DATA",IF(Q49<10,"<10 TONNES",">=10 TONNES")) -> >=10 TONNES | Q49: 369 | S49: =IF(CH49="CANCELLED","CANCELLED",IF(CV49<>"","EXTRACTION DONE",IF(CH49="ON GOING EXTRACTION","ON GOING EXTRACTION",IF(AR49="RFE","READY FOR EXTRACTION",IF(AR49="ON GOING PERMITTING","ON GOING PERMITTING",IF(AC49<>"","DESIGN APPROVED",IF(AB49<>"","DESIGN SUBMITTED",IF(AA49<>"","DESIGN COMPLETED",IF(Z49<>"","ON GOING DESIGN",IF(Y49<>"","ON GOING SURVEY","NOT STARTED")))))))))) -> ON GOING SURVEY | T49: =IFERROR((AN49*33%)+(BR49*27%)+(CI49*40%),0) -> 0.066 | X49: =IF(AD49>0,"DESIGN WITH CONCERN",IF(AC49>0,"DESIGN APPROVED",IF(AB49>0,"DESIGN FOR APPROVAL",IF(AA49>0,"DESIGN FOR SUBMISSION",IF(Z49>0,"ON GOING DESIGN",IF(Y49>0,"ON GOING SURVEY","FOR SURVEY")))))) -> ON GOING SURVEY | Y49: 46321 | AF49: =IF(AA49-Y49<0,0,AA49-Y49) -> 0 | AG49: =AH49+AI49 -> 0 | AN49: =COUNT(Y49:AC49)/5 -> 0.2 | AO49: =IF(AQ49>0,WEEKNUM(AQ49,1)&"-"&YEAR(AQ49),"") | AR49: =IF(AA49="","WAITING FOR PLAN",IF(AU49="","PERMITTING NOT STARTED",IF(BR49>=100%,"RFE","ON GOING PERMITTING"))) -> WAITING FOR PLAN | BR49: =IFERROR((COUNT(BD49)*40%)+(COUNT(BL49)*20%)+(COUNT(BH49)*10%)+(COUNT(BP49)*10%)+(COUNT(AV49)*10%)+(COUNT(AZ49)*10%),0) -> 0 | BS49: =IF(BT49>0,WEEKNUM(BT49,1)&"-"&YEAR(BT49),"") | BU49: =IF(BV49>0,WEEKNUM(BV49,1)&"-"&YEAR(BV49),"") | BW49: =IF(BX49>0,WEEKNUM(BX49,1)&"-"&YEAR(BX49),"") -> 21-1900 | BX49: =IF(CA49="",BV49+CD49,CA49+CD49) -> 147.6 | CB49: =IF(AI49<>0,CC49*0.25,0) -> 0 | CC49: 2 | CD49: =IF(R49=0,IFERROR(Q49/(CC49)/1.25,0),IFERROR(R49/(CC49)/1.25,0)) -> 147.6 | CH49: =IF(CA49="","NOT STARTED",IF(CA49<>"","ON GOING EXTRACTION",IF(CV49<>"","EXTRACTION COMPLETED"))) -> NOT STARTED | CI49: =IFERROR(CQ49/CM49,0) -> 0 | CM49: =AG49 -> 0 | CN49: =AI49 -> 0 | CR49: =CM49-CQ49 -> 0 | CU49: =CS49+CT49 -> 0
